Workbook
Name \0: #REF!
Name \a: #REF!
Name \b: #REF!
Name \b1: [1]MEDIÇÃO!#REF!
Name \c: #REF!
Name \CC: #REF!
Name \D: #REF!
Name \e: #REF!
Name \f: #REF!
Name \i: #REF!
Name \j: #REF!
Name \l: #REF!
Name \M: #REF!
Name \M1: [1]MEDIÇÃO!#REF!
Name \M10: #REF!
Name \M11: #REF!
Name \M12: #REF!
Name \M13: #REF!
Name \M2: #REF!
Name \M3: #REF!
Name \M4: #REF!
Name \M5: #REF!
Name \M6: #REF!
Name \M7: #REF!
Name \M8: #REF!
Name \M9: #REF!
Name \MM: #REF!
Name \O: #REF!
Name \p: [2]DETAILS!#REF!
Name \PP: #REF!
Name \q: #REF!
Name \R: #REF!
Name \s: #REF!
Name \T: #REF!
Name \y: #REF!
Name \z: #REF!
Name __________CAB1: #REF!
Name __________LOC1: #REF!
Name _________ANT1202: [3]FaixasCrit!#REF!
Name _________ANT1203: [3]FaixasCrit!#REF!
Name _________CAB1: #REF!
Name _________LOC1: #REF!
Name _________LOC10: '[4]MEDIÇAO 1'!#REF!
Name _________LOC11: '[4]MEDIÇAO 1'!#REF!
Name _________LOC12: '[4]MEDIÇAO 1'!#REF!
Name _________LOC13: '[4]MEDIÇAO 1'!#REF!
Name _________LOC14: '[4]MEDIÇAO 1'!#REF!
Name _________LOC15: '[4]MEDIÇAO 1'!#REF!
Name _________LOC16: '[4]MEDIÇAO 1'!#REF!
Name _________LOC17: '[4]MEDIÇAO 1'!#REF!
Name _________LOC18: '[4]MEDIÇAO 1'!#REF!
Name _________LOC19: '[4]MEDIÇAO 1'!#REF!
Name _________LOC2: '[4]MEDIÇAO 1'!#REF!
Name _________LOC20: '[4]MEDIÇAO 1'!#REF!
Name _________LOC21: '[4]MEDIÇAO 1'!#REF!
Name _________LOC22: '[4]MEDIÇAO 1'!#REF!
Name _________LOC23: '[4]MEDIÇAO 1'!#REF!
Name _________LOC24: '[4]MEDIÇAO 1'!#REF!
Name _________LOC25: '[4]MEDIÇAO 1'!#REF!
Name _________LOC26: '[4]MEDIÇAO 1'!#REF!

Sheet Dashboard
B2: Dados Básicos do Projeto | C2: Cliente | D2: FRIGELAR | J2: Custos Serviços | K2: Grupo de Custo | L2: Valor | M2: % Custo | N2: % PV | R2: Venda | S2: Preço de Venda | Y2: Parâmetros de Mão de Obra Precificada
K3: Mão de Obra Indireta | L3: =Precificação!U4 -> 17160 | M3: =IFERROR(L3/$L$36,0) -> 0.016341739 | S3: Serviços | T3: =ROUND(L28*(1+D35),2) -> 1278817.6
C4: Projeto | D4: FRIGELAR_GERENCIAMENTO DE OBRA | K4: Mão de Obra Direta | L4: =Precificação!U91 -> 555080 | M4: =IFERROR(L4/$L$36,0) -> 0.52861145 | S4: Materiais para revenda | T4: =SUMIF(Tarefas!$AA$32:$AA$54,"Revenda",Tarefas!$AN$32:$AN$54) -> 0 | X4: =T9/X6-1 -> -0.27785842 | Y4: Venda M.O. | Z4: R$ Homem x mês | AA4: =IFERROR(T3/(SUMPRODUCT(Precificação!L6:L89,Precificação!M6:M89)+SUMPRODUCT(Precificação!L95:L587,Precificação!M95:M587)),0) -> 29290.372
K5: Mão de Obra Direta (rotina) | L5: =Precificação!U535 -> 0 | M5: =IFERROR(L5/$L$36,0) -> 0 | S5: Materiais de Aplicação | T5: =SUMIF(Tarefas!$AA$32:$AA$54,"Aplicação",Tarefas!$AN$32:$AN$54) -> 0 | X5: =X6-T9 -> 591128.24 | Z5: R$ HH Produtivo | AA5: =IFERROR(T3/AA14,0) -> 154.69468
C6: Unidade | D6: CABREÚVA | K6: Encargos Sociais - Mensalistas | L6: =Precificação!U589 -> 85085.251 | M6: =IFERROR(L6/$L$36,0) -> 0.081028028 | S6: Faturamento Direto | T6: =SUMIF(Tarefas!$AA$32:$AA$54,"FD",Tarefas!$AN$32:$AN$54) -> 0 | X6: 2127444 | Z6: R$ HH Total | AA6: =IFERROR(T3/AA16,0) -> 151.29324
K7: Encargos Sociais - Horistas | L7: =Precificação!U627 -> 0 | M7: =IFERROR(L7/$L$36,0) -> 0 | S7: Serviço Terceirizado | T7: =SUMIF(Tarefas!$AA$32:$AA$54,"Serviço",Tarefas!$AN$32:$AN$54) -> 257498.17
C8: Localidade | D8: Município | F8: UF | K8: Mobilização/ Integração de Mão de Obra | L8: =Precificação!U665 -> 0 | M8: =IFERROR(L8/$L$36,0) -> 0 | Y8: Horas Trabalhadas | Z8: Horas Normais MOI | AA8: =SUMPRODUCT(Precificação!$L$7:$L$89,Precificação!$M$7:$M$89)*Dashboard!$D$15 -> 185.856
D9: CABREÚVA | F9: SP | K9: Desmobilização de Mão de Obra | L9: =Precificação!U683 -> 0 | M9: =IFERROR(L9/$L$36,0) -> 0 | S9: Preço de Venda | T9: =SUM(T3:T7) -> 1536315.8 | Z9: Horas Extras MOI | AA9: =SUMPRODUCT(Precificação!$L$7:$L$89,Precificação!$M$7:$M$89,Precificação!$BM$7:$BM$89)+SUMPRODUCT(Precificação!$L$7:$L$89,Precificação!$M$7:$M$89,Precificação!$BR$7:$BR$89)+SUMPRODUCT(Precificação!$L$7:$L$89,Precificação!$M$7:$M$89,Precificação!$BW$7:$BW$89) -> 0
K10: Canteiro de Obras, Infraestrutura de Apoio e Alojamento | L10: =Precificação!U701 -> 0 | M10: =IFERROR(L10/$L$36,0) -> 0 | Q10: =T9/D13 -> 153631.58 | Z10: Horas Totais MOI | AA10: =AA8+AA9 -> 185.856
C11: Mês e ano de início | K11: Benefícios | L11: =Precificação!U815 -> 62455.76 | M11: =IFERROR(L11/$L$36,0) -> 0.059477607 | Q11: =T9 -> 1536315.8 | T11: 0
K12: Exames Médicos e Gestão da Saúde Ocupacional | L12: =Precificação!U845 -> 3915 | M12: =IFERROR(L12/$L$36,0) -> 0.0037283163 | S12: Preço por Mês | T12: =IFERROR(T9/$D$14,0) -> 153631.58 | Z12: Horas Normais MOD | AA12: =SUMPRODUCT(Precificação!$L$95:$L$587,Precificação!$M$95:$M$587)*Dashboard!$D$15 -> 8266.72
B13: Prazos | C13: Prazo do Contrato | D13: 10 | E13: meses | K13: EPI's - Equipamentos de Proteção Individual | L13: =Precificação!U857 -> 14142.384 | M13: =IFERROR(L13/$L$36,0) -> 0.013468015 | Z13: Horas Extras MOD | AA13: =SUMPRODUCT(Precificação!$L$95:$L$587,Precificação!$M$95:$M$587,Precificação!$BM$95:$BM$587)+SUMPRODUCT(Precificação!$L$95:$L$587,Precificação!$M$95:$M$587,Precificação!$BR$95:$BR$587)+SUMPRODUCT(Precificação!$L$95:$L$587,Precificação!$M$95:$M$587,Precificação!$BW$95:$BW$587) -> 0
C14: Prazo de Execução | D14: 10 | E14: meses | K14: EPC's - Equipamentos de Proteção Coletiva | L14: =Precificação!U922 -> 2464.5833 | M14: =IFERROR(L14/$L$36,0) -> 0.0023470616 | Z14: Horas Totais MOD | AA14: =AA12+AA13 -> 8266.72
C15: Carga horária mês | D15: =D16*D17 -> 193.6 | E15: horas | K15: Treinamentos | L15: =Precificação!U941 -> 0 | M15: =IFERROR(L15/$L$36,0) -> 0
C16: Dias trabalhados no mês | D16: 22 | E16: dias/mês | K16: Viagens e Hospedagem | L16: =Precificação!U967 -> 87000 | M16: =IFERROR(L16/$L$36,0) -> 0.082851474 | Z16: Horas Totais MO | AA16: =AA10+AA14 -> 8452.576
C17: Carga horária diária | D17: 8.8 | E17: horas/dia | K17: Equipamentos e Ferramentas | L17: =Precificação!U986 -> 2000 | M17: =IFERROR(L17/$L$36,0) -> 0.0019046316
K18: Equipamentos de Informática e Softwares | L18: =Precificação!U1191 -> 39989.467 | M18: =IFERROR(L18/$L$36,0) -> 0.038082601 | Y18: Relações de Mão de Obra | Z18: MOI (Máxima) | AA18: ='Cronog. e Histog.'!I851 -> 0.08
B19: Acordo Coletivo | C19: Tarifa Banco de Horas | D19: 0.5 | E19: % | K19: Veículos leves e Fretamento | L19: =Precificação!U1219 -> 0 | M19: =IFERROR(L19/$L$36,0) -> 0 | Z19: MOD (Máxima) | AA19: ='Cronog. e Histog.'!I691+'Cronog. e Histog.'!I748 -> 4.27
C20: Tarifa Hora Extra 1 | D20: 0.75 | E20: % | K20: Veículos e Equipamentos Pesados | L20: =Precificação!U1246 -> 0 | M20: =IFERROR(L20/$L$36,0) -> 0 | Z20: MO Total (Máxima) | AA20: =AA18+AA19 -> 4.35
C21: Tarifa Hora Extra 2 | D21: 1 | E21: % | K21: Materiais de Consumo | L21: =Precificação!U1378 -> 0 | M21: =IFERROR(L21/$L$36,0) -> 0
C22: Taxa de reajuste (dissídio) | D22: 0.06 | E22: % | K22: Materiais de Aplicação Gerais | L22: =Precificação!U1417 -> 0 | M22: =IFERROR(L22/$L$36,0) -> 0 | Z22: % MOI (Máxima) | AA22: =IFERROR(AA18/$AA$20,0) -> 0.018390805
C23: Carga horária base mensal | D23: 220 | E23: horas/mês | K23: Serviços Terceirizados | L23: =Precificação!U1427 -> 3929.4 | M23: =IFERROR(L23/$L$36,0) -> 0.0037420297 | Z23: % MOD (Máxima) | AA23: =IFERROR(AA19/$AA$20,0) -> 0.9816092
A24: Empreitada | B24: Faturamento Indireto | K24: Locações | L24: =Precificação!U1460 -> 0 | M24: =IFERROR(L24/$L$36,0) -> 0 | Q24: Faturamento Indireto | R24: Resultados e Análises | U24: %
B25: =IF(A24="Empreitada","Margem","Markup") -> Margem | C25: =IF(A24="Empreitada","Lucro","Taxa de Administração") -> Lucro | D25: 0.11 | E25: =SUM(D25:D28) -> 0.23 | K25: Mobilização e Desmobilização de Recursos | L25: =Precificação!U1474 -> 850 | M25: =IFERROR(L25/$L$36,0) -> 0.00080946842 | R25: Margem | S25: =IF(C25>0,C25,"") -> Lucro | T25: =IF(AND($Q$24=$B$24,$A$24="Empreitada"),D25*($T$9-$T$6),D25*(($T$9-$T$6)/(1+$D$35))) -> 168994.74 | U25: =IFERROR(T25/($T$9-$T$6),0) -> 0.11 | Z25: MOI/MOD (Média) | AA25: =IFERROR(SUM('Cronog. e Histog.'!K860:BR860)/SUM('Cronog. e Histog.'!K858:BR859),0) -> 0.022482436
C26: Overhead | D26: 0.1 | K26: Riscos e Contingências | L26: =Precificação!U1543 -> 0 | M26: =IFERROR(L26/$L$36,0) -> 0 | N26: =IFERROR(L26/$L$36,0) -> 0 | S26: =IF(C26>0,C26,"") -> Overhead | T26: =IF(AND($Q$24=$B$24,$A$24="Empreitada"),D26*($T$9-$T$6),D26*(($T$9-$T$6)/(1+$D$35))) -> 153631.58 | U26: =IFERROR(T26/($T$9-$T$6),0) -> 0.1
C27: Taxa de negociação | D27: 0.02 | K27: Outros Custos | L27: =Precificação!U1549 -> 0 | M27: =IFERROR(L27/$L$36,0) -> 0 | S27: =IF(C27>0,C27,"") -> Taxa de negociação | T27: =IF(AND($Q$24=$B$24,$A$24="Empreitada"),D27*($T$9-$T$6),D27*(($T$9-$T$6)/(1+$D$35))) -> 30726.316 | U27: =IFERROR(T27/($T$9-$T$6),0) -> 0.02
C28: Custo Financeiro | D28: 0 | K28: Custo Total - Serviços | L28: =SUM(L3:L27) -> 874071.84 | M28: =IFERROR(L28/$L$36,0) -> 0.83239242 | S28: =IF(C28>0,C28,"") -> Custo Financeiro | T28: =IF(AND($Q$24=$B$24,$A$24="Empreitada"),D28*($T$9-$T$6),D28*(($T$9-$T$6)/(1+$D$35))) -> 0 | U28: =IFERROR(T28/($T$9-$T$6),0) -> 0
R29: Valor Total - Margem | T29: =SUM(T25:T28) -> 353352.63 | U29: =SUM(U25:U28) -> 0.23
B30: Impostos (serviços) | C30: PIS | D30: 0.0065 | E30: =SUM(D30:D33) -> 0.0865 | J30: Custos Materiais/ Terceiros | K30: Materiais para revenda | L30: =SUMIF(Tarefas!$AA$32:$AA$54,"Revenda",Tarefas!$AC$32:$AC$54) -> 0 | M30: =IFERROR(L30/$L$36,0) -> 0
C31: COFINS | D31: 0.03 | K31: Materiais de Aplicação | L31: =SUMIF(Tarefas!$AA$32:$AA$54,"Aplicação",Tarefas!$AC$32:$AC$54) -> 0 | M31: =IFERROR(L31/$L$36,0) -> 0 | R31: Impostos (serviços) | S31: =IF(C30>0,C30,"") -> PIS | T31: =D30*($T$9-$T$6-$T$7) -> 8312.3145 | U31: =IFERROR(T31/$T$9,0) -> 0.0054105507
C32: ISSQN | D32: =VLOOKUP(D9,'APOIO Impostos'!L:O,2,0) -> 0.05 | K32: Faturamento Direto | L32: =SUMIF(Tarefas!$AA$32:$AA$54,"FD",Tarefas!$AC$32:$AC$54) -> 0 | M32: =IFERROR(L32/$L$36,0) -> 0 | S32: =IF(C31>0,C31,"") -> COFINS | T32: =D31*($T$9-$T$6-$T$7) -> 38364.529 | U32: =IFERROR(T32/$T$9,0) -> 0.024971773
C33: CPRB | K33: Serviço Terceirizado | L33: =SUMIF(Tarefas!$AA$32:$AA$54,"Serviço",Tarefas!$AC$32:$AC$54) -> 176000 | M33: =IFERROR(L33/$L$36,0) -> 0.16760758 | S33: =IF(C32>0,C32,"") -> ISSQN | T33: =D32*($T$9-$T$6-$T$7) -> 63940.881 | U33: =IFERROR(T33/$T$9,0) -> 0.041619621
K34: Custo Total - Materiais/ Terceiros | L34: =SUM(L30:L33) -> 176000 | M34: =IFERROR(L34/$L$36,0) -> 0.16760758 | S34: =IF(C33>0,C33,"") -> CPRB | T34: =D33*($T$9-$T$6-$T$7) -> 0 | U34: =IFERROR(T34/$T$9,0) -> 0
B35: BDI Multiplicador sobre o custo | D35: =IF(A24="Empreitada",(1/(1-E25-E30))-1,(1*(1+E25)/(1-E30))-1) -> 0.46305779 | S35: Impostos sobre Materiais | T35: =E30*($T$7) -> 22273.592
J36: Custo Total | L36: =L28+L34 -> 1050071.8 | R36: Valor Total - Impostos | T36: =SUM(T31:T35) -> 132891.32
A37: Empreitada | B37: Faturamento Direto | Q37: Faturamento Direto | R37: Resultados e Análises | U37: % | X37: A | Y37: Receita Total | Z37: =T9 -> 1536315.8 | AA37: =IFERROR(Z37/$Z$37,0) -> 1
B38: =IF(A37="Empreitada","Margem","Markup") -> Margem | C38: =IF(A37="Empreitada","Lucro","Taxa de Administração") -> Lucro | D38: =D25 -> 0.11 | E38: =SUM(D38:D41) -> 0.23 | R38: Margem | S38: =IF(C38>0,C38,"") -> Lucro | T38: =IF(AND($Q$37=$B$37,$A$37="Empreitada"),(D38/(1-$E$43)*($T$6))*(1-$E$43),D38*(($T$6)/(1+$D$48))) -> 0 | U38: =IF(AND($Q$37=$B$37,$A$37="Empreitada"),T38/($T$4),T38/(($T$4)/(1+$D$48))) -> #DIV/0! | X38: B | Y38: Impostos de Serviços | Z38: =T31+T32+T33 -> 110617.72 | AA38: =IFERROR(SUM(Z38:Z39)/$Z$37,0) -> 0.0865
C39: Overhead | D39: =D26 -> 0.1 | S39: =IF(C39>0,C39,"") -> Overhead | T39: =IF(AND($Q$37=$B$37,$A$37="Empreitada"),(D39/(1-$E$43)*($T$6))*(1-$E$43),D39*(($T$6)/(1+$D$48))) -> 0 | U39: =IF(AND($Q$37=$B$37,$A$37="Empreitada"),T39/($T$4),T39/(($T$4)/(1+$D$48))) -> #DIV/0! | X39: C | Y39: Impostos de Materiais | Z39: =T35+T49 -> 22273.592
C40: Taxa de negociação | D40: =D27 -> 0.02 | S40: =IF(C40>0,C40,"") -> Taxa de negociação | T40: =IF(AND($Q$37=$B$37,$A$37="Empreitada"),(D40/(1-$E$43)*($T$6))*(1-$E$43),D40*(($T$6)/(1+$D$48))) -> 0 | U40: =IF(AND($Q$37=$B$37,$A$37="Empreitada"),T40/($T$4),T40/(($T$4)/(1+$D$48))) -> #DIV/0! | X40: D | Y40: Custos de Serviços | Z40: =L28 -> 874071.84 | AA40: =IFERROR(SUM(Z40:Z41)/$Z$37,0) -> 0.6835
C41: Custo Financeiro | D41: =D28 -> 0 | S41: =IF(C41>0,C41,"") -> Custo Financeiro | T41: =IF(AND($Q$37=$B$37,$A$37="Empreitada"),(D41/(1-$E$43)*($T$6))*(1-$E$43),D41*(($T$6)/(1+$D$48))) -> 0 | U41: =IF(AND($Q$37=$B$37,$A$37="Empreitada"),T41/($T$4),T41/(($T$4)/(1+$D$48))) -> #DIV/0! | X41: E | Y41: Custos de Materiais | Z41: =Tarefas!AC28 -> 176000
R42: Valor Total - Margem | T42: =SUM(T38:T41) -> 0 | U42: =SUM(U38:U41) -> #DIV/0! | X42: F | Y42: Margem Bruta | Z42: =Z37-(Z38+Z39+Z40+Z41) -> 353352.63 | AA42: =IFERROR(Z42/$Z$37,0) -> 0.23
B43: Impostos (serviços) | C43: PIS | D43: 0.0165 | E43: =SUM(D43:D46) -> 0.1425 | X43: G | Y43: =S26 -> Overhead | Z43: =T26+T39 -> 153631.58 | AA43: =IFERROR(Z43/$Z$37,0) -> 0.1
C44: COFINS | D44: 0.076 | R44: Impostos (serviços) | S44: =IF(C43>0,C43,"") -> PIS | T44: =D43*($T$42/(1-$E$43)) -> 0 | U44: =IFERROR(T44/$T$9,0) -> 0 | X44: H | Y44: =S27 -> Taxa de negociação | Z44: =T27+T40 -> 30726.316 | AA44: =IFERROR(Z44/$Z$37,0) -> 0.02
C45: ISSQN | D45: =VLOOKUP(D9,'APOIO Impostos'!L:O,2,0) -> 0.05 | S45: =IF(C44>0,C44,"") -> COFINS | T45: =D44*($T$42/(1-$E$43)) -> 0 | U45: =IFERROR(T45/$T$9,0) -> 0 | X45: H | Y45: =S28 -> Custo Financeiro | Z45: =T28+T41 -> 0 | AA45: =IFERROR(Z45/$Z$37,0) -> 0
C46: CPRB | S46: =IF(C45>0,C45,"") -> ISSQN | T46: =D45*($T$42/(1-$E$43)) -> 0 | U46: =IFERROR(T46/$T$9,0) -> 0 | X46: I | Y46: Margem Líquida | Z46: =Z42-SUM(Z43:Z45) -> 168994.74 | AA46: =IFERROR(Z46/$Z$37,0) -> 0.11
S47: =IF(C46>0,C46,"") -> CPRB | T47: =D46*($T$42/(1-$E$43)) -> 0 | U47: =IFERROR(T47/$T$9,0) -> 0
B48: BDI Multiplicador sobre o custo | D48: =IF(A37="Empreitada",(1/(1-(E38/(1-E43))))-1,(1*(1+(E38/(1-E43))))-1) -> 0.36653386
R49: Valor Total - Impostos | T49: =SUM(T44:T48) -> 0

Sheet Gráficos
B2: Gráficos Técnicos
B4: Avanço Físico - Curva S
B5: 1 | C5: 2 | D5: 3 | E5: 4 | F5: 5 | G5: 6 | H5: 7 | I5: 8 | J5: 9 | K5: 10 | L5: 11 | M5: 12 | N5: 13 | O5: 14 | P5: 15 | Q5: 16 | R5: 17 | S5: 18 | T5: 19 | U5: 20 | V5: 21 | W5: 22 | X5: 23 | Y5: 24 | Z5: 25 | AA5: 26 | AB5: 27 | AC5: 28 | AD5: 29 | AE5: 30 | AF5: 31 | AG5: 32 | AH5: 33 | AI5: 34 | AJ5: 35 | AK5: 36 | AL5: 37 | AM5: 38 | AN5: 39 | AO5: 40 | AP5: 41 | AQ5: 42 | AR5: 43 | AS5: 44 | AT5: 45 | AU5: 46 | AV5: 47 | AW5: 48 | AX5: 49 | AY5: 50 | AZ5: 51 | BA5: 52 | BB5: 53 | BC5: 54 | BD5: 55 | BE5: 56 | BF5: 57 | BG5: 58 | BH5: 59 | BI5: 60
B6: =IF('Cronog. e Histog.'!K97>0,'Cronog. e Histog.'!K97,#N/A) -> 0.1 | C6: =IF('Cronog. e Histog.'!L97>0,'Cronog. e Histog.'!L97,#N/A) -> 0.1 | D6: =IF('Cronog. e Histog.'!M97>0,'Cronog. e Histog.'!M97,#N/A) -> 0.1 | E6: =IF('Cronog. e Histog.'!N97>0,'Cronog. e Histog.'!N97,#N/A) -> 0.1 | F6: =IF('Cronog. e Histog.'!O97>0,'Cronog. e Histog.'!O97,#N/A) -> 0.1 | G6: =IF('Cronog. e Histog.'!P97>0,'Cronog. e Histog.'!P97,#N/A) -> 0.1 | H6: =IF('Cronog. e Histog.'!Q97>0,'Cronog. e Histog.'!Q97,#N/A) -> 0.1 | I6: =IF('Cronog. e Histog.'!R97>0,'Cronog. e Histog.'!R97,#N/A) -> 0.1 | ... BI6: =IF('Cronog. e Histog.'!BR97>0,'Cronog. e Histog.'!BR97,#N/A) -> #N/A
B7: =IF('Cronog. e Histog.'!K98>0,'Cronog. e Histog.'!K98,#N/A) -> 0.1 | C7: =IF('Cronog. e Histog.'!L98>0,'Cronog. e Histog.'!L98,#N/A) -> 0.2 | D7: =IF('Cronog. e Histog.'!M98>0,'Cronog. e Histog.'!M98,#N/A) -> 0.3 | E7: =IF('Cronog. e Histog.'!N98>0,'Cronog. e Histog.'!N98,#N/A) -> 0.4 | F7: =IF('Cronog. e Histog.'!O98>0,'Cronog. e Histog.'!O98,#N/A) -> 0.5 | G7: =IF('Cronog. e Histog.'!P98>0,'Cronog. e Histog.'!P98,#N/A) -> 0.6 | H7: =IF('Cronog. e Histog.'!Q98>0,'Cronog. e Histog.'!Q98,#N/A) -> 0.7 | I7: =IF('Cronog. e Histog.'!R98>0,'Cronog. e Histog.'!R98,#N/A) -> 0.8 | ... BI7: =IF('Cronog. e Histog.'!BR98>0,'Cronog. e Histog.'!BR98,#N/A) -> #N/A
B25: Histograma de Mão de Obra Direta
B26: 1 | C26: 2 | D26: 3 | E26: 4 | F26: 5 | G26: 6 | H26: 7 | I26: 8 | J26: 9 | K26: 10 | L26: 11 | M26: 12 | N26: 13 | O26: 14 | P26: 15 | Q26: 16 | R26: 17 | S26: 18 | T26: 19 | U26: 20 | V26: 21 | W26: 22 | X26: 23 | Y26: 24 | Z26: 25 | AA26: 26 | AB26: 27 | AC26: 28 | AD26: 29 | AE26: 30 | AF26: 31 | AG26: 32 | AH26: 33 | AI26: 34 | AJ26: 35 | AK26: 36 | AL26: 37 | AM26: 38 | AN26: 39 | AO26: 40 | AP26: 41 | AQ26: 42 | AR26: 43 | AS26: 44 | AT26: 45 | AU26: 46 | AV26: 47 | AW26: 48 | AX26: 49 | AY26: 50 | AZ26: 51 | BA26: 52 | BB26: 53 | BC26: 54 | BD26: 55 | BE26: 56 | BF26: 57 | BG26: 58 | BH26: 59 | BI26: 60
B27: =B69 -> 8.54 | C27: =C69 -> 8.54 | D27: =D69 -> 8.54 | E27: =E69 -> 8.54 | F27: =F69 -> 8.54 | G27: =G69 -> 8.54 | H27: =H69 -> 8.54 | I27: =I69 -> 8.54 | ... BI27: =BI69 -> #N/A
B46: Histograma de Mão de Obra Indireta
B47: 1 | C47: 2 | D47: 3 | E47: 4 | F47: 5 | G47: 6 | H47: 7 | I47: 8 | J47: 9 | K47: 10 | L47: 11 | M47: 12 | N47: 13 | O47: 14 | P47: 15 | Q47: 16 | R47: 17 | S47: 18 | T47: 19 | U47: 20 | V47: 21 | W47: 22 | X47: 23 | Y47: 24 | Z47: 25 | AA47: 26 | AB47: 27 | AC47: 28 | AD47: 29 | AE47: 30 | AF47: 31 | AG47: 32 | AH47: 33 | AI47: 34 | AJ47: 35 | AK47: 36 | AL47: 37 | AM47: 38 | AN47: 39 | AO47: 40 | AP47: 41 | AQ47: 42 | AR47: 43 | AS47: 44 | AT47: 45 | AU47: 46 | AV47: 47 | AW47: 48 | AX47: 49 | AY47: 50 | AZ47: 51 | BA47: 52 | BB47: 53 | BC47: 54 | BD47: 55 | BE47: 56 | BF47: 57 | BG47: 58 | BH47: 59 | BI47: 60
B48: =B70 -> 0.08 | C48: =C70 -> 0.08 | D48: =D70 -> 0.08 | E48: =E70 -> 0.08 | F48: =F70 -> 0.08 | G48: =G70 -> 0.08 | H48: =H70 -> 0.08 | I48: =I70 -> 0.08 | ... BI48: =BI70 -> #N/A
B67: Histograma de Mão de Obra
B68: 1 | C68: 2 | D68: 3 | E68: 4 | F68: 5 | G68: 6 | H68: 7 | I68: 8 | J68: 9 | K68: 10 | L68: 11 | M68: 12 | N68: 13 | O68: 14 | P68: 15 | Q68: 16 | R68: 17 | S68: 18 | T68: 19 | U68: 20 | V68: 21 | W68: 22 | X68: 23 | Y68: 24 | Z68: 25 | AA68: 26 | AB68: 27 | AC68: 28 | AD68: 29 | AE68: 30 | AF68: 31 | AG68: 32 | AH68: 33 | AI68: 34 | AJ68: 35 | AK68: 36 | AL68: 37 | AM68: 38 | AN68: 39 | AO68: 40 | AP68: 41 | AQ68: 42 | AR68: 43 | AS68: 44 | AT68: 45 | AU68: 46 | AV68: 47 | AW68: 48 | AX68: 49 | AY68: 50 | AZ68: 51 | BA68: 52 | BB68: 53 | BC68: 54 | BD68: 55 | BE68: 56 | BF68: 57 | BG68: 58 | BH68: 59 | BI68: 60
B69: =IF('Cronog. e Histog.'!K858+'Cronog. e Histog.'!K859>0,'Cronog. e Histog.'!K858+'Cronog. e Histog.'!K858,#N/A) -> 8.54 | C69: =IF('Cronog. e Histog.'!L858+'Cronog. e Histog.'!L859>0,'Cronog. e Histog.'!L858+'Cronog. e Histog.'!L858,#N/A) -> 8.54 | D69: =IF('Cronog. e Histog.'!M858+'Cronog. e Histog.'!M859>0,'Cronog. e Histog.'!M858+'Cronog. e Histog.'!M858,#N/A) -> 8.54 | E69: =IF('Cronog. e Histog.'!N858+'Cronog. e Histog.'!N859>0,'Cronog. e Histog.'!N858+'Cronog. e Histog.'!N858,#N/A) -> 8.54 | F69: =IF('Cronog. e Histog.'!O858+'Cronog. e Histog.'!O859>0,'Cronog. e Histog.'!O858+'Cronog. e Histog.'!O858,#N/A) -> 8.54 | G69: =IF('Cronog. e Histog.'!P858+'Cronog. e Histog.'!P859>0,'Cronog. e Histog.'!P858+'Cronog. e Histog.'!P858,#N/A) -> 8.54 | H69: =IF('Cronog. e Histog.'!Q858+'Cronog. e Histog.'!Q859>0,'Cronog. e Histog.'!Q858+'Cronog. e Histog.'!Q858,#N/A) -> 8.54 | I69: =IF('Cronog. e Histog.'!R858+'Cronog. e Histog.'!R859>0,'Cronog. e Histog.'!R858+'Cronog. e Histog.'!R858,#N/A) -> 8.54 | ... BI69: =IF('Cronog. e Histog.'!BR858+'Cronog. e Histog.'!BR859>0,'Cronog. e Histog.'!BR858+'Cronog. e Histog.'!BR858,#N/A) -> #N/A
B70: =IF('Cronog. e Histog.'!K860>0,'Cronog. e Histog.'!K860,#N/A) -> 0.08 | C70: =IF('Cronog. e Histog.'!L860>0,'Cronog. e Histog.'!L860,#N/A) -> 0.08 | D70: =IF('Cronog. e Histog.'!M860>0,'Cronog. e Histog.'!M860,#N/A) -> 0.08 | E70: =IF('Cronog. e Histog.'!N860>0,'Cronog. e Histog.'!N860,#N/A) -> 0.08 | F70: =IF('Cronog. e Histog.'!O860>0,'Cronog. e Histog.'!O860,#N/A) -> 0.08 | G70: =IF('Cronog. e Histog.'!P860>0,'Cronog. e Histog.'!P860,#N/A) -> 0.08 | H70: =IF('Cronog. e Histog.'!Q860>0,'Cronog. e Histog.'!Q860,#N/A) -> 0.08 | I70: =IF('Cronog. e Histog.'!R860>0,'Cronog. e Histog.'!R860,#N/A) -> 0.08 | ... BI70: =IF('Cronog. e Histog.'!BR860>0,'Cronog. e Histog.'!BR860,#N/A) -> #N/A
B71: ='Cronog. e Histog.'!K861 -> 4.35 | C71: ='Cronog. e Histog.'!L861 -> 4.35 | D71: ='Cronog. e Histog.'!M861 -> 4.35 | E71: ='Cronog. e Histog.'!N861 -> 4.35 | F71: ='Cronog. e Histog.'!O861 -> 4.35 | G71: ='Cronog. e Histog.'!P861 -> 4.35 | H71: ='Cronog. e Histog.'!Q861 -> 4.35 | I71: ='Cronog. e Histog.'!R861 -> 4.35 | ... BI71: ='Cronog. e Histog.'!BR861 -> 0
B90: Gráficos de Custos e Resultados
B92: Custos
B93: =Dashboard!K3 -> Mão de Obra Indireta | C93: =IF(Dashboard!L3>0,Dashboard!L3,#N/A) -> 17160
B94: =Dashboard!K5 -> Mão de Obra Direta (rotina) | C94: =IF(Dashboard!L5>0,Dashboard!L5,#N/A) -> #N/A
B95: =Dashboard!K7 -> Encargos Sociais - Horistas | C95: =IF(Dashboard!L7>0,Dashboard!L7,#N/A) -> #N/A
B96: =Dashboard!K8 -> Mobilização/ Integração de Mão de Obra | C96: =IF(Dashboard!L8>0,Dashboard!L8,#N/A) -> #N/A
B97: =Dashboard!K9 -> Desmobilização de Mão de Obra | C97: =IF(Dashboard!L9>0,Dashboard!L9,#N/A) -> #N/A
B98: =Dashboard!K10 -> Canteiro de Obras, Infraestrutura de Apoio e Alojamento | C98: =IF(Dashboard!L10>0,Dashboard!L10,#N/A) -> #N/A
B99: =Dashboard!K11 -> Benefícios | C99: =IF(Dashboard!L11>0,Dashboard!L11,#N/A) -> 62455.76
B100: =Dashboard!K12 -> Exames Médicos e Gestão da Saúde Ocupacional | C100: =IF(Dashboard!L12>0,Dashboard!L12,#N/A) -> 3915
B101: =Dashboard!K13 -> EPI's - Equipamentos de Proteção Individual | C101: =IF(Dashboard!L13>0,Dashboard!L13,#N/A) -> 14142.384
B102: =Dashboard!K14 -> EPC's - Equipamentos de Proteção Coletiva | C102: =IF(Dashboard!L14>0,Dashboard!L14,#N/A) -> 2464.5833
B103: =Dashboard!K15 -> Treinamentos | C103: =IF(Dashboard!L15>0,Dashboard!L15,#N/A) -> #N/A
B104: =Dashboard!K16 -> Viagens e Hospedagem | C104: =IF(Dashboard!L16>0,Dashboard!L16,#N/A) -> 87000
B105: =Dashboard!K17 -> Equipamentos e Ferramentas | C105: =IF(Dashboard!L17>0,Dashboard!L17,#N/A) -> 2000
B106: =Dashboard!K18 -> Equipamentos de Informática e Softwares | C106: =IF(Dashboard!L18>0,Dashboard!L18,#N/A) -> 39989.467
B107: =Dashboard!K19 -> Veículos leves e Fretamento | C107: =IF(Dashboard!L19>0,Dashboard!L19,#N/A) -> #N/A
B108: =Dashboard!K21 -> Materiais de Consumo | C108: =IF(Dashboard!L21>0,Dashboard!L21,#N/A) -> #N/A
B109: =Dashboard!K22 -> Materiais de Aplicação Gerais | C109: =IF(Dashboard!L22>0,Dashboard!L22,#N/A) -> #N/A
B110: =Dashboard!K23 -> Serviços Terceirizados | C110: =IF(Dashboard!L23>0,Dashboard!L23,#N/A) -> 3929.4
B111: =Dashboard!K24 -> Locações | C111: =IF(Dashboard!L24>0,Dashboard!L24,#N/A) -> #N/A
B112: =Dashboard!K25 -> Mobilização e Desmobilização de Recursos | C112: =IF(Dashboard!L25>0,Dashboard!L25,#N/A) -> 850
B113: =Dashboard!K26 -> Riscos e Contingências | C113: =IF(Dashboard!L26>0,Dashboard!L26,#N/A) -> #N/A
B114: =Dashboard!K27 -> Outros Custos | C114: =IF(Dashboard!L27>0,Dashboard!L27,#N/A) -> #N/A
B115: Materiais | C115: =IF(Dashboard!L32>0,Dashboard!L32,#N/A) -> #N/A
B117: Resultado | T117: Peso de Custo - Serviços e Materiais | AL117: Impostos
B118: =Dashboard!S25 -> Lucro | C118: =IF(Dashboard!T25>0,Dashboard!T25,#N/A) -> 168994.74 | T118: =Dashboard!S3 -> Serviços | U118: =IF(Dashboard!L28>0,Dashboard!L28/(Dashboard!#REF!),#N/A) -> #REF! | AL118: =Dashboard!S31 -> PIS | AM118: =IF(Dashboard!T31>0,Dashboard!T31,#N/A) -> 8312.3145
B119: =Dashboard!S26 -> Overhead | C119: =IF(Dashboard!T26>0,Dashboard!T26,#N/A) -> 153631.58 | T119: =Dashboard!S4 -> Materiais para revenda | U119: =IF(Dashboard!L32>0,Dashboard!L32/(Dashboard!#REF!),#N/A) -> #N/A | AL119: =Dashboard!S32 -> COFINS | AM119: =IF(Dashboard!T32>0,Dashboard!T32,#N/A) -> 38364.529
B120: =Dashboard!S27 -> Taxa de negociação | C120: =IF(Dashboard!T27>0,Dashboard!T27,#N/A) -> 30726.316 | AL120: =Dashboard!S33 -> ISSQN | AM120: =IF(Dashboard!T33>0,Dashboard!T33,#N/A) -> 63940.881
B121: =Dashboard!S28 -> Custo Financeiro | C121: =IF(Dashboard!T28>0,Dashboard!T28,#N/A) -> #N/A | AL121: =Dashboard!S34 -> CPRB | AM121: =IF(Dashboard!T34>0,Dashboard!T34,#N/A) -> #N/A
AL122: =Dashboard!S35 -> Impostos sobre Materiais | AM122: =IF(Dashboard!T35>0,Dashboard!T35,#N/A) -> 22273.592
B140: Gráficos Comerciais
B142: Evolução de Faturamento
C143: 1 | D143: 2 | E143: 3 | F143: 4 | G143: 5 | H143: 6 | I143: 7 | J143: 8 | K143: 9 | L143: 10 | M143: 11 | N143: 12 | O143: 13 | P143: 14 | Q143: 15 | R143: 16 | S143: 17 | T143: 18 | U143: 19 | V143: 20 | W143: 21 | X143: 22 | Y143: 23 | Z143: 24 | AA143: 25 | AB143: 26 | AC143: 27 | AD143: 28 | AE143: 29 | AF143: 30 | AG143: 31 | AH143: 32 | AI143: 33 | AJ143: 34 | AK143: 35 | AL143: 36 | AM143: 37 | AN143: 38 | AO143: 39 | AP143: 40 | AQ143: 41 | AR143: 42 | AS143: 43 | AT143: 44 | AU143: 45 | AV143: 46 | AW143: 47 | AX143: 48 | AY143: 49 | AZ143: 50 | BA143: 51 | BB143: 52 | BC143: 53 | BD143: 54 | BE143: 55 | BF143: 56 | BG143: 57 | BH143: 58 | BI143: 59 | BJ143: 60 | BK143: 61 | BL143: 62 | BM143: 63 | BN143: 64
B144: Faturamento mês (x 1000) | C144: =IF(#REF!>0,#REF!,#N/A)/1000 -> #REF! | D144: =IF(#REF!>0,#REF!,#N/A)/1000 -> #REF! | E144: =IF(#REF!>0,#REF!,#N/A)/1000 -> #REF! | F144: =IF(#REF!>0,#REF!,#N/A)/1000 -> #REF! | G144: =IF(#REF!>0,#REF!,#N/A)/1000 -> #REF! | H144: =IF(#REF!>0,#REF!,#N/A)/1000 -> #REF! | I144: =IF(#REF!>0,#REF!,#N/A)/1000 -> #REF! | J144: =IF(#REF!>0,#REF!,#N/A)/1000 -> #REF! | ... BN144: =IF(#REF!>0,#REF!,#N/A)/1000 -> #REF!
B163: Fluxo de Caixa Previsto
C164: 1 | D164: 2 | E164: 3 | F164: 4 | G164: 5 | H164: 6 | I164: 7 | J164: 8 | K164: 9 | L164: 10 | M164: 11 | N164: 12 | O164: 13 | P164: 14 | Q164: 15 | R164: 16 | S164: 17 | T164: 18 | U164: 19 | V164: 20 | W164: 21 | X164: 22 | Y164: 23 | Z164: 24 | AA164: 25 | AB164: 26 | AC164: 27 | AD164: 28 | AE164: 29 | AF164: 30 | AG164: 31 | AH164: 32 | AI164: 33 | AJ164: 34 | AK164: 35 | AL164: 36 | AM164: 37 | AN164: 38 | AO164: 39 | AP164: 40 | AQ164: 41 | AR164: 42 | AS164: 43 | AT164: 44 | AU164: 45 | AV164: 46 | AW164: 47 | AX164: 48 | AY164: 49 | AZ164: 50 | BA164: 51 | BB164: 52 | BC164: 53 | BD164: 54 | BE164: 55 | BF164: 56 | BG164: 57 | BH164: 58 | BI164: 59 | BJ164: 60 | BK164: 61 | BL164: 62 | BM164: 63 | BN164: 64
B165: Receita Bruta | C165: =IF(#REF!>0,#REF!,#N/A) -> #REF! | D165: =IF(#REF!>0,#REF!,#N/A) -> #REF! | E165: =IF(#REF!>0,#REF!,#N/A) -> #REF! | F165: =IF(#REF!>0,#REF!,#N/A) -> #REF! | G165: =IF(#REF!>0,#REF!,#N/A) -> #REF! | H165: =IF(#REF!>0,#REF!,#N/A) -> #REF! | I165: =IF(#REF!>0,#REF!,#N/A) -> #REF! | J165: =IF(#REF!>0,#REF!,#N/A) -> #REF! | ... BN165: =IF(#REF!>0,#REF!,#N/A) -> #REF!
B166: Impostos | C166: =IF(#REF!>0,#REF!,#N/A) -> #REF! | D166: =IF(#REF!>0,#REF!,#N/A) -> #REF! | E166: =IF(#REF!>0,#REF!,#N/A) -> #REF! | F166: =IF(#REF!>0,#REF!,#N/A) -> #REF! | G166: =IF(#REF!>0,#REF!,#N/A) -> #REF! | H166: =IF(#REF!>0,#REF!,#N/A) -> #REF! | I166: =IF(#REF!>0,#REF!,#N/A) -> #REF! | J166: =IF(#REF!>0,#REF!,#N/A) -> #REF! | ... BN166: =IF(#REF!>0,#REF!,#N/A) -> #REF!
B167: Custos | C167: =IF(#REF!>0,#REF!,#N/A) -> #REF! | D167: =IF(#REF!>0,#REF!,#N/A) -> #REF! | E167: =IF(#REF!>0,#REF!,#N/A) -> #REF! | F167: =IF(#REF!>0,#REF!,#N/A) -> #REF! | G167: =IF(#REF!>0,#REF!,#N/A) -> #REF! | H167: =IF(#REF!>0,#REF!,#N/A) -> #REF! | I167: =IF(#REF!>0,#REF!,#N/A) -> #REF! | J167: =IF(#REF!>0,#REF!,#N/A) -> #REF! | ... BN167: =IF(#REF!>0,#REF!,#N/A) -> #REF!
B168: Margem Bruta | C168: =IF(#REF!>0,#REF!,#N/A) -> #REF! | D168: =IF(#REF!>0,#REF!,#N/A) -> #REF! | E168: =IF(#REF!>0,#REF!,#N/A) -> #REF! | F168: =IF(#REF!>0,#REF!,#N/A) -> #REF! | G168: =IF(#REF!>0,#REF!,#N/A) -> #REF! | H168: =IF(#REF!>0,#REF!,#N/A) -> #REF! | I168: =IF(#REF!>0,#REF!,#N/A) -> #REF! | J168: =IF(#REF!>0,#REF!,#N/A) -> #REF! | ... BN168: =IF(#REF!>0,#REF!,#N/A) -> #REF!
B169: Custo Financeiro | C169: =IF(#REF!>0,#REF!,#N/A) -> #REF! | D169: =IF(#REF!>0,#REF!,#N/A) -> #REF! | E169: =IF(#REF!>0,#REF!,#N/A) -> #REF! | F169: =IF(#REF!>0,#REF!,#N/A) -> #REF! | G169: =IF(#REF!>0,#REF!,#N/A) -> #REF! | H169: =IF(#REF!>0,#REF!,#N/A) -> #REF! | I169: =IF(#REF!>0,#REF!,#N/A) -> #REF! | J169: =IF(#REF!>0,#REF!,#N/A) -> #REF! | ... BN169: =IF(#REF!>0,#REF!,#N/A) -> #REF!

Sheet HISTOGRAMA
D2: HISTOGRAMA
D3: TERRAPLENAGEM | G3: EXECUÇÃO DA OBRA
D4: PRÉ-OBRA
D5: 1 | E5: 2 | F5: 1 | G5: 2 | H5: 3 | I5: 4 | J5: 5 | K5: 6 | L5: 7 | M5: 11 | N5: 12 | O5: 13 | P5: 14 | Q5: 15 | R5: 16 | S5: 17 | T5: 18
B6: EQUIPE | C6: Prazo | D6: M1 | E6: M2 | F6: M3 | G6: M4 | H6: M5 | I6: M6 | J6: M7 | K6: M8 | L6: M9 | M6: M10 | N6: M11 | O6: M12 | P6: M13 | Q6: M14 | R6: M15 | S6: M16 | T6: M17
A7: CÓD | B7: GERENCIAMENTO DE OBRA
A8: Equipe_01 | B8: =IFERROR(INDEX(Tarefas!F:F,MATCH(A8,Tarefas!N:N,0)),"") -> Coordenador de Obras - Full time 100% | C8: =COUNTA(D8:T8) -> 10 | D8: 1 | E8: 1 | F8: 1 | G8: 1 | H8: 1 | I8: 1 | J8: 1 | K8: 1 | L8: 1 | M8: 1
A9: Equipe_02 | B9: =IFERROR(INDEX(Tarefas!F:F,MATCH(A9,Tarefas!N:N,0)),"") -> Engenheiro Pl. de Planejamento, Qualidade e Custos ( Supervisor) - Full time | C9: =COUNTA(D9:T9) -> 7 | G9: 1 | H9: 1 | I9: 1 | J9: 1 | K9: 1 | L9: 1 | M9: 1
A10: Equipe_10 | B10: =IFERROR(INDEX(Tarefas!F:F,MATCH(A10,Tarefas!N:N,0)),"") -> Engenheiro Pl. de Planejamento, Qualidade e Custos ( Supervisor) - Full time | C10: =COUNTA(D10:T10) -> 3 | D10: 0.2 | E10: 0.2 | F10: 0.2
A11: Equipe_03 | B11: =IFERROR(INDEX(Tarefas!F:F,MATCH(A11,Tarefas!N:N,0)),"") -> Engenheiro Jr. Qualidade ( Supervisor) - Instalações 25% | C11: =COUNTA(D11:T11) -> 5 | I11: 0.25 | J11: 0.25 | K11: 0.25 | L11: 0.25 | M11: 0.25
A12: Equipe_04 | B12: =IFERROR(INDEX(Tarefas!F:F,MATCH(A12,Tarefas!N:N,0)),"") -> Analista de Custos - An. Sr. 50% | C12: =COUNTA(D12:T12) -> 6 | H12: 0.5 | I12: 0.5 | J12: 0.5 | K12: 0.5 | L12: 0.5 | M12: 0.5
A13: Equipe_05 | B13: =IFERROR(INDEX(Tarefas!F:F,MATCH(A13,Tarefas!N:N,0)),"") -> Arquiteto Pl. ( Gestão de projetos) - Remoto ( Supervisor) - 100% | C13: =COUNTA(D13:T13) -> 6 | F13: 1 | G13: 1 | H13: 1 | I13: 1 | J13: 1 | K13: 1
A14: Equipe_20 | B14: =IFERROR(INDEX(Tarefas!F:F,MATCH(A14,Tarefas!N:N,0)),"") -> Arquiteto Pl. ( Gestão de projetos) - Remoto ( Supervisor) - 50% | C14: =COUNTA(D14:T14) -> 2 | L14: 0.5 | M14: 0.5
A15: Equipe_06 | B15: =IFERROR(INDEX(Tarefas!F:F,MATCH(A15,Tarefas!N:N,0)),"") -> Técnico de Segurança | C15: =COUNTA(D15:T15) -> 10 | D15: 1 | E15: 1 | F15: 1 | G15: 1 | H15: 1 | I15: 1 | J15: 1 | K15: 1 | L15: 1 | M15: 1
A16: Equipe_07 | B16: =IFERROR(INDEX(Tarefas!F:F,MATCH(A16,Tarefas!N:N,0)),"") -> Gerrente de Obras - 5% - Considerado equipe diluida nas linhas com 10 meses | C16: =COUNTA(D16:T16) -> 10 | D16: =1*0 -> 0 | E16: =1*0 -> 0 | F16: =1*0 -> 0 | G16: =1*0 -> 0 | H16: =1*0 -> 0 | I16: =1*0 -> 0 | J16: =1*0 -> 0 | K16: =1*0 -> 0 | ... M16: =1*0 -> 0
A17: Equipe_08 | B17: =IFERROR(INDEX(Tarefas!F:F,MATCH(A17,Tarefas!N:N,0)),"") -> Engenheiro de Segurança - 5% - Considerado equipe diluida nas linhas com 10 meses | C17: =COUNTA(D17:T17) -> 10 | D17: =1*0 -> 0 | E17: =1*0 -> 0 | F17: =1*0 -> 0 | G17: =1*0 -> 0 | H17: =1*0 -> 0 | I17: =1*0 -> 0 | J17: =1*0 -> 0 | K17: =1*0 -> 0 | ... M17: =1*0 -> 0
A18: Equipe_09 | B18: =IFERROR(INDEX(Tarefas!F:F,MATCH(A18,Tarefas!N:N,0)),"") -> Coordenador de Arquitetura - Excluso | C18: =COUNTA(D18:T18) -> 0
A19: Equipe_10 | B19: =IFERROR(INDEX(Tarefas!F:F,MATCH(A19,Tarefas!N:N,0)),"") -> Engenheiro Pl. de Planejamento, Qualidade e Custos ( Supervisor) - Full time | C19: =COUNTA(D19:T19) -> 0
A20: Equipe_11 | B20: =IFERROR(INDEX(Tarefas!F:F,MATCH(A20,Tarefas!N:N,0)),"") -> N/A | C20: =COUNTA(D20:T20) -> 0
A21: Equipe_12 | B21: =IFERROR(INDEX(Tarefas!F:F,MATCH(A21,Tarefas!N:N,0)),"") -> N/A | C21: =COUNTA(D21:T21) -> 0
A22: Equipe_13 | B22: =IFERROR(INDEX(Tarefas!F:F,MATCH(A22,Tarefas!N:N,0)),"") -> N/A | C22: =COUNTA(D22:T22) -> 0
A23: Equipe_14 | B23: =IFERROR(INDEX(Tarefas!F:F,MATCH(A23,Tarefas!N:N,0)),"") -> N/A | C23: =COUNTA(D23:T23) -> 0
A24: Equipe_15 | B24: =IFERROR(INDEX(Tarefas!F:F,MATCH(A24,Tarefas!N:N,0)),"") -> N/A | C24: =COUNTA(D24:T24) -> 0
A25: CÓD | B25: PRÉ-OBRA: APOIO À FASE DE CONCORRÊNCIA / SUPRIMENTOS
A26: Equipe_16 | B26: =IFERROR(INDEX(Tarefas!F:F,MATCH(A26,Tarefas!N:N,0)),"") -> Coordenador de Orçamentos - Part time - 50% mês | C26: =COUNTA(D26:T26) -> 2 | D26: 0.5 | E26: 0.5
A27: Equipe_17 | B27: =IFERROR(INDEX(Tarefas!F:F,MATCH(A27,Tarefas!N:N,0)),"") -> Arquiteto Pl. ( Gestão de projetos) - Remoto ( Supervisor) - 20% mês | C27: =COUNTA(D27:T27) -> 2 | D27: 0.2 | E27: 0.2
A28: Equipe_18 | B28: =IFERROR(INDEX(Tarefas!F:F,MATCH(A28,Tarefas!N:N,0)),"") -> Engenheiro Pl. de Planejamento, Qualidade e Custos ( Supervisor) - 10% - mês | C28: =COUNTA(D28:T28) -> 2 | D28: 0.1 | E28: 0.1
A29: Equipe_19 | B29: =IFERROR(INDEX(Tarefas!F:F,MATCH(A29,Tarefas!N:N,0)),"") -> Analista de Financeiro - An. Sr. 50% ( Análise financeira das empresas) | C29: =COUNTA(D29:T29) -> 1 | D29: 0.5
B30: TOTAL GERAL | D30: =SUM(D8:D29) -> 3.5 | E30: =SUM(E8:E29) -> 3 | F30: =SUM(F8:F29) -> 3.2 | G30: =SUM(G8:G29) -> 4 | H30: =SUM(H8:H29) -> 4.5 | I30: =SUM(I8:I29) -> 4.75 | J30: =SUM(J8:J29) -> 4.75 | K30: =SUM(K8:K29) -> 4.75 | ... T30: =SUM(T8:T29) -> 0
D32: CURVA DE DESEMBOLSO
D33: TERRAPLENAGEM | G33: EXECUÇÃO DA OBRA
D34: PRÉ-OBRA
D35: -3 | E35: -2 | F35: 1 | G35: 2 | H35: 3 | I35: 4 | J35: 5 | K35: 6 | L35: 7 | M35: 11 | N35: 12 | O35: 13 | P35: 14 | Q35: 12 | R35: 13 | S35: 14 | T35: 15
B36: EQUIPE (DEDICALÇAO INTEGRAL) | C36: VALOR TOTAL R$ | D36: M1 | E36: M2 | F36: M3 | G36: M4 | H36: M5 | I36: M6 | J36: M7 | K36: M8 | L36: M9 | M36: M10 | N36: M11 | O36: M12 | P36: M13 | Q36: M14 | R36: M15 | S36: M16 | T36: M17
A37: CÓD | B37: GERENCIAMENTO DE OBRA
A38: Equipe_01 | B38: =IFERROR(INDEX(Tarefas!F:F,MATCH(A38,Tarefas!N:N,0)),"") -> Coordenador de Obras - Full time 100% | C38: =ROUND(SUM(D38:T38),2) -> 509614.9 | D38: =ROUND(IF(D8>0,(INDEX(Tarefas!$AS:$AS,MATCH($A38,Tarefas!$N:$N,0))),0),2) -> 50961.49 | E38: =ROUND(IF(E8>0,(INDEX(Tarefas!$AS:$AS,MATCH($A38,Tarefas!$N:$N,0))),0),2) -> 50961.49 | F38: =ROUND(IF(F8>0,(INDEX(Tarefas!$AS:$AS,MATCH($A38,Tarefas!$N:$N,0))),0),2) -> 50961.49 | G38: =ROUND(IF(G8>0,(INDEX(Tarefas!$AS:$AS,MATCH($A38,Tarefas!$N:$N,0))),0),2) -> 50961.49 | H38: =ROUND(IF(H8>0,(INDEX(Tarefas!$AS:$AS,MATCH($A38,Tarefas!$N:$N,0))),0),2) -> 50961.49 | I38: =ROUND(IF(I8>0,(INDEX(Tarefas!$AS:$AS,MATCH($A38,Tarefas!$N:$N,0))),0),2) -> 50961.49 | J38: =ROUND(IF(J8>0,(INDEX(Tarefas!$AS:$AS,MATCH($A38,Tarefas!$N:$N,0))),0),2) -> 50961.49 | K38: =ROUND(IF(K8>0,(INDEX(Tarefas!$AS:$AS,MATCH($A38,Tarefas!$N:$N,0))),0),2) -> 50961.49 | ... T38: =ROUND(IF(T8>0,(INDEX(Tarefas!$AS:$AS,MATCH($A38,Tarefas!$N:$N,0))),0),2) -> 0
A39: Equipe_02 | B39: =IFERROR(INDEX(Tarefas!F:F,MATCH(A39,Tarefas!N:N,0)),"") -> Engenheiro Pl. de Planejamento, Qualidade e Custos ( Supervisor) - Full time | C39: =SUM(D39:T39) -> 278491.92 | D39: =ROUND(IF(D9>0,(INDEX(Tarefas!$AS:$AS,MATCH($A39,Tarefas!$N:$N,0))),0),2) -> 0 | E39: =ROUND(IF(E9>0,(INDEX(Tarefas!$AS:$AS,MATCH($A39,Tarefas!$N:$N,0))),0),2) -> 0 | F39: =ROUND(IF(F9>0,(INDEX(Tarefas!$AS:$AS,MATCH($A39,Tarefas!$N:$N,0))),0),2) -> 0 | G39: =ROUND(IF(G9>0,(INDEX(Tarefas!$AS:$AS,MATCH($A39,Tarefas!$N:$N,0))),0),2) -> 39784.56 | H39: =ROUND(IF(H9>0,(INDEX(Tarefas!$AS:$AS,MATCH($A39,Tarefas!$N:$N,0))),0),2) -> 39784.56 | I39: =ROUND(IF(I9>0,(INDEX(Tarefas!$AS:$AS,MATCH($A39,Tarefas!$N:$N,0))),0),2) -> 39784.56 | J39: =ROUND(IF(J9>0,(INDEX(Tarefas!$AS:$AS,MATCH($A39,Tarefas!$N:$N,0))),0),2) -> 39784.56 | K39: =ROUND(IF(K9>0,(INDEX(Tarefas!$AS:$AS,MATCH($A39,Tarefas!$N:$N,0))),0),2) -> 39784.56 | ... T39: =ROUND(IF(T9>0,(INDEX(Tarefas!$AS:$AS,MATCH($A39,Tarefas!$N:$N,0))),0),2) -> 0
A40: Equipe_10 | B40: =IFERROR(INDEX(Tarefas!F:F,MATCH(A40,Tarefas!N:N,0)),"") -> Engenheiro Pl. de Planejamento, Qualidade e Custos ( Supervisor) - Full time | C40: =SUM(D40:T40) -> 41747.04 | D40: =ROUND(IF(D10>0,(INDEX(Tarefas!$AS:$AS,MATCH($A40,Tarefas!$N:$N,0))),0),2) -> 13915.68 | E40: =ROUND(IF(E10>0,(INDEX(Tarefas!$AS:$AS,MATCH($A40,Tarefas!$N:$N,0))),0),2) -> 13915.68 | F40: =ROUND(IF(F10>0,(INDEX(Tarefas!$AS:$AS,MATCH($A40,Tarefas!$N:$N,0))),0),2) -> 13915.68 | G40: =ROUND(IF(G10>0,(INDEX(Tarefas!$AS:$AS,MATCH($A40,Tarefas!$N:$N,0))),0),2) -> 0 | H40: =ROUND(IF(H10>0,(INDEX(Tarefas!$AS:$AS,MATCH($A40,Tarefas!$N:$N,0))),0),2) -> 0 | I40: =ROUND(IF(I10>0,(INDEX(Tarefas!$AS:$AS,MATCH($A40,Tarefas!$N:$N,0))),0),2) -> 0 | J40: =ROUND(IF(J10>0,(INDEX(Tarefas!$AS:$AS,MATCH($A40,Tarefas!$N:$N,0))),0),2) -> 0 | K40: =ROUND(IF(K10>0,(INDEX(Tarefas!$AS:$AS,MATCH($A40,Tarefas!$N:$N,0))),0),2) -> 0 | ... T40: =ROUND(IF(T10>0,(INDEX(Tarefas!$AS:$AS,MATCH($A40,Tarefas!$N:$N,0))),0),2) -> 0
A41: Equipe_03 | B41: =IFERROR(INDEX(Tarefas!F:F,MATCH(A41,Tarefas!N:N,0)),"") -> Engenheiro Jr. Qualidade ( Supervisor) - Instalações 25% | C41: =SUM(D41:T41) -> 63875.8 | D41: =ROUND(IF(D11>0,(INDEX(Tarefas!$AS:$AS,MATCH($A41,Tarefas!$N:$N,0))),0),2) -> 0 | E41: =ROUND(IF(E11>0,(INDEX(Tarefas!$AS:$AS,MATCH($A41,Tarefas!$N:$N,0))),0),2) -> 0 | F41: =ROUND(IF(F11>0,(INDEX(Tarefas!$AS:$AS,MATCH($A41,Tarefas!$N:$N,0))),0),2) -> 0 | G41: =ROUND(IF(G11>0,(INDEX(Tarefas!$AS:$AS,MATCH($A41,Tarefas!$N:$N,0))),0),2) -> 0 | H41: =ROUND(IF(H11>0,(INDEX(Tarefas!$AS:$AS,MATCH($A41,Tarefas!$N:$N,0))),0),2) -> 0 | I41: =ROUND(IF(I11>0,(INDEX(Tarefas!$AS:$AS,MATCH($A41,Tarefas!$N:$N,0))),0),2) -> 12775.16 | J41: =ROUND(IF(J11>0,(INDEX(Tarefas!$AS:$AS,MATCH($A41,Tarefas!$N:$N,0))),0),2) -> 12775.16 | K41: =ROUND(IF(K11>0,(INDEX(Tarefas!$AS:$AS,MATCH($A41,Tarefas!$N:$N,0))),0),2) -> 12775.16 | ... T41: =ROUND(IF(T11>0,(INDEX(Tarefas!$AS:$AS,MATCH($A41,Tarefas!$N:$N,0))),0),2) -> 0
A42: Equipe_04 | B42: =IFERROR(INDEX(Tarefas!F:F,MATCH(A42,Tarefas!N:N,0)),"") -> Analista de Custos - An. Sr. 50% | C42: =SUM(D42:T42) -> 73229.46 | D42: =ROUND(IF(D12>0,(INDEX(Tarefas!$AS:$AS,MATCH($A42,Tarefas!$N:$N,0))),0),2) -> 0 | E42: =ROUND(IF(E12>0,(INDEX(Tarefas!$AS:$AS,MATCH($A42,Tarefas!$N:$N,0))),0),2) -> 0 | F42: =ROUND(IF(F12>0,(INDEX(Tarefas!$AS:$AS,MATCH($A42,Tarefas!$N:$N,0))),0),2) -> 0 | G42: =ROUND(IF(G12>0,(INDEX(Tarefas!$AS:$AS,MATCH($A42,Tarefas!$N:$N,0))),0),2) -> 0 | H42: =ROUND(IF(H12>0,(INDEX(Tarefas!$AS:$AS,MATCH($A42,Tarefas!$N:$N,0))),0),2) -> 12204.91 | I42: =ROUND(IF(I12>0,(INDEX(Tarefas!$AS:$AS,MATCH($A42,Tarefas!$N:$N,0))),0),2) -> 12204.91 | J42: =ROUND(IF(J12>0,(INDEX(Tarefas!$AS:$AS,MATCH($A42,Tarefas!$N:$N,0))),0),2) -> 12204.91 | K42: =ROUND(IF(K12>0,(INDEX(Tarefas!$AS:$AS,MATCH($A42,Tarefas!$N:$N,0))),0),2) -> 12204.91 | ... T42: =ROUND(IF(T12>0,(INDEX(Tarefas!$AS:$AS,MATCH($A42,Tarefas!$N:$N,0))),0),2) -> 0
A43: Equipe_05 | B43: =IFERROR(INDEX(Tarefas!F:F,MATCH(A43,Tarefas!N:N,0)),"") -> Arquiteto Pl. ( Gestão de projetos) - Remoto ( Supervisor) - 100% | C43: =SUM(D43:T43) -> 232322.4 | D43: =ROUND(IF(D13>0,(INDEX(Tarefas!$AS:$AS,MATCH($A43,Tarefas!$N:$N,0))),0),2) -> 0 | E43: =ROUND(IF(E13>0,(INDEX(Tarefas!$AS:$AS,MATCH($A43,Tarefas!$N:$N,0))),0),2) -> 0 | F43: =ROUND(IF(F13>0,(INDEX(Tarefas!$AS:$AS,MATCH($A43,Tarefas!$N:$N,0))),0),2) -> 38720.4 | G43: =ROUND(IF(G13>0,(INDEX(Tarefas!$AS:$AS,MATCH($A43,Tarefas!$N:$N,0))),0),2) -> 38720.4 | H43: =ROUND(IF(H13>0,(INDEX(Tarefas!$AS:$AS,MATCH($A43,Tarefas!$N:$N,0))),0),2) -> 38720.4 | I43: =ROUND(IF(I13>0,(INDEX(Tarefas!$AS:$AS,MATCH($A43,Tarefas!$N:$N,0))),0),2) -> 38720.4 | J43: =ROUND(IF(J13>0,(INDEX(Tarefas!$AS:$AS,MATCH($A43,Tarefas!$N:$N,0))),0),2) -> 38720.4 | K43: =ROUND(IF(K13>0,(INDEX(Tarefas!$AS:$AS,MATCH($A43,Tarefas!$N:$N,0))),0),2) -> 38720.4 | ... T43: =ROUND(IF(T13>0,(INDEX(Tarefas!$AS:$AS,MATCH($A43,Tarefas!$N:$N,0))),0),2) -> 0
A44: Equipe_20 | B44: =IFERROR(INDEX(Tarefas!F:F,MATCH(A44,Tarefas!N:N,0)),"") -> Arquiteto Pl. ( Gestão de projetos) - Remoto ( Supervisor) - 50% | C44: =SUM(D44:T44) -> 47183.66 | D44: =ROUND(IF(D14>0,(INDEX(Tarefas!$AS:$AS,MATCH($A44,Tarefas!$N:$N,0))),0),2) -> 0 | E44: =ROUND(IF(E14>0,(INDEX(Tarefas!$AS:$AS,MATCH($A44,Tarefas!$N:$N,0))),0),2) -> 0 | F44: =ROUND(IF(F14>0,(INDEX(Tarefas!$AS:$AS,MATCH($A44,Tarefas!$N:$N,0))),0),2) -> 0 | G44: =ROUND(IF(G14>0,(INDEX(Tarefas!$AS:$AS,MATCH($A44,Tarefas!$N:$N,0))),0),2) -> 0 | H44: =ROUND(IF(H14>0,(INDEX(Tarefas!$AS:$AS,MATCH($A44,Tarefas!$N:$N,0))),0),2) -> 0 | I44: =ROUND(IF(I14>0,(INDEX(Tarefas!$AS:$AS,MATCH($A44,Tarefas!$N:$N,0))),0),2) -> 0 | J44: =ROUND(IF(J14>0,(INDEX(Tarefas!$AS:$AS,MATCH($A44,Tarefas!$N:$N,0))),0),2) -> 0 | K44: =ROUND(IF(K14>0,(INDEX(Tarefas!$AS:$AS,MATCH($A44,Tarefas!$N:$N,0))),0),2) -> 0 | ... T44: =ROUND(IF(T14>0,(INDEX(Tarefas!$AS:$AS,MATCH($A44,Tarefas!$N:$N,0))),0),2) -> 0
A45: Equipe_06 | B45: =IFERROR(INDEX(Tarefas!F:F,MATCH(A45,Tarefas!N:N,0)),"") -> Técnico de Segurança | C45: =SUM(D45:T45) -> 212325.8 | D45: =ROUND(IF(D15>0,(INDEX(Tarefas!$AS:$AS,MATCH($A45,Tarefas!$N:$N,0))),0),2) -> 21232.58 | E45: =ROUND(IF(E15>0,(INDEX(Tarefas!$AS:$AS,MATCH($A45,Tarefas!$N:$N,0))),0),2) -> 21232.58 | F45: =ROUND(IF(F15>0,(INDEX(Tarefas!$AS:$AS,MATCH($A45,Tarefas!$N:$N,0))),0),2) -> 21232.58 | G45: =ROUND(IF(G15>0,(INDEX(Tarefas!$AS:$AS,MATCH($A45,Tarefas!$N:$N,0))),0),2) -> 21232.58 | H45: =ROUND(IF(H15>0,(INDEX(Tarefas!$AS:$AS,MATCH($A45,Tarefas!$N:$N,0))),0),2) -> 21232.58 | I45: =ROUND(IF(I15>0,(INDEX(Tarefas!$AS:$AS,MATCH($A45,Tarefas!$N:$N,0))),0),2) -> 21232.58 | J45: =ROUND(IF(J15>0,(INDEX(Tarefas!$AS:$AS,MATCH($A45,Tarefas!$N:$N,0))),0),2) -> 21232.58 | K45: =ROUND(IF(K15>0,(INDEX(Tarefas!$AS:$AS,MATCH($A45,Tarefas!$N:$N,0))),0),2) -> 21232.58 | ... T45: =ROUND(IF(T15>0,(INDEX(Tarefas!$AS:$AS,MATCH($A45,Tarefas!$N:$N,0))),0),2) -> 0
A46: Equipe_07 | B46: =IFERROR(INDEX(Tarefas!F:F,MATCH(A46,Tarefas!N:N,0)),"") -> Gerrente de Obras - 5% - Considerado equipe diluida nas linhas com 10 meses | C46: =SUM(D46:T46) -> 0 | D46: =ROUND(IF(D16>0,(INDEX(Tarefas!$AS:$AS,MATCH($A46,Tarefas!$N:$N,0))),0),2) -> 0 | E46: =ROUND(IF(E16>0,(INDEX(Tarefas!$AS:$AS,MATCH($A46,Tarefas!$N:$N,0))),0),2) -> 0 | F46: =ROUND(IF(F16>0,(INDEX(Tarefas!$AS:$AS,MATCH($A46,Tarefas!$N:$N,0))),0),2) -> 0 | G46: =ROUND(IF(G16>0,(INDEX(Tarefas!$AS:$AS,MATCH($A46,Tarefas!$N:$N,0))),0),2) -> 0 | H46: =ROUND(IF(H16>0,(INDEX(Tarefas!$AS:$AS,MATCH($A46,Tarefas!$N:$N,0))),0),2) -> 0 | I46: =ROUND(IF(I16>0,(INDEX(Tarefas!$AS:$AS,MATCH($A46,Tarefas!$N:$N,0))),0),2) -> 0 | J46: =ROUND(IF(J16>0,(INDEX(Tarefas!$AS:$AS,MATCH($A46,Tarefas!$N:$N,0))),0),2) -> 0 | K46: =ROUND(IF(K16>0,(INDEX(Tarefas!$AS:$AS,MATCH($A46,Tarefas!$N:$N,0))),0),2) -> 0 | ... T46: =ROUND(IF(T16>0,(INDEX(Tarefas!$AS:$AS,MATCH($A46,Tarefas!$N:$N,0))),0),2) -> 0
A47: Equipe_08 | B47: =IFERROR(INDEX(Tarefas!F:F,MATCH(A47,Tarefas!N:N,0)),"") -> Engenheiro de Segurança - 5% - Considerado equipe diluida nas linhas com 10 meses | C47: =SUM(D47:T47) -> 0 | D47: =ROUND(IF(D17>0,(INDEX(Tarefas!$AS:$AS,MATCH($A47,Tarefas!$N:$N,0))),0),2) -> 0 | E47: =ROUND(IF(E17>0,(INDEX(Tarefas!$AS:$AS,MATCH($A47,Tarefas!$N:$N,0))),0),2) -> 0 | F47: =ROUND(IF(F17>0,(INDEX(Tarefas!$AS:$AS,MATCH($A47,Tarefas!$N:$N,0))),0),2) -> 0 | G47: =ROUND(IF(G17>0,(INDEX(Tarefas!$AS:$AS,MATCH($A47,Tarefas!$N:$N,0))),0),2) -> 0 | H47: =ROUND(IF(H17>0,(INDEX(Tarefas!$AS:$AS,MATCH($A47,Tarefas!$N:$N,0))),0),2) -> 0 | I47: =ROUND(IF(I17>0,(INDEX(Tarefas!$AS:$AS,MATCH($A47,Tarefas!$N:$N,0))),0),2) -> 0 | J47: =ROUND(IF(J17>0,(INDEX(Tarefas!$AS:$AS,MATCH($A47,Tarefas!$N:$N,0))),0),2) -> 0 | K47: =ROUND(IF(K17>0,(INDEX(Tarefas!$AS:$AS,MATCH($A47,Tarefas!$N:$N,0))),0),2) -> 0 | ... T47: =ROUND(IF(T17>0,(INDEX(Tarefas!$AS:$AS,MATCH($A47,Tarefas!$N:$N,0))),0),2) -> 0
A48: Equipe_09 | B48: =IFERROR(INDEX(Tarefas!F:F,MATCH(A48,Tarefas!N:N,0)),"") -> Coordenador de Arquitetura - Excluso | C48: =SUM(D48:T48) -> 0 | D48: =ROUND(IF(D18>0,(INDEX(Tarefas!$AS:$AS,MATCH($A48,Tarefas!$N:$N,0))),0),2) -> 0 | E48: =ROUND(IF(E18>0,(INDEX(Tarefas!$AS:$AS,MATCH($A48,Tarefas!$N:$N,0))),0),2) -> 0 | F48: =ROUND(IF(F18>0,(INDEX(Tarefas!$AS:$AS,MATCH($A48,Tarefas!$N:$N,0))),0),2) -> 0 | G48: =ROUND(IF(G18>0,(INDEX(Tarefas!$AS:$AS,MATCH($A48,Tarefas!$N:$N,0))),0),2) -> 0 | H48: =ROUND(IF(H18>0,(INDEX(Tarefas!$AS:$AS,MATCH($A48,Tarefas!$N:$N,0))),0),2) -> 0 | I48: =ROUND(IF(I18>0,(INDEX(Tarefas!$AS:$AS,MATCH($A48,Tarefas!$N:$N,0))),0),2) -> 0 | J48: =ROUND(IF(J18>0,(INDEX(Tarefas!$AS:$AS,MATCH($A48,Tarefas!$N:$N,0))),0),2) -> 0 | K48: =ROUND(IF(K18>0,(INDEX(Tarefas!$AS:$AS,MATCH($A48,Tarefas!$N:$N,0))),0),2) -> 0 | ... T48: =ROUND(IF(T18>0,(INDEX(Tarefas!$AS:$AS,MATCH($A48,Tarefas!$N:$N,0))),0),2) -> 0
A49: Equipe_10 | B49: =IFERROR(INDEX(Tarefas!F:F,MATCH(A49,Tarefas!N:N,0)),"") -> Engenheiro Pl. de Planejamento, Qualidade e Custos ( Supervisor) - Full time | C49: =SUM(D49:T49) -> 0 | D49: =ROUND(IF(D19>0,(INDEX(Tarefas!$AS:$AS,MATCH($A49,Tarefas!$N:$N,0))),0),2) -> 0 | E49: =ROUND(IF(E19>0,(INDEX(Tarefas!$AS:$AS,MATCH($A49,Tarefas!$N:$N,0))),0),2) -> 0 | F49: =ROUND(IF(F19>0,(INDEX(Tarefas!$AS:$AS,MATCH($A49,Tarefas!$N:$N,0))),0),2) -> 0 | G49: =ROUND(IF(G19>0,(INDEX(Tarefas!$AS:$AS,MATCH($A49,Tarefas!$N:$N,0))),0),2) -> 0 | H49: =ROUND(IF(H19>0,(INDEX(Tarefas!$AS:$AS,MATCH($A49,Tarefas!$N:$N,0))),0),2) -> 0 | I49: =ROUND(IF(I19>0,(INDEX(Tarefas!$AS:$AS,MATCH($A49,Tarefas!$N:$N,0))),0),2) -> 0 | J49: =ROUND(IF(J19>0,(INDEX(Tarefas!$AS:$AS,MATCH($A49,Tarefas!$N:$N,0))),0),2) -> 0 | K49: =ROUND(IF(K19>0,(INDEX(Tarefas!$AS:$AS,MATCH($A49,Tarefas!$N:$N,0))),0),2) -> 0 | ... T49: =ROUND(IF(T19>0,(INDEX(Tarefas!$AS:$AS,MATCH($A49,Tarefas!$N:$N,0))),0),2) -> 0
A50: Equipe_11 | B50: =IFERROR(INDEX(Tarefas!F:F,MATCH(A50,Tarefas!N:N,0)),"") -> N/A | C50: =SUM(D50:T50) -> 0 | D50: =ROUND(IF(D20>0,(INDEX(Tarefas!$AS:$AS,MATCH($A50,Tarefas!$N:$N,0))),0),2) -> 0 | E50: =ROUND(IF(E20>0,(INDEX(Tarefas!$AS:$AS,MATCH($A50,Tarefas!$N:$N,0))),0),2) -> 0 | F50: =ROUND(IF(F20>0,(INDEX(Tarefas!$AS:$AS,MATCH($A50,Tarefas!$N:$N,0))),0),2) -> 0 | G50: =ROUND(IF(G20>0,(INDEX(Tarefas!$AS:$AS,MATCH($A50,Tarefas!$N:$N,0))),0),2) -> 0 | H50: =ROUND(IF(H20>0,(INDEX(Tarefas!$AS:$AS,MATCH($A50,Tarefas!$N:$N,0))),0),2) -> 0 | I50: =ROUND(IF(I20>0,(INDEX(Tarefas!$AS:$AS,MATCH($A50,Tarefas!$N:$N,0))),0),2) -> 0 | J50: =ROUND(IF(J20>0,(INDEX(Tarefas!$AS:$AS,MATCH($A50,Tarefas!$N:$N,0))),0),2) -> 0 | K50: =ROUND(IF(K20>0,(INDEX(Tarefas!$AS:$AS,MATCH($A50,Tarefas!$N:$N,0))),0),2) -> 0 | ... T50: =ROUND(IF(T20>0,(INDEX(Tarefas!$AS:$AS,MATCH($A50,Tarefas!$N:$N,0))),0),2) -> 0
... A54: Equipe_15 | B54: =IFERROR(INDEX(Tarefas!F:F,MATCH(A54,Tarefas!N:N,0)),"") -> N/A | C54: =SUM(D54:T54) -> 0 | D54: =ROUND(IF(D24>0,(INDEX(Tarefas!$AS:$AS,MATCH($A54,Tarefas!$N:$N,0))),0),2) -> 0 | E54: =ROUND(IF(E24>0,(INDEX(Tarefas!$AS:$AS,MATCH($A54,Tarefas!$N:$N,0))),0),2) -> 0 | F54: =ROUND(IF(F24>0,(INDEX(Tarefas!$AS:$AS,MATCH($A54,Tarefas!$N:$N,0))),0),2) -> 0 | G54: =ROUND(IF(G24>0,(INDEX(Tarefas!$AS:$AS,MATCH($A54,Tarefas!$N:$N,0))),0),2) -> 0 | H54: =ROUND(IF(H24>0,(INDEX(Tarefas!$AS:$AS,MATCH($A54,Tarefas!$N:$N,0))),0),2) -> 0 | I54: =ROUND(IF(I24>0,(INDEX(Tarefas!$AS:$AS,MATCH($A54,Tarefas!$N:$N,0))),0),2) -> 0 | J54: =ROUND(IF(J24>0,(INDEX(Tarefas!$AS:$AS,MATCH($A54,Tarefas!$N:$N,0))),0),2) -> 0 | K54: =ROUND(IF(K24>0,(INDEX(Tarefas!$AS:$AS,MATCH($A54,Tarefas!$N:$N,0))),0),2) -> 0 | ... T54: =ROUND(IF(T24>0,(INDEX(Tarefas!$AS:$AS,MATCH($A54,Tarefas!$N:$N,0))),0),2) -> 0
B55: TOTAL GERAL | C55: =SUM(C37:C54) -> 1458791 | D55: =SUM(D37:D54) -> 86109.75 | E55: =SUM(E37:E54) -> 86109.75 | F55: =SUM(F37:F54) -> 124830.15 | G55: =SUM(G37:G54) -> 150699.03 | H55: =SUM(H37:H54) -> 162903.94 | I55: =SUM(I37:I54) -> 175679.1 | J55: =SUM(J37:J54) -> 175679.1 | ... T55: =SUM(T37:T54) -> 0
A56: CÓD | B56: PRÉ-OBRA: APOIO À FASE DE CONCORRÊNCIA / SUPRIMENTOS
A57: Equipe_16 | B57: =IFERROR(INDEX(Tarefas!F:F,MATCH(A57,Tarefas!N:N,0)),"") -> Coordenador de Orçamentos - Part time - 50% mês | C57: =SUM(D57:T57) -> 46699.14 | D57: =ROUND(IF(D26>0,(INDEX(Tarefas!$AS:$AS,MATCH($A57,Tarefas!$N:$N,0))),0),2) -> 23349.57 | E57: =ROUND(IF(E26>0,(INDEX(Tarefas!$AS:$AS,MATCH($A57,Tarefas!$N:$N,0))),0),2) -> 23349.57 | F57: =ROUND(IF(F26>0,(INDEX(Tarefas!$AS:$AS,MATCH($A57,Tarefas!$N:$N,0))),0),2) -> 0 | G57: =ROUND(IF(G26>0,(INDEX(Tarefas!$AS:$AS,MATCH($A57,Tarefas!$N:$N,0))),0),2) -> 0 | H57: =ROUND(IF(H26>0,(INDEX(Tarefas!$AS:$AS,MATCH($A57,Tarefas!$N:$N,0))),0),2) -> 0 | I57: =ROUND(IF(I26>0,(INDEX(Tarefas!$AS:$AS,MATCH($A57,Tarefas!$N:$N,0))),0),2) -> 0 | J57: =ROUND(IF(J26>0,(INDEX(Tarefas!$AS:$AS,MATCH($A57,Tarefas!$N:$N,0))),0),2) -> 0 | K57: =ROUND(IF(K26>0,(INDEX(Tarefas!$AS:$AS,MATCH($A57,Tarefas!$N:$N,0))),0),2) -> 0 | ... T57: =ROUND(IF(T26>0,(INDEX(Tarefas!$AS:$AS,MATCH($A57,Tarefas!$N:$N,0))),0),2) -> 0
A58: Equipe_17 | B58: =IFERROR(INDEX(Tarefas!F:F,MATCH(A58,Tarefas!N:N,0)),"") -> Arquiteto Pl. ( Gestão de projetos) - Remoto ( Supervisor) - 20% mês | C58: =SUM(D58:T58) -> 12901.52 | D58: =ROUND(IF(D27>0,(INDEX(Tarefas!$AS:$AS,MATCH($A58,Tarefas!$N:$N,0))),0),2) -> 6450.76 | E58: =ROUND(IF(E27>0,(INDEX(Tarefas!$AS:$AS,MATCH($A58,Tarefas!$N:$N,0))),0),2) -> 6450.76 | F58: =ROUND(IF(F27>0,(INDEX(Tarefas!$AS:$AS,MATCH($A58,Tarefas!$N:$N,0))),0),2) -> 0 | G58: =ROUND(IF(G27>0,(INDEX(Tarefas!$AS:$AS,MATCH($A58,Tarefas!$N:$N,0))),0),2) -> 0 | H58: =ROUND(IF(H27>0,(INDEX(Tarefas!$AS:$AS,MATCH($A58,Tarefas!$N:$N,0))),0),2) -> 0 | I58: =ROUND(IF(I27>0,(INDEX(Tarefas!$AS:$AS,MATCH($A58,Tarefas!$N:$N,0))),0),2) -> 0 | J58: =ROUND(IF(J27>0,(INDEX(Tarefas!$AS:$AS,MATCH($A58,Tarefas!$N:$N,0))),0),2) -> 0 | K58: =ROUND(IF(K27>0,(INDEX(Tarefas!$AS:$AS,MATCH($A58,Tarefas!$N:$N,0))),0),2) -> 0 | ... T58: =ROUND(IF(T27>0,(INDEX(Tarefas!$AS:$AS,MATCH($A58,Tarefas!$N:$N,0))),0),2) -> 0
A59: Equipe_18 | B59: =IFERROR(INDEX(Tarefas!F:F,MATCH(A59,Tarefas!N:N,0)),"") -> Engenheiro Pl. de Planejamento, Qualidade e Custos ( Supervisor) - 10% - mês | C59: =SUM(D59:T59) -> 9376.88 | D59: =ROUND(IF(D28>0,(INDEX(Tarefas!$AS:$AS,MATCH($A59,Tarefas!$N:$N,0))),0),2) -> 4688.44 | E59: =ROUND(IF(E28>0,(INDEX(Tarefas!$AS:$AS,MATCH($A59,Tarefas!$N:$N,0))),0),2) -> 4688.44 | F59: =ROUND(IF(F28>0,(INDEX(Tarefas!$AS:$AS,MATCH($A59,Tarefas!$N:$N,0))),0),2) -> 0 | G59: =ROUND(IF(G28>0,(INDEX(Tarefas!$AS:$AS,MATCH($A59,Tarefas!$N:$N,0))),0),2) -> 0 | H59: =ROUND(IF(H28>0,(INDEX(Tarefas!$AS:$AS,MATCH($A59,Tarefas!$N:$N,0))),0),2) -> 0 | I59: =ROUND(IF(I28>0,(INDEX(Tarefas!$AS:$AS,MATCH($A59,Tarefas!$N:$N,0))),0),2) -> 0 | J59: =ROUND(IF(J28>0,(INDEX(Tarefas!$AS:$AS,MATCH($A59,Tarefas!$N:$N,0))),0),2) -> 0 | K59: =ROUND(IF(K28>0,(INDEX(Tarefas!$AS:$AS,MATCH($A59,Tarefas!$N:$N,0))),0),2) -> 0 | ... T59: =ROUND(IF(T28>0,(INDEX(Tarefas!$AS:$AS,MATCH($A59,Tarefas!$N:$N,0))),0),2) -> 0
A60: Equipe_19 | B60: =IFERROR(INDEX(Tarefas!F:F,MATCH(A60,Tarefas!N:N,0)),"") -> Analista de Financeiro - An. Sr. 50% ( Análise financeira das empresas) | C60: =SUM(D60:T60) -> 8547.26 | D60: =ROUND(IF(D29>0,(INDEX(Tarefas!$AS:$AS,MATCH($A60,Tarefas!$N:$N,0))),0),2) -> 8547.26 | E60: =ROUND(IF(E29>0,(INDEX(Tarefas!$AS:$AS,MATCH($A60,Tarefas!$N:$N,0))),0),2) -> 0 | F60: =ROUND(IF(F29>0,(INDEX(Tarefas!$AS:$AS,MATCH($A60,Tarefas!$N:$N,0))),0),2) -> 0 | G60: =ROUND(IF(G29>0,(INDEX(Tarefas!$AS:$AS,MATCH($A60,Tarefas!$N:$N,0))),0),2) -> 0 | H60: =ROUND(IF(H29>0,(INDEX(Tarefas!$AS:$AS,MATCH($A60,Tarefas!$N:$N,0))),0),2) -> 0 | I60: =ROUND(IF(I29>0,(INDEX(Tarefas!$AS:$AS,MATCH($A60,Tarefas!$N:$N,0))),0),2) -> 0 | J60: =ROUND(IF(J29>0,(INDEX(Tarefas!$AS:$AS,MATCH($A60,Tarefas!$N:$N,0))),0),2) -> 0 | K60: =ROUND(IF(K29>0,(INDEX(Tarefas!$AS:$AS,MATCH($A60,Tarefas!$N:$N,0))),0),2) -> 0 | ... T60: =ROUND(IF(T29>0,(INDEX(Tarefas!$AS:$AS,MATCH($A60,Tarefas!$N:$N,0))),0),2) -> 0
B61: TOTAL GERAL | C61: =SUM(C56:C60) -> 77524.8 | D61: =SUM(D56:D60) -> 43036.03 | E61: =SUM(E56:E60) -> 34488.77 | F61: =SUM(F56:F60) -> 0 | G61: =SUM(G56:G60) -> 0 | H61: =SUM(H56:H60) -> 0 | I61: =SUM(I56:I60) -> 0 | J61: =SUM(J56:J60) -> 0 | ... M61: =SUM(M56:M60) -> 0 | N61: =SUM(N38:N60) -> 0 | O61: =SUM(O38:O60) -> 0 | P61: =SUM(P38:P60) -> 0 | Q61: =SUM(Q38:Q60) -> 0 | R61: =SUM(R38:R60) -> 0 | S61: =SUM(S38:S60) -> 0 | T61: =SUM(T38:T60) -> 0
B62: TOTAL ACUMULADO | C62: =C61+C55 -> 1536315.8 | D62: =D61+D55 -> 129145.78 | E62: =D62+E61+E55 -> 249744.3 | F62: =E62+F61+F55 -> 374574.45 | G62: =F62+G61+G55 -> 525273.48 | H62: =G62+H61+H55 -> 688177.42 | I62: =H62+I61+I55 -> 863856.52 | J62: =I62+J61+J55 -> 1039535.6 | K62: =J62+K61+K55 -> 1215214.7 | L62: =K62+L61+L55 -> 1375765.2 | ... T62: =S62+T61+T55 -> 1536315.8
B64: Valor Da obra | C64: =150000000 -> 150000000
B65: % | C65: =C61/C64 -> 0.000516832
C70: Pré-Obra
C71: Terraplenagem
C72: Obra
C73: Instalação dos equipamentos

Sheet Tarefas
E2: Item | F2: Descrição da Equipe | G2: Sigla | H2: Disciplina | L2: Improd. por Equipe | O2: HH Total por equipe | S2: Custo Total por Equipe | T2: Custo da Hora por Disciplina | BT2: =HYPERLINK("#GER",BU2) -> GER. (OBRA/PROJ) | BU2: ='Base Salarial'!G5 -> GER. (OBRA/PROJ)
E3: 1 | F3: Equipe01 | G3: Equipe_01 | H3: PROJETO | L3: =IFERROR(_xlfn.XLOOKUP(G3,Improdutividade!$R$1:$AK$1,Improdutividade!$R$17:$AK$17),0) -> 0 | O3: =SUMIF($N$32:$N$54,G3,$O$32:$O$54) -> 1992.4667 | S3: =IFERROR(SUM(Precificação!U96:U115)/SUM(Precificação!$U$96:$U$533)*Precificação!$U$2,0) -> 308321.8 | T3: =IFERROR(S3/O3,0) -> 154.74377 | BT3: =HYPERLINK("#COORD.",BU3) -> COORD. | BU3: ='Base Salarial'!G7 -> COORD.
E4: 2 | F4: Equipe02 | G4: Equipe_02 | H4: PERMITS | L4: =IFERROR(_xlfn.XLOOKUP(G4,Improdutividade!$R$1:$AK$1,Improdutividade!$R$17:$AK$17),0) -> 0 | O4: =SUMIF($N$32:$N$54,G4,$O$32:$O$54) -> 1394.7267 | S4: =IFERROR(SUM(Precificação!U118:U137)/SUM(Precificação!$U$96:$U$533)*Precificação!$U$2,0) -> 162349.22 | T4: =IFERROR(S4/O4,0) -> 116.40218 | BT4: =HYPERLINK("#SUP.ESP",BU4) -> SUP.-ESP | BU4: ='Base Salarial'!G8 -> SUP.-ESP
E5: 3 | F5: Equipe03 | G5: Equipe_03 | H5: GERENCIMENTO | L5: =IFERROR(_xlfn.XLOOKUP(G5,Improdutividade!$R$1:$AK$1,Improdutividade!$R$17:$AK$17),0) -> 0 | O5: =SUMIF($N$32:$N$54,G5,$O$32:$O$54) -> 242 | S5: =IFERROR(SUM(Precificação!U140:U159)/SUM(Precificação!$U$96:$U$533)*Precificação!$U$2,0) -> 28659.126 | T5: =IFERROR(S5/O5,0) -> 118.42614 | BT5: =HYPERLINK("#ENGARQSR",BU5) -> ENG/ARQ SR. | BU5: ='Base Salarial'!G9 -> ENG/ARQ SR.
E6: 4 | F6: Equipe04 | G6: Equipe_04 | H6: SUPRIMENTOS | L6: =IFERROR(_xlfn.XLOOKUP(G6,Improdutividade!$R$1:$AK$1,Improdutividade!$R$17:$AK$17),0) -> 0 | O6: =SUMIF($N$32:$N$54,G6,$O$32:$O$54) -> 580.8 | S6: =IFERROR(SUM(Precificação!U162:U181)/SUM(Precificação!$U$96:$U$533)*Precificação!$U$2,0) -> 35052.315 | T6: =IFERROR(S6/O6,0) -> 60.351783 | BT6: =HYPERLINK("#ENGARQPL",BU6) -> ENG/ARQ PL. | BU6: ='Base Salarial'!G10 -> ENG/ARQ PL.
E7: 5 | F7: Equipe05 | G7: Equipe_05 | H7: ORÇAMENTOS | L7: =IFERROR(_xlfn.XLOOKUP(G7,Improdutividade!$R$1:$AK$1,Improdutividade!$R$17:$AK$17),0) -> 0 | O7: =SUMIF($N$32:$N$54,G7,$O$32:$O$54) -> 1176.12 | S7: =IFERROR(SUM(Precificação!U184:U203)/SUM(Precificação!$U$96:$U$533)*Precificação!$U$2,0) -> 134792.37 | T7: =IFERROR(S7/O7,0) -> 114.60767 | BT7: =HYPERLINK("#ENGARQJR",BU7) -> ENG/ARQ JR. | BU7: ='Base Salarial'!G11 -> ENG/ARQ JR.
E8: 6 | F8: Equipe06 | G8: Equipe_06 | L8: =IFERROR(_xlfn.XLOOKUP(G8,Improdutividade!$R$1:$AK$1,Improdutividade!$R$17:$AK$17),0) -> 0 | O8: =SUMIF($N$32:$N$54,G8,$O$32:$O$54) -> 2089.2667 | S8: =IFERROR(SUM(Precificação!U206:U225)/SUM(Precificação!$U$96:$U$533)*Precificação!$U$2,0) -> 115124.65 | T8: =IFERROR(S8/O8,0) -> 55.102901 | BT8: =HYPERLINK("#ANSR.ENGARQ",BU8) -> AN SR. ENG/ARQ | BU8: ='Base Salarial'!G12 -> AN SR. ENG/ARQ
E9: 7 | F9: Equipe07 | G9: Equipe_07 | L9: =IFERROR(_xlfn.XLOOKUP(G9,Improdutividade!$R$1:$AK$1,Improdutividade!$R$17:$AK$17),0) -> 0 | O9: =SUMIF($N$32:$N$54,G9,$O$32:$O$54) -> 0 | S9: =IFERROR(SUM(Precificação!U228:U247)/SUM(Precificação!$U$96:$U$533)*Precificação!$U$2,0) -> 0 | T9: =IFERROR(S9/O9,0) -> 0 | BT9: =HYPERLINK("#ANPL.ENGARQ",BU9) -> AN PL. ENG/ARQ | BU9: ='Base Salarial'!G13 -> AN PL. ENG/ARQ
E10: 8 | F10: Equipe08 | G10: Equipe_08 | L10: =IFERROR(_xlfn.XLOOKUP(G10,Improdutividade!$R$1:$AK$1,Improdutividade!$R$17:$AK$17),0) -> 0 | O10: =SUMIF($N$32:$N$54,G10,$O$32:$O$54) -> 0 | S10: =IFERROR(SUM(Precificação!U250:U269)/SUM(Precificação!$U$96:$U$533)*Precificação!$U$2,0) -> 0 | T10: =IFERROR(S10/O10,0) -> 0 | BT10: =HYPERLINK("#ANJR.ENGARQ",BU10) -> AN JR. ENG/ARQ | BU10: ='Base Salarial'!G14 -> AN JR. ENG/ARQ
E11: 9 | F11: Equipe09 | G11: Equipe_09 | L11: =IFERROR(_xlfn.XLOOKUP(G11,Improdutividade!$R$1:$AK$1,Improdutividade!$R$17:$AK$17),0) -> 0 | O11: =SUMIF($N$32:$N$54,G11,$O$32:$O$54) -> 0 | S11: =IFERROR(SUM(Precificação!U272:U291)/SUM(Precificação!$U$96:$U$533)*Precificação!$U$2,0) -> 0 | T11: =IFERROR(S11/O11,0) -> 0 | BT11: =HYPERLINK("#ANSR.ADMCRP",BU11) -> AN SR. ADM/CRP | BU11: ='Base Salarial'!G15 -> AN SR. ADM/CRP
E12: 10 | F12: Equipe10 | G12: Equipe_10 | L12: =IFERROR(_xlfn.XLOOKUP(G12,Improdutividade!$R$1:$AK$1,Improdutividade!$R$17:$AK$17),0) -> 0 | O12: =SUMIF($N$32:$N$54,G12,$O$32:$O$54) -> 133.1 | S12: =IFERROR(SUM(Precificação!U294:U313)/SUM(Precificação!$U$96:$U$533)*Precificação!$U$2,0) -> 16534.111 | T12: =IFERROR(S12/O12,0) -> 124.22322 | BT12: =HYPERLINK("#ANPL.ADMCRP",BU12) -> AN PL. ADM/CRP | BU12: ='Base Salarial'!G16 -> AN PL. ADM/CRP
E13: 11 | F13: Equipe11 | G13: Equipe_11 | L13: =IFERROR(_xlfn.XLOOKUP(G13,Improdutividade!$R$1:$AK$1,Improdutividade!$R$17:$AK$17),0) -> 0 | O13: =SUMIF($N$32:$N$54,G13,$O$32:$O$54) -> 0 | S13: =IFERROR(SUM(Precificação!U316:U335)/SUM(Precificação!$U$96:$U$533)*Precificação!$U$2,0) -> 0 | T13: =IFERROR(S13/O13,0) -> 0 | BT13: =HYPERLINK("#ANJR.ADMCRP",BU13) -> AN JR. ADM/CRP | BU13: ='Base Salarial'!G17 -> AN JR. ADM/CRP
E14: 12 | F14: Equipe12 | G14: Equipe_12 | L14: =IFERROR(_xlfn.XLOOKUP(G14,Improdutividade!$R$1:$AK$1,Improdutividade!$R$17:$AK$17),0) -> 0 | O14: =SUMIF($N$32:$N$54,G14,$O$32:$O$54) -> 0 | S14: =IFERROR(SUM(Precificação!U338:U357)/SUM(Precificação!$U$96:$U$533)*Precificação!$U$2,0) -> 0 | T14: =IFERROR(S14/O14,0) -> 0 | BT14: =HYPERLINK("#TECIII",BU14) -> TEC III | BU14: ='Base Salarial'!G18 -> TEC III
E15: 13 | F15: Equipe13 | G15: Equipe_13 | L15: =IFERROR(_xlfn.XLOOKUP(G15,Improdutividade!$R$1:$AK$1,Improdutividade!$R$17:$AK$17),0) -> 0 | O15: =SUMIF($N$32:$N$54,G15,$O$32:$O$54) -> 0 | S15: =IFERROR(SUM(Precificação!U360:U379)/SUM(Precificação!$U$96:$U$533)*Precificação!$U$2,0) -> 0 | T15: =IFERROR(S15/O15,0) -> 0 | BT15: =HYPERLINK("#TECII",BU15) -> TEC II | BU15: ='Base Salarial'!G19 -> TEC II
E16: 14 | F16: Equipe14 | G16: Equipe_14 | L16: =IFERROR(_xlfn.XLOOKUP(G16,Improdutividade!$R$1:$AK$1,Improdutividade!$R$17:$AK$17),0) -> 0 | O16: =SUMIF($N$32:$N$54,G16,$O$32:$O$54) -> 0 | S16: =IFERROR(SUM(Precificação!U382:U401)/SUM(Precificação!$U$96:$U$533)*Precificação!$U$2,0) -> 0 | T16: =IFERROR(S16/O16,0) -> 0 | BT16: =HYPERLINK("#TECI",BU16) -> TEC I | BU16: ='Base Salarial'!G20 -> TEC I
E17: 15 | F17: Equipe15 | G17: Equipe_15 | L17: =IFERROR(_xlfn.XLOOKUP(G17,Improdutividade!$R$1:$AK$1,Improdutividade!$R$17:$AK$17),0) -> 0 | O17: =SUMIF($N$32:$N$54,G17,$O$32:$O$54) -> 0 | S17: =IFERROR(SUM(Precificação!U404:U423)/SUM(Precificação!$U$96:$U$533)*Precificação!$U$2,0) -> 0 | T17: =IFERROR(S17/O17,0) -> 0 | BT17: =HYPERLINK("#AUXTEC",BU17) -> AUX TEC | BU17: ='Base Salarial'!G21 -> AUX TEC
E18: 16 | F18: Equipe16 | G18: Equipe_16 | L18: =IFERROR(_xlfn.XLOOKUP(G18,Improdutividade!$R$1:$AK$1,Improdutividade!$R$17:$AK$17),0) -> 0 | O18: =SUMIF($N$32:$N$54,G18,$O$32:$O$54) -> 193.6 | S18: =IFERROR(SUM(Precificação!U426:U445)/SUM(Precificação!$U$96:$U$533)*Precificação!$U$2,0) -> 29918.868 | T18: =IFERROR(S18/O18,0) -> 154.53961 | BT18: =HYPERLINK("#AUXADM",BU18) -> AUX ADM | BU18: ='Base Salarial'!G22 -> AUX ADM
E19: 17 | F19: Equipe17 | G19: Equipe_17 | L19: =IFERROR(_xlfn.XLOOKUP(G19,Improdutividade!$R$1:$AK$1,Improdutividade!$R$17:$AK$17),0) -> 0 | O19: =SUMIF($N$32:$N$54,G19,$O$32:$O$54) -> 77.44 | S19: =IFERROR(SUM(Precificação!U448:U467)/SUM(Precificação!$U$96:$U$533)*Precificação!$U$2,0) -> 8818.1926 | T19: =IFERROR(S19/O19,0) -> 113.87129 | BT19: =HYPERLINK("#EST",BU19) -> EST_III | BU19: ='Base Salarial'!G25 -> EST_III
E20: 18 | F20: Equipe18 | G20: Equipe_18 | L20: =IFERROR(_xlfn.XLOOKUP(G20,Improdutividade!$R$1:$AK$1,Improdutividade!$R$17:$AK$17),0) -> 0 | O20: =SUMIF($N$32:$N$54,G20,$O$32:$O$54) -> 38.72 | S20: =IFERROR(SUM(Precificação!U470:U489)/SUM(Precificação!$U$96:$U$533)*Precificação!$U$2,0) -> 4409.0963 | T20: =IFERROR(S20/O20,0) -> 113.87129
E21: 19 | F21: Equipe19 | G21: Equipe_19 | L21: =IFERROR(_xlfn.XLOOKUP(G21,Improdutividade!$R$1:$AK$1,Improdutividade!$R$17:$AK$17),0) -> 0 | O21: =SUMIF($N$32:$N$54,G21,$O$32:$O$54) -> 96.8 | S21: =IFERROR(SUM(Precificação!U492:U511)/SUM(Precificação!$U$96:$U$533)*Precificação!$U$2,0) -> 5842.0526 | T21: =IFERROR(S21/O21,0) -> 60.351783
E22: 20 | F22: Equipe20 | G22: Equipe_20 | L22: =IFERROR(_xlfn.XLOOKUP(G22,Improdutividade!$R$1:$AK$1,Improdutividade!$R$17:$AK$17),0) -> 0 | O22: =SUMIF($N$32:$N$54,G22,$O$32:$O$54) -> 198.44 | S22: =IFERROR(SUM(Precificação!U514:U533)/SUM(Precificação!$U$96:$U$533)*Precificação!$U$2,0) -> 24250.03 | T22: =IFERROR(S22/O22,0) -> 122.20333
O23: =SUM(O3:O22) -> 8213.48 | S23: =SUM(S3:S22) -> 874071.84 | T23: =IFERROR(S23/O23,0) -> 106.41918
E25: Descrição das Atividades/ Itens | J25: Produtividade | K25: Produtividade | Q25: Valor de Serviços | R25: Valores de Serviços Próprios | W25: Suprimentos | X25: Valores de Materiais | AP25: Preço de Venda | AQ25: Preço de Venda | AY25: Impostos | AZ25: Impostos Totais | BO25: Memória de Cálculo | BP25: Gerentes e Coordenadores | BT25: =BO25 -> Memória de Cálculo | BY25: Supervisores e Especialistas | CD25: Engenheiros e Arquitetos | CQ25: Analistas Engenheiros e Arquitetos | DD25: Analistas Administrativos | DQ25: Técnicos | ED25: Auxiliares e Estágiários | EY25: Serviços Fornecedores | FO25: Memória de Cálculo - PPU | FP25: =FO25 -> Memória de Cálculo - PPU
F27: =F28*0.05 -> 12000000 | O27: HH Total | S27: Custo Total | U27: Venda Total | AC27: Custo Total | AN27: Venda Total | AS27: =AT28/F28 -> 0.0064013158 | AT27: Venda Total | AZ27: Impostos Serviços | BE27: Impostos de Materiais
F28: =60000*4000 -> 240000000 | O28: =SUM(O32:O54) -> 8213.48 | S28: =SUM(S32:S54) -> 874071.84 | U28: =SUM(U32:U54) -> 1278817.6 | AC28: =SUM(AC32:AC54) -> 176000 | AN28: =SUM(AN32:AN54) -> 257498.17 | AS28: =AT28/Dashboard!D13 -> 153631.58 | AT28: =SUM(AT32:AT54) -> 1536315.8 | AZ28: =SUM(AZ32:AZ54) -> 110617.72 | BA28: =SUM(BA32:BA54) -> 46676.843 | BB28: =SUM(BB32:BB54) -> 0 | BC28: =SUM(BC32:BC54) -> 63940.881 | BE28: =SUM(BE32:BE54) -> 22273.592 | BF28: =SUM(BF32:BF54) -> 0 | BG28: =SUM(BG32:BG54) -> 9398.6832 | BH28: =SUM(BH32:BH54) -> 0 | BI28: =SUM(BI32:BI54) -> 12874.909 | BJ28: =SUM(BJ32:BJ54) -> 0 | BK28: =SUM(BK32:BK54) -> 0 | BT28: 1 | BX28: 2 | CC28: 3 | CH28: 4 | CL28: 5 | CP28: 6 | CU28: 7 | CY28: 8 | DC28: 9 | DH28: 10 | DL28: 11 | DP28: 12 | DU28: 13 | DY28: 14 | EC28: 15 | EH28: 16 | EL28: 17 | EP28: 18 | ET28: 19 | EX28: 20 | EZ28: 21 | FA28: 22 | FB28: 23 | FC28: 24 | FD28: 25 | FE28: 26 | FF28: 27 | FG28: 28 | FH28: 29 | FI28: 30 | FJ28: 31 | FK28: 32
BR29: =#REF!/#REF! -> #REF! | BT29: PJ | BX29: PJ | CC29: Mensalista | CH29: PJ | CL29: PJ | CP29: PJ | CU29: Mensalista | CY29: Mensalista | DC29: Mensalista | DH29: Mensalista | DL29: Mensalista | DP29: Mensalista | DU29: Mensalista | DY29: Mensalista | EC29: Mensalista | EH29: Mensalista | EL29: Mensalista | EP29: PJ | ET29: PJ | EX29: PJ
B30: De | C30: Para | E30: Item | F30: Descrição | G30: Un. | H30: Qtd. | K30: Índice Puro | L30: Improdut. (%) | M30: Índice Improdutivo | N30: Equipe | O30: HH Total | R30: Custo Unit. | S30: Custo Total | T30: Venda Unit. | U30: Venda Total | X30: Custo Unit. | Y30: By-out | Z30: Fornecedor | AA30: Tipo de Fornecimento | AB30: Custo Unitário | AC30: Custo Total | AE30: ICMS - Origem | AF30: Taxa ICMS | AG30: PIS/ COFINS | AH30: CPRB | AI30: ISSQN | AJ30: IPI | AK30: Outros Imp. ou Taxas | AM30: Venda Unit. | AN30: Venda Total | AQ30: Venda Unitário Serviço | AR30: Venda Unitário Material | AS30: Venda Unitário Serviço + Material | AT30: Venda Total | AU30: % | AZ30: Impostos Serviços | BA30: PIS/COFINS | BB30: CPRB | BC30: ISSQN | BE30: Total Impostos de Materiais | BF30: ICMS | BG30: PIS/COFINS | BH30: CPRB | BI30: ISSQN | BJ30: IPI | BK30: Outros Impostos ou Taxas | BQ30: QT | BR30: D/M | BS30: h/D | BT30: GER. (OBRA/PROJ) | BU30: QT | BV30: D/M | BW30: H/D | BX30: =INDEX('Base Salarial'!$G$5:$G$25,MATCH(BX28,'Base Salarial'!$A$5:$A$25,0)) -> COORD. | BZ30: QT | CA30: D/M | CB30: H/D | CC30: =INDEX('Base Salarial'!$G$5:$G$25,MATCH(CC28,'Base Salarial'!$A$5:$A$25,0)) -> SUP.-ESP | CE30: QT | CF30: D/M | CG30: h/D | CH30: ENG/ARQ SR. | CI30: QT | CJ30: D/M | CK30: h/D | CL30: =INDEX('Base Salarial'!$G$5:$G$25,MATCH(CL28,'Base Salarial'!$A$5:$A$25,0)) -> ENG/ARQ PL. | CM30: QT | CN30: D/M | CO30: H/D | CP30: =INDEX('Base Salarial'!$G$5:$G$25,MATCH(CP28,'Base Salarial'!$A$5:$A$25,0)) -> ENG/ARQ JR. | CR30: QT | CS30: D/M | CT30: H/D | CU30: =INDEX('Base Salarial'!$G$5:$G$25,MATCH(CU28,'Base Salarial'!$A$5:$A$25,0)) -> AN SR. ENG/ARQ | CV30: QT | CW30: D/M | CX30: H/D | CY30: =INDEX('Base Salarial'!$G$5:$G$25,MATCH(CY28,'Base Salarial'!$A$5:$A$25,0)) -> AN PL. ENG/ARQ | CZ30: QT | DA30: D/M | DB30: H/D | DC30: =INDEX('Base Salarial'!$G$5:$G$25,MATCH(DC28,'Base Salarial'!$A$5:$A$25,0)) -> AN JR. ENG/ARQ | DE30: QT | DF30: D/M | DG30: H/D | DH30: =INDEX('Base Salarial'!$G$5:$G$25,MATCH(DH28,'Base Salarial'!$A$5:$A$25,0)) -> AN SR. ADM/CRP | DI30: QT | DJ30: D/M | DK30: H/D | DL30: =INDEX('Base Salarial'!$G$5:$G$25,MATCH(DL28,'Base Salarial'!$A$5:$A$25,0)) -> AN PL. ADM/CRP | DM30: QT | DN30: D/M | DO30: H/D | DP30: =INDEX('Base Salarial'!$G$5:$G$25,MATCH(DP28,'Base Salarial'!$A$5:$A$25,0)) -> AN JR. ADM/CRP | DR30: QT | DS30: D/M | DT30: H/D | DU30: =INDEX('Base Salarial'!$G$5:$G$25,MATCH(DU28,'Base Salarial'!$A$5:$A$25,0)) -> TEC III | DV30: QT | DW30: D/M | DX30: H/D | DY30: =INDEX('Base Salarial'!$G$5:$G$25,MATCH(DY28,'Base Salarial'!$A$5:$A$25,0)) -> TEC II | DZ30: QT | EA30: D/M | EB30: H/D | EC30: =INDEX('Base Salarial'!$G$5:$G$25,MATCH(EC28,'Base Salarial'!$A$5:$A$25,0)) -> TEC I | EE30: QT | EF30: D/M | EG30: H/D | EH30: =INDEX('Base Salarial'!$G$5:$G$25,MATCH(EH28,'Base Salarial'!$A$5:$A$25,0)) -> AUX TEC | EI30: QT | EJ30: D/M | EK30: H/D | EL30: =INDEX('Base Salarial'!$G$5:$G$25,MATCH(EL28,'Base Salarial'!$A$5:$A$25,0)) -> AUX ADM | EM30: QT | EN30: D/M | EO30: H/D | EP30: =INDEX('Base Salarial'!$G$5:$G$25,MATCH(EP28,'Base Salarial'!$A$5:$A$25,0)) -> EST | EQ30: QT | ER30: D/M | ES30: H/D | ET30: EST_II | EU30: QT | EV30: D/M | EW30: H/D | EX30: EST_III | EZ30: Ajuda de Custo
F31: GERENCIAMENTO DE OBRA
B32: =IFERROR(VLOOKUP(AE32,'Tabela ICMS'!$C$5:$D$32,2,0),"") | C32: =IFERROR(HLOOKUP(Dashboard!$F$9,'Tabela ICMS'!$E$3:$AF$4,2,0),"") -> 25 | E32: 1 | F32: Coordenador de Obras - Full time 100% | G32: mês | H32: =HISTOGRAMA!C8 -> 10 | K32: =SUMIFS(BT32:FK32,$BT$28:$FK$28,">=1",$BT$28:$FK$28,"<=18") -> 199.24667 | L32: =IFERROR(_xlfn.XLOOKUP(N32,$G$3:$G$22,$L$3:$L$22),0) -> 0 | M32: =K32*(1+L32) -> 199.24667 | N32: Equipe_01 | O32: =H32*M32 -> 1992.4667 | R32: =IFERROR(M32*VLOOKUP(N32,$G$3:$T$22,14,0),0) -> 30832.18 | S32: =H32*R32 -> 308321.8 | T32: =R32*(1+Dashboard!$D$35) -> 45109.262 | U32: =H32*T32 -> 451092.62 | X32: =SUMIFS(EZ32:FK32,$EZ$28:$FK$28,">=19",$EZ$28:$FK$28,"<=30") -> 4000 | AA32: Serviço | AB32: =X32*(1-Y32) -> 4000 | AC32: =H32*AB32 -> 40000 | AF32: {=IFERROR(INDEX('Tabela ICMS'!$E$5:$AF$32,Tarefas!B32,Tarefas!C32),0)} -> 0 | AG32: =IF(AA32="FD",(Dashboard!$D$43+Dashboard!$D$44),(Dashboard!$D$30+Dashboard!$D$31)) -> 0.0365 | AH32: =IF(AA32="FD",(Dashboard!$D$46),(Dashboard!$D$33)) -> 0 | AI32: =IF(AA32="FD",(Dashboard!$D$45),(Dashboard!$D$32)) -> 0.05 | AM32: =IF(AA32="FD",AB32*(1+Dashboard!$D$48),AB32*(1+Dashboard!$D$35)) -> 5852.2312 | AN32: =H32*AM32 -> 58522.312 | AQ32: =T32 -> 45109.262 | AR32: =AM32 -> 5852.2312 | AS32: =ROUND(T32+AM32,2) -> 50961.49 | AT32: =ROUND(U32+AN32,2) -> 509614.93 | AU32: =IFERROR(AT32/$AT$28,0) -> 0.33171235 | AZ32: =SUM(BA32:BC32) -> 39019.511 | BA32: =(Dashboard!$D$30+Dashboard!$D$31)*U32 -> 16464.881 | BB32: =Dashboard!$D$33*U32 -> 0 | BC32: =Dashboard!$D$32*U32 -> 22554.631 | BE32: =SUM(BF32:BK32) -> 5062.18 | BF32: =AF32*$AN32 -> 0 | BG32: =IF(AA32="FD",($AN32-$AC32)*AG32,AG32*$AN32) -> 2136.0644 | BH32: =IF(AB32="FD",($AN32-$AC32)*AH32,AH32*$AN32) -> 0 | BI32: =IF(AC32="FD",($AN32-$AC32)*AI32,AI32*$AN32) -> 2926.1156 | BJ32: =IF(AD32="FD",($AN32-$AC32)*AJ32,AJ32*$AN32) -> 0 | BK32: =IF(AE32="FD",($AN32-$AC32)*AK32,AK32*$AN32) -> 0 | BQ32: 1 | BR32: =22*0.05*1/3 -> 0.36666667 | BS32: 8.8 | BT32: =BQ32*BR32*BS32 -> 3.2266667 | BU32: 1 | BV32: 22 | BW32: 8.8 | BX32: =BU32*BV32*BW32 -> 193.6 | BZ32: 0 | CA32: 22 | CB32: 8.8 | CC32: =BZ32*CA32*CB32 -> 0 | CE32: 1 | CF32: =0.05*22*1/4 -> 0.275 | CG32: 8.8 | CH32: =CE32*CF32*CG32 -> 2.42 | CI32: 0 | CJ32: 22 | CK32: 8.8 | CL32: =CI32*CJ32*CK32 -> 0 | CM32: 0 | CN32: 22 | CO32: 8.8 | CP32: =CM32*CN32*CO32 -> 0 | CR32: 0 | CS32: 22 | CT32: 8.8 | CU32: =CR32*CS32*CT32 -> 0 | CV32: 0 | CW32: 22 | CX32: 8.8 | CY32: =CV32*CW32*CX32 -> 0 | CZ32: 0 | DA32: 22 | DB32: 8.8 | DC32: =CZ32*DA32*DB32 -> 0 | DE32: 0 | DF32: 22 | DG32: 8.8 | DH32: =DE32*DF32*DG32 -> 0 | DI32: 0 | DJ32: 22 | DK32: 8.8 | DL32: =DI32*DJ32*DK32 -> 0 | DM32: 0 | DN32: 22 | DO32: 8.8 | DP32: =DM32*DN32*DO32 -> 0 | DR32: 0 | DS32: 22 | DT32: 8.8 | DU32: =DR32*DS32*DT32 -> 0 | DV32: 0 | DW32: 22 | DX32: 8.8 | DY32: =DV32*DW32*DX32 -> 0 | DZ32: 0 | EA32: 22 | EB32: 8.8 | EC32: =DZ32*EA32*EB32 -> 0 | EE32: 0 | EF32: 22 | EG32: 8.8 | EH32: =EE32*EF32*EG32 -> 0 | EI32: 0 | EJ32: 22 | EK32: 8.8 | EL32: =EI32*EJ32*EK32 -> 0 | EM32: 0 | EN32: 22 | EO32: 8.8 | EP32: =EM32*EN32*EO32 -> 0 | EQ32: 0 | ER32: 22 | ES32: 8.8 | ET32: =EQ32*ER32*ES32 -> 0 | EU32: 0 | EV32: 22 | EW32: 8.8 | EX32: =EU32*EV32*EW32 -> 0 | EZ32: 4000
B33: =IFERROR(VLOOKUP(AE33,'Tabela ICMS'!$C$5:$D$32,2,0),"") | C33: =IFERROR(HLOOKUP(Dashboard!$F$9,'Tabela ICMS'!$E$3:$AF$4,2,0),"") -> 25 | E33: 2 | F33: Engenheiro Pl. de Planejamento, Qualidade e Custos ( Supervisor) - Full time | G33: mês | H33: =HISTOGRAMA!C9 -> 7 | K33: =SUMIFS(BT33:FK33,$BT$28:$FK$28,">=1",$BT$28:$FK$28,"<=18") -> 199.24667 | L33: =IFERROR(_xlfn.XLOOKUP(N33,$G$3:$G$22,$L$3:$L$22),0) -> 0 | M33: =K33*(1+L33) -> 199.24667 | N33: Equipe_02 | O33: =H33*M33 -> 1394.7267 | R33: =IFERROR(M33*VLOOKUP(N33,$G$3:$T$22,14,0),0) -> 23192.746 | S33: =H33*R33 -> 162349.22 | T33: =R33*(1+Dashboard!$D$35) -> 33932.328 | U33: =H33*T33 -> 237526.3 | X33: =SUMIFS(EZ33:FK33,$EZ$28:$FK$28,">=19",$EZ$28:$FK$28,"<=30") -> 4000 | AA33: Serviço | AB33: =X33*(1-Y33) -> 4000 | AC33: =H33*AB33 -> 28000 | AF33: {=IFERROR(INDEX('Tabela ICMS'!$E$5:$AF$32,Tarefas!B33,Tarefas!C33),0)} -> 0 | AG33: =IF(AA33="FD",(Dashboard!$D$43+Dashboard!$D$44),(Dashboard!$D$30+Dashboard!$D$31)) -> 0.0365 | AH33: =IF(AA33="FD",(Dashboard!$D$46),(Dashboard!$D$33)) -> 0 | AI33: =IF(AA33="FD",(Dashboard!$D$45),(Dashboard!$D$32)) -> 0.05 | AM33: =IF(AA33="FD",AB33*(1+Dashboard!$D$48),AB33*(1+Dashboard!$D$35)) -> 5852.2312 | AN33: =H33*AM33 -> 40965.618 | AQ33: =T33 -> 33932.328 | AR33: =AM33 -> 5852.2312 | AS33: =ROUND(T33+AM33,2) -> 39784.56 | AT33: =ROUND(U33+AN33,2) -> 278491.92 | AU33: =IFERROR(AT33/$AT$28,0) -> 0.18127257 | AZ33: =SUM(BA33:BC33) -> 20546.025 | BA33: =(Dashboard!$D$30+Dashboard!$D$31)*U33 -> 8669.7098 | BB33: =Dashboard!$D$33*U33 -> 0 | BC33: =Dashboard!$D$32*U33 -> 11876.315 | BE33: =SUM(BF33:BK33) -> 3543.526 | BF33: =AF33*$AN33 -> 0 | BG33: =IF(AA33="FD",($AN33-$AC33)*AG33,AG33*$AN33) -> 1495.2451 | BH33: =IF(AB33="FD",($AN33-$AC33)*AH33,AH33*$AN33) -> 0 | BI33: =IF(AC33="FD",($AN33-$AC33)*AI33,AI33*$AN33) -> 2048.2809 | BJ33: =IF(AD33="FD",($AN33-$AC33)*AJ33,AJ33*$AN33) -> 0 | BK33: =IF(AE33="FD",($AN33-$AC33)*AK33,AK33*$AN33) -> 0 | BQ33: 1 | BR33: =22*0.05*1/3 -> 0.36666667 | BS33: 8.8 | BT33: =BQ33*BR33*BS33 -> 3.2266667 | BU33: 0 | BV33: 22 | BW33: 8.8 | BX33: =BU33*BV33*BW33 -> 0 | BZ33: 0 | CA33: 22 | CB33: 8.8 | CC33: =BZ33*CA33*CB33 -> 0 | CE33: 1 | CF33: =0.05*22*1/4 -> 0.275 | CG33: 8.8 | CH33: =CE33*CF33*CG33 -> 2.42 | CI33: 1 | CJ33: =22 -> 22 | CK33: 8.8 | CL33: =CI33*CJ33*CK33 -> 193.6 | CM33: 0 | CN33: 22 | CO33: 8.8 | CP33: =CM33*CN33*CO33 -> 0 | CR33: 0 | CS33: 22 | CT33: 8.8 | CU33: =CR33*CS33*CT33 -> 0 | CV33: 0 | CW33: 22 | CX33: 8.8 | CY33: =CV33*CW33*CX33 -> 0 | CZ33: 0 | DA33: 22 | DB33: 8.8 | DC33: =CZ33*DA33*DB33 -> 0 | DE33: 0 | DF33: 22 | DG33: 8.8 | DH33: =DE33*DF33*DG33 -> 0 | DI33: 0 | DJ33: 22 | DK33: 8.8 | DL33: =DI33*DJ33*DK33 -> 0 | DM33: 0 | DN33: 22 | DO33: 8.8 | DP33: =DM33*DN33*DO33 -> 0 | DR33: 0 | DS33: 22 | DT33: 8.8 | DU33: =DR33*DS33*DT33 -> 0 | DV33: 0 | DW33: 22 | DX33: 8.8 | DY33: =DV33*DW33*DX33 -> 0 | DZ33: 0 | EA33: 22 | EB33: 8.8 | EC33: =DZ33*EA33*EB33 -> 0 | EE33: 0 | EF33: 22 | EG33: 8.8 | EH33: =EE33*EF33*EG33 -> 0 | EI33: 0 | EJ33: 22 | EK33: 8.8 | EL33: =EI33*EJ33*EK33 -> 0 | EM33: 0 | EN33: 22 | EO33: 8.8 | EP33: =EM33*EN33*EO33 -> 0 | EQ33: 0 | ER33: 22 | ES33: 8.8 | ET33: =EQ33*ER33*ES33 -> 0 | EU33: 0 | EV33: 22 | EW33: 8.8 | EX33: =EU33*EV33*EW33 -> 0 | EZ33: 4000
B34: =IFERROR(VLOOKUP(AE34,'Tabela ICMS'!$C$5:$D$32,2,0),"") | C34: =IFERROR(HLOOKUP(Dashboard!$F$9,'Tabela ICMS'!$E$3:$AF$4,2,0),"") -> 25 | E34: 3 | F34: Engenheiro Pl. de Planejamento, Qualidade e Custos ( Supervisor) - Full time | G34: mês | H34: =HISTOGRAMA!C10 -> 3 | K34: =SUMIFS(BT34:FK34,$BT$28:$FK$28,">=1",$BT$28:$FK$28,"<=18") -> 44.366667 | L34: =IFERROR(_xlfn.XLOOKUP(N34,$G$3:$G$22,$L$3:$L$22),0) -> 0 | M34: =K34*(1+L34) -> 44.366667 | N34: Equipe_10 | O34: =H34*M34 -> 133.1 | R34: =IFERROR(M34*VLOOKUP(N34,$G$3:$T$22,14,0),0) -> 5511.3704 | S34: =H34*R34 -> 16534.111 | T34: =R34*(1+Dashboard!$D$35) -> 8063.4533 | U34: =H34*T34 -> 24190.36 | X34: =SUMIFS(EZ34:FK34,$EZ$28:$FK$28,">=19",$EZ$28:$FK$28,"<=30") -> 4000 | AA34: Serviço | AB34: =X34*(1-Y34) -> 4000 | AC34: =H34*AB34 -> 12000 | AF34: {=IFERROR(INDEX('Tabela ICMS'!$E$5:$AF$32,Tarefas!B34,Tarefas!C34),0)} -> 0 | AG34: =IF(AA34="FD",(Dashboard!$D$43+Dashboard!$D$44),(Dashboard!$D$30+Dashboard!$D$31)) -> 0.0365 | AH34: =IF(AA34="FD",(Dashboard!$D$46),(Dashboard!$D$33)) -> 0 | AI34: =IF(AA34="FD",(Dashboard!$D$45),(Dashboard!$D$32)) -> 0.05 | AM34: =IF(AA34="FD",AB34*(1+Dashboard!$D$48),AB34*(1+Dashboard!$D$35)) -> 5852.2312 | AN34: =H34*AM34 -> 17556.693 | AQ34: =T34 -> 8063.4533 | AR34: =AM34 -> 5852.2312 | AS34: =ROUND(T34+AM34,2) -> 13915.68 | AT34: =ROUND(U34+AN34,2) -> 41747.05 | AU34: =IFERROR(AT34/$AT$28,0) -> 0.027173482 | AZ34: =SUM(BA34:BC34) -> 2092.4661 | BA34: =(Dashboard!$D$30+Dashboard!$D$31)*U34 -> 882.94814 | BB34: =Dashboard!$D$33*U34 -> 0 | BC34: =Dashboard!$D$32*U34 -> 1209.518 | BE34: =SUM(BF34:BK34) -> 1518.654 | BF34: =AF34*$AN34 -> 0 | BG34: =IF(AA34="FD",($AN34-$AC34)*AG34,AG34*$AN34) -> 640.81931 | BH34: =IF(AB34="FD",($AN34-$AC34)*AH34,AH34*$AN34) -> 0 | BI34: =IF(AC34="FD",($AN34-$AC34)*AI34,AI34*$AN34) -> 877.83467 | BJ34: =IF(AD34="FD",($AN34-$AC34)*AJ34,AJ34*$AN34) -> 0 | BK34: =IF(AE34="FD",($AN34-$AC34)*AK34,AK34*$AN34) -> 0 | BQ34: 1 | BR34: =22*0.05*1/3 -> 0.36666667 | BS34: 8.8 | BT34: =BQ34*BR34*BS34 -> 3.2266667 | BU34: 0 | BV34: 22 | BW34: 8.8 | BX34: =BU34*BV34*BW34 -> 0 | BZ34: 0 | CA34: 22 | CB34: 8.8 | CC34: =BZ34*CA34*CB34 -> 0 | CE34: 1 | CF34: =0.05*22*1/4 -> 0.275 | CG34: 8.8 | CH34: =CE34*CF34*CG34 -> 2.42 | CI34: 1 | CJ34: =20%*22 -> 4.4 | CK34: 8.8 | CL34: =CI34*CJ34*CK34 -> 38.72 | CM34: 0 | CN34: 22 | CO34: 8.8 | CP34: =CM34*CN34*CO34 -> 0 | CR34: 0 | CS34: 22 | CT34: 8.8 | CU34: =CR34*CS34*CT34 -> 0 | CV34: 0 | CW34: 22 | CX34: 8.8 | CY34: =CV34*CW34*CX34 -> 0 | CZ34: 0 | DA34: 22 | DB34: 8.8 | DC34: =CZ34*DA34*DB34 -> 0 | DE34: 0 | DF34: 22 | DG34: 8.8 | DH34: =DE34*DF34*DG34 -> 0 | DI34: 0 | DJ34: 22 | DK34: 8.8 | DL34: =DI34*DJ34*DK34 -> 0 | DM34: 0 | DN34: 22 | DO34: 8.8 | DP34: =DM34*DN34*DO34 -> 0 | DR34: 0 | DS34: 22 | DT34: 8.8 | DU34: =DR34*DS34*DT34 -> 0 | DV34: 0 | DW34: 22 | DX34: 8.8 | DY34: =DV34*DW34*DX34 -> 0 | DZ34: 0 | EA34: 22 | EB34: 8.8 | EC34: =DZ34*EA34*EB34 -> 0 | EE34: 0 | EF34: 22 | EG34: 8.8 | EH34: =EE34*EF34*EG34 -> 0 | EI34: 0 | EJ34: 22 | EK34: 8.8 | EL34: =EI34*EJ34*EK34 -> 0 | EM34: 0 | EN34: 22 | EO34: 8.8 | EP34: =EM34*EN34*EO34 -> 0 | EQ34: 0 | ER34: 22 | ES34: 8.8 | ET34: =EQ34*ER34*ES34 -> 0 | EU34: 0 | EV34: 22 | EW34: 8.8 | EX34: =EU34*EV34*EW34 -> 0 | EZ34: 4000
B35: =IFERROR(VLOOKUP(AE35,'Tabela ICMS'!$C$5:$D$32,2,0),"") | C35: =IFERROR(HLOOKUP(Dashboard!$F$9,'Tabela ICMS'!$E$3:$AF$4,2,0),"") -> 25 | E35: 4 | F35: Engenheiro Jr. Qualidade ( Supervisor) - Instalações 25% | G35: mês | H35: =HISTOGRAMA!C11 -> 5 | K35: =SUMIFS(BT35:FK35,$BT$28:$FK$28,">=1",$BT$28:$FK$28,"<=18") -> 48.4 | L35: =IFERROR(_xlfn.XLOOKUP(N35,$G$3:$G$22,$L$3:$L$22),0) -> 0 | M35: =K35*(1+L35) -> 48.4 | N35: Equipe_03 | O35: =H35*M35 -> 242 | R35: =IFERROR(M35*VLOOKUP(N35,$G$3:$T$22,14,0),0) -> 5731.8252 | S35: =H35*R35 -> 28659.126 | T35: =R35*(1+Dashboard!$D$35) -> 8385.9915 | U35: =H35*T35 -> 41929.957 | X35: =SUMIFS(EZ35:FK35,$EZ$28:$FK$28,">=19",$EZ$28:$FK$28,"<=30") -> 3000 | AA35: Serviço | AB35: =X35*(1-Y35) -> 3000 | AC35: =H35*AB35 -> 15000 | AF35: {=IFERROR(INDEX('Tabela ICMS'!$E$5:$AF$32,Tarefas!B35,Tarefas!C35),0)} -> 0 | AG35: =IF(AA35="FD",(Dashboard!$D$43+Dashboard!$D$44),(Dashboard!$D$30+Dashboard!$D$31)) -> 0.0365 | AH35: =IF(AA35="FD",(Dashboard!$D$46),(Dashboard!$D$33)) -> 0 | AI35: =IF(AA35="FD",(Dashboard!$D$45),(Dashboard!$D$32)) -> 0.05 | AM35: =IF(AA35="FD",AB35*(1+Dashboard!$D$48),AB35*(1+Dashboard!$D$35)) -> 4389.1734 | AN35: =H35*AM35 -> 21945.867 | AQ35: =T35 -> 8385.9915 | AR35: =AM35 -> 4389.1734 | AS35: =ROUND(T35+AM35,2) -> 12775.16 | AT35: =ROUND(U35+AN35,2) -> 63875.82 | AU35: =IFERROR(AT35/$AT$28,0) -> 0.041577272 | AZ35: =SUM(BA35:BC35) -> 3626.9413 | BA35: =(Dashboard!$D$30+Dashboard!$D$31)*U35 -> 1530.4434 | BB35: =Dashboard!$D$33*U35 -> 0 | BC35: =Dashboard!$D$32*U35 -> 2096.4979 | BE35: =SUM(BF35:BK35) -> 1898.3175 | BF35: =AF35*$AN35 -> 0 | BG35: =IF(AA35="FD",($AN35-$AC35)*AG35,AG35*$AN35) -> 801.02414 | BH35: =IF(AB35="FD",($AN35-$AC35)*AH35,AH35*$AN35) -> 0 | BI35: =IF(AC35="FD",($AN35-$AC35)*AI35,AI35*$AN35) -> 1097.2933 | BJ35: =IF(AD35="FD",($AN35-$AC35)*AJ35,AJ35*$AN35) -> 0 | BK35: =IF(AE35="FD",($AN35-$AC35)*AK35,AK35*$AN35) -> 0 | BQ35: 0 | BR35: 0 | BS35: 8.8 | BT35: =BQ35*BR35*BS35 -> 0 | BU35: 0 | BV35: 22 | BW35: 8.8 | BX35: =BU35*BV35*BW35 -> 0 | BZ35: 0 | CA35: 22 | CB35: 8.8 | CC35: =BZ35*CA35*CB35 -> 0 | CE35: 0 | CF35: 0 | CG35: 8.8 | CH35: =CE35*CF35*CG35 -> 0 | CI35: 0 | CJ35: 22 | CK35: 8.8 | CL35: =CI35*CJ35*CK35 -> 0 | CM35: 1 | CN35: =22*25% -> 5.5 | CO35: 8.8 | CP35: =CM35*CN35*CO35 -> 48.4 | CR35: 0 | CS35: 22 | CT35: 8.8 | CU35: =CR35*CS35*CT35 -> 0 | CV35: 0 | CW35: 22 | CX35: 8.8 | CY35: =CV35*CW35*CX35 -> 0 | CZ35: 0 | DA35: 22 | DB35: 8.8 | DC35: =CZ35*DA35*DB35 -> 0 | DE35: 0 | DF35: 22 | DG35: 8.8 | DH35: =DE35*DF35*DG35 -> 0 | DI35: 0 | DJ35: 22 | DK35: 8.8 | DL35: =DI35*DJ35*DK35 -> 0 | DM35: 0 | DN35: 22 | DO35: 8.8 | DP35: =DM35*DN35*DO35 -> 0 | DR35: 0 | DS35: 22 | DT35: 8.8 | DU35: =DR35*DS35*DT35 -> 0 | DV35: 0 | DW35: 22 | DX35: 8.8 | DY35: =DV35*DW35*DX35 -> 0 | DZ35: 0 | EA35: 22 | EB35: 8.8 | EC35: =DZ35*EA35*EB35 -> 0 | EE35: 0 | EF35: 22 | EG35: 8.8 | EH35: =EE35*EF35*EG35 -> 0 | EI35: 0 | EJ35: 22 | EK35: 8.8 | EL35: =EI35*EJ35*EK35 -> 0 | EM35: 0 | EN35: 22 | EO35: 8.8 | EP35: =EM35*EN35*EO35 -> 0 | EQ35: 0 | ER35: 22 | ES35: 8.8 | ET35: =EQ35*ER35*ES35 -> 0 | EU35: 0 | EV35: 22 | EW35: 8.8 | EX35: =EU35*EV35*EW35 -> 0 | EZ35: =4000*0+3000 -> 3000
B36: =IFERROR(VLOOKUP(AE36,'Tabela ICMS'!$C$5:$D$32,2,0),"") | C36: =IFERROR(HLOOKUP(Dashboard!$F$9,'Tabela ICMS'!$E$3:$AF$4,2,0),"") -> 25 | E36: 5 | F36: Analista de Custos - An. Sr. 50% | G36: mês | H36: =HISTOGRAMA!C12 -> 6 | K36: =SUMIFS(BT36:FK36,$BT$28:$FK$28,">=1",$BT$28:$FK$28,"<=18") -> 96.8 | L36: =IFERROR(_xlfn.XLOOKUP(N36,$G$3:$G$22,$L$3:$L$22),0) -> 0 | M36: =K36*(1+L36) -> 96.8 | N36: Equipe_04 | O36: =H36*M36 -> 580.8 | R36: =IFERROR(M36*VLOOKUP(N36,$G$3:$T$22,14,0),0) -> 5842.0526 | S36: =H36*R36 -> 35052.315 | T36: =R36*(1+Dashboard!$D$35) -> 8547.2605 | U36: =H36*T36 -> 51283.563 | X36: =SUMIFS(EZ36:FK36,$EZ$28:$FK$28,">=19",$EZ$28:$FK$28,"<=30") -> 2500 | AA36: Serviço | AB36: =X36*(1-Y36) -> 2500 | AC36: =H36*AB36 -> 15000 | AF36: {=IFERROR(INDEX('Tabela ICMS'!$E$5:$AF$32,Tarefas!B36,Tarefas!C36),0)} -> 0 | AG36: =IF(AA36="FD",(Dashboard!$D$43+Dashboard!$D$44),(Dashboard!$D$30+Dashboard!$D$31)) -> 0.0365 | AH36: =IF(AA36="FD",(Dashboard!$D$46),(Dashboard!$D$33)) -> 0 | AI36: =IF(AA36="FD",(Dashboard!$D$45),(Dashboard!$D$32)) -> 0.05 | AM36: =IF(AA36="FD",AB36*(1+Dashboard!$D$48),AB36*(1+Dashboard!$D$35)) -> 3657.6445 | AN36: =H36*AM36 -> 21945.867 | AQ36: =T36 -> 8547.2605 | AR36: =AM36 -> 3657.6445 | AS36: =ROUND(T36+AM36,2) -> 12204.91 | AT36: =ROUND(U36+AN36,2) -> 73229.43 | AU36: =IFERROR(AT36/$AT$28,0) -> 0.04766561 | AZ36: =SUM(BA36:BC36) -> 4436.0282 | BA36: =(Dashboard!$D$30+Dashboard!$D$31)*U36 -> 1871.8501 | BB36: =Dashboard!$D$33*U36 -> 0 | BC36: =Dashboard!$D$32*U36 -> 2564.1782 | BE36: =SUM(BF36:BK36) -> 1898.3175 | BF36: =AF36*$AN36 -> 0 | BG36: =IF(AA36="FD",($AN36-$AC36)*AG36,AG36*$AN36) -> 801.02414 | BH36: =IF(AB36="FD",($AN36-$AC36)*AH36,AH36*$AN36) -> 0 | BI36: =IF(AC36="FD",($AN36-$AC36)*AI36,AI36*$AN36) -> 1097.2933 | BJ36: =IF(AD36="FD",($AN36-$AC36)*AJ36,AJ36*$AN36) -> 0 | BK36: =IF(AE36="FD",($AN36-$AC36)*AK36,AK36*$AN36) -> 0 | BQ36: 0 | BR36: 0 | BS36: 8.8 | BT36: =BQ36*BR36*BS36 -> 0 | BU36: 0 | BV36: 22 | BW36: 8.8 | BX36: =BU36*BV36*BW36 -> 0 | BZ36: 0 | CA36: 22 | CB36: 8.8 | CC36: =BZ36*CA36*CB36 -> 0 | CE36: 0 | CF36: 0 | CG36: 8.8 | CH36: =CE36*CF36*CG36 -> 0 | CI36: 0 | CJ36: 22 | CK36: 8.8 | CL36: =CI36*CJ36*CK36 -> 0 | CM36: 0 | CN36: 22 | CO36: 8.8 | CP36: =CM36*CN36*CO36 -> 0 | CR36: 0 | CS36: 22 | CT36: 8.8 | CU36: =CR36*CS36*CT36 -> 0 | CV36: 0 | CW36: 22 | CX36: 8.8 | CY36: =CV36*CW36*CX36 -> 0 | CZ36: 0 | DA36: 22 | DB36: 8.8 | DC36: =CZ36*DA36*DB36 -> 0 | DE36: 1 | DF36: =22/2 -> 11 | DG36: 8.8 | DH36: =DE36*DF36*DG36 -> 96.8 | DI36: 0 | DJ36: 22 | DK36: 8.8 | DL36: =DI36*DJ36*DK36 -> 0 | DM36: 0 | DN36: 22 | DO36: 8.8 | DP36: =DM36*DN36*DO36 -> 0 | DR36: 0 | DS36: 22 | DT36: 8.8 | DU36: =DR36*DS36*DT36 -> 0 | DV36: 0 | DW36: 22 | DX36: 8.8 | DY36: =DV36*DW36*DX36 -> 0 | DZ36: 0 | EA36: 22 | EB36: 8.8 | EC36: =DZ36*EA36*EB36 -> 0 | EE36: 0 | EF36: 22 | EG36: 8.8 | EH36: =EE36*EF36*EG36 -> 0 | EI36: 0 | EJ36: 22 | EK36: 8.8 | EL36: =EI36*EJ36*EK36 -> 0 | EM36: 0 | EN36: 22 | EO36: 8.8 | EP36: =EM36*EN36*EO36 -> 0 | EQ36: 0 | ER36: 22 | ES36: 8.8 | ET36: =EQ36*ER36*ES36 -> 0 | EU36: 0 | EV36: 22 | EW36: 8.8 | EX36: =EU36*EV36*EW36 -> 0 | EZ36: 2500
B37: =IFERROR(VLOOKUP(AE37,'Tabela ICMS'!$C$5:$D$32,2,0),"") | C37: =IFERROR(HLOOKUP(Dashboard!$F$9,'Tabela ICMS'!$E$3:$AF$4,2,0),"") -> 25 | E37: 6 | F37: Arquiteto Pl. ( Gestão de projetos) - Remoto ( Supervisor) - 100% | G37: mês | H37: =HISTOGRAMA!C13 -> 6 | K37: =SUMIFS(BT37:FK37,$BT$28:$FK$28,">=1",$BT$28:$FK$28,"<=18") -> 196.02 | L37: =IFERROR(_xlfn.XLOOKUP(N37,$G$3:$G$22,$L$3:$L$22),0) -> 0 | M37: =K37*(1+L37) -> 196.02 | N37: Equipe_05 | O37: =H37*M37 -> 1176.12 | R37: =IFERROR(M37*VLOOKUP(N37,$G$3:$T$22,14,0),0) -> 22465.395 | S37: =H37*R37 -> 134792.37 | T37: =R37*(1+Dashboard!$D$35) -> 32868.172 | U37: =H37*T37 -> 197209.03 | X37: =SUMIFS(EZ37:FK37,$EZ$28:$FK$28,">=19",$EZ$28:$FK$28,"<=30") -> 4000 | AA37: Serviço | AB37: =X37*(1-Y37) -> 4000 | AC37: =H37*AB37 -> 24000 | AF37: {=IFERROR(INDEX('Tabela ICMS'!$E$5:$AF$32,Tarefas!B37,Tarefas!C37),0)} -> 0 | AG37: =IF(AA37="FD",(Dashboard!$D$43+Dashboard!$D$44),(Dashboard!$D$30+Dashboard!$D$31)) -> 0.0365 | AH37: =IF(AA37="FD",(Dashboard!$D$46),(Dashboard!$D$33)) -> 0 | AI37: =IF(AA37="FD",(Dashboard!$D$45),(Dashboard!$D$32)) -> 0.05 | AM37: =IF(AA37="FD",AB37*(1+Dashboard!$D$48),AB37*(1+Dashboard!$D$35)) -> 5852.2312 | AN37: =H37*AM37 -> 35113.387 | AQ37: =T37 -> 32868.172 | AR37: =AM37 -> 5852.2312 | AS37: =ROUND(T37+AM37,2) -> 38720.4 | AT37: =ROUND(U37+AN37,2) -> 232322.42 | AU37: =IFERROR(AT37/$AT$28,0) -> 0.15122048 | AZ37: =SUM(BA37:BC37) -> 17058.581 | BA37: =(Dashboard!$D$30+Dashboard!$D$31)*U37 -> 7198.1296 | BB37: =Dashboard!$D$33*U37 -> 0 | BC37: =Dashboard!$D$32*U37 -> 9860.4515 | BE37: =SUM(BF37:BK37) -> 3037.308 | BF37: =AF37*$AN37 -> 0 | BG37: =IF(AA37="FD",($AN37-$AC37)*AG37,AG37*$AN37) -> 1281.6386 | BH37: =IF(AB37="FD",($AN37-$AC37)*AH37,AH37*$AN37) -> 0 | BI37: =IF(AC37="FD",($AN37-$AC37)*AI37,AI37*$AN37) -> 1755.6693 | BJ37: =IF(AD37="FD",($AN37-$AC37)*AJ37,AJ37*$AN37) -> 0 | BK37: =IF(AE37="FD",($AN37-$AC37)*AK37,AK37*$AN37) -> 0 | BQ37: 0 | BR37: =22*0.05*1/4 -> 0.275 | BS37: 8.8 | BT37: =BQ37*BR37*BS37 -> 0 | BU37: 0 | BV37: =0.15*22 -> 3.3 | BW37: 8.8 | BX37: =BU37*BV37*BW37 -> 0 | BZ37: 0 | CA37: 22 | CB37: 8.8 | CC37: =BZ37*CA37*CB37 -> 0 | CE37: 1 | CF37: =0.05*22*1/4 -> 0.275 | CG37: 8.8 | CH37: =CE37*CF37*CG37 -> 2.42 | CI37: 1 | CJ37: 22 | CK37: 8.8 | CL37: =CI37*CJ37*CK37 -> 193.6 | CM37: 0 | CN37: 22 | CO37: 8.8 | CP37: =CM37*CN37*CO37 -> 0 | CR37: 0 | CS37: 22 | CT37: 8.8 | CU37: =CR37*CS37*CT37 -> 0 | CV37: 0 | CW37: 22 | CX37: 8.8 | CY37: =CV37*CW37*CX37 -> 0 | CZ37: 0 | DA37: 22 | DB37: 8.8 | DC37: =CZ37*DA37*DB37 -> 0 | DE37: 0 | DF37: 22 | DG37: 8.8 | DH37: =DE37*DF37*DG37 -> 0 | DI37: 0 | DJ37: 22 | DK37: 8.8 | DL37: =DI37*DJ37*DK37 -> 0 | DM37: 0 | DN37: 22 | DO37: 8.8 | DP37: =DM37*DN37*DO37 -> 0 | DR37: 0 | DS37: 22 | DT37: 8.8 | DU37: =DR37*DS37*DT37 -> 0 | DV37: 0 | DW37: 22 | DX37: 8.8 | DY37: =DV37*DW37*DX37 -> 0 | DZ37: 0 | EA37: 22 | EB37: 8.8 | EC37: =DZ37*EA37*EB37 -> 0 | EE37: 0 | EF37: 22 | EG37: 8.8 | EH37: =EE37*EF37*EG37 -> 0 | EI37: 0 | EJ37: 22 | EK37: 8.8 | EL37: =EI37*EJ37*EK37 -> 0 | EM37: 0 | EN37: 22 | EO37: 8.8 | EP37: =EM37*EN37*EO37 -> 0 | EQ37: 0 | ER37: 22 | ES37: 8.8 | ET37: =EQ37*ER37*ES37 -> 0 | EU37: 0 | EV37: 22 | EW37: 8.8 | EX37: =EU37*EV37*EW37 -> 0 | EZ37: 4000
B38: =IFERROR(VLOOKUP(AE38,'Tabela ICMS'!$C$5:$D$32,2,0),"") | C38: =IFERROR(HLOOKUP(Dashboard!$F$9,'Tabela ICMS'!$E$3:$AF$4,2,0),"") -> 25 | E38: 6.1 | F38: Arquiteto Pl. ( Gestão de projetos) - Remoto ( Supervisor) - 50% | G38: mês | H38: =HISTOGRAMA!C14 -> 2 | K38: =SUMIFS(BT38:FK38,$BT$28:$FK$28,">=1",$BT$28:$FK$28,"<=18") -> 99.22 | L38: =IFERROR(_xlfn.XLOOKUP(N38,$G$3:$G$22,$L$3:$L$22),0) -> 0 | M38: =K38*(1+L38) -> 99.22 | N38: Equipe_20 | O38: =H38*M38 -> 198.44 | R38: =IFERROR(M38*VLOOKUP(N38,$G$3:$T$22,14,0),0) -> 12125.015 | S38: =H38*R38 -> 24250.03 | T38: =R38*(1+Dashboard!$D$35) -> 17739.597 | U38: =H38*T38 -> 35479.195 | X38: =SUMIFS(EZ38:FK38,$EZ$28:$FK$28,">=19",$EZ$28:$FK$28,"<=30") -> 4000 | AA38: Serviço | AB38: =X38*(1-Y38) -> 4000 | AC38: =H38*AB38 -> 8000 | AF38: {=IFERROR(INDEX('Tabela ICMS'!$E$5:$AF$32,Tarefas!B38,Tarefas!C38),0)} -> 0 | AG38: =IF(AA38="FD",(Dashboard!$D$43+Dashboard!$D$44),(Dashboard!$D$30+Dashboard!$D$31)) -> 0.0365 | AH38: =IF(AA38="FD",(Dashboard!$D$46),(Dashboard!$D$33)) -> 0 | AI38: =IF(AA38="FD",(Dashboard!$D$45),(Dashboard!$D$32)) -> 0.05 | AM38: =IF(AA38="FD",AB38*(1+Dashboard!$D$48),AB38*(1+Dashboard!$D$35)) -> 5852.2312 | AN38: =H38*AM38 -> 11704.462 | AQ38: =T38 -> 17739.597 | AR38: =AM38 -> 5852.2312 | AS38: =ROUND(T38+AM38,2) -> 23591.83 | AT38: =ROUND(U38+AN38,2) -> 47183.66 | AU38: =IFERROR(AT38/$AT$28,0) -> 0.030712214 | AZ38: =SUM(BA38:BC38) -> 3068.9503 | BA38: =(Dashboard!$D$30+Dashboard!$D$31)*U38 -> 1294.9906 | BB38: =Dashboard!$D$33*U38 -> 0 | BC38: =Dashboard!$D$32*U38 -> 1773.9597 | BE38: =SUM(BF38:BK38) -> 1012.436 | BF38: =AF38*$AN38 -> 0 | BG38: =IF(AA38="FD",($AN38-$AC38)*AG38,AG38*$AN38) -> 427.21287 | BH38: =IF(AB38="FD",($AN38-$AC38)*AH38,AH38*$AN38) -> 0 | BI38: =IF(AC38="FD",($AN38-$AC38)*AI38,AI38*$AN38) -> 585.22312 | BJ38: =IF(AD38="FD",($AN38-$AC38)*AJ38,AJ38*$AN38) -> 0 | BK38: =IF(AE38="FD",($AN38-$AC38)*AK38,AK38*$AN38) -> 0 | BQ38: 0 | BR38: =22*0.05*1/4 -> 0.275 | BS38: 8.8 | BT38: =BQ38*BR38*BS38 -> 0 | BU38: 0 | BV38: =0.15*22 -> 3.3 | BW38: 8.8 | BX38: =BU38*BV38*BW38 -> 0 | BZ38: 0 | CA38: 22 | CB38: 8.8 | CC38: =BZ38*CA38*CB38 -> 0 | CE38: 1 | CF38: =0.05*22*1/4 -> 0.275 | CG38: 8.8 | CH38: =CE38*CF38*CG38 -> 2.42 | CI38: 1 | CJ38: =50%*22 -> 11 | CK38: 8.8 | CL38: =CI38*CJ38*CK38 -> 96.8 | CM38: 0 | CN38: 22 | CO38: 8.8 | CP38: =CM38*CN38*CO38 -> 0 | CR38: 0 | CS38: 22 | CT38: 8.8 | CU38: =CR38*CS38*CT38 -> 0 | CV38: 0 | CW38: 22 | CX38: 8.8 | CY38: =CV38*CW38*CX38 -> 0 | CZ38: 0 | DA38: 22 | DB38: 8.8 | DC38: =CZ38*DA38*DB38 -> 0 | DE38: 0 | DF38: 22 | DG38: 8.8 | DH38: =DE38*DF38*DG38 -> 0 | DI38: 0 | DJ38: 22 | DK38: 8.8 | DL38: =DI38*DJ38*DK38 -> 0 | DM38: 0 | DN38: 22 | DO38: 8.8 | DP38: =DM38*DN38*DO38 -> 0 | DR38: 0 | DS38: 22 | DT38: 8.8 | DU38: =DR38*DS38*DT38 -> 0 | DV38: 0 | DW38: 22 | DX38: 8.8 | DY38: =DV38*DW38*DX38 -> 0 | DZ38: 0 | EA38: 22 | EB38: 8.8 | EC38: =DZ38*EA38*EB38 -> 0 | EE38: 0 | EF38: 22 | EG38: 8.8 | EH38: =EE38*EF38*EG38 -> 0 | EI38: 0 | EJ38: 22 | EK38: 8.8 | EL38: =EI38*EJ38*EK38 -> 0 | EM38: 0 | EN38: 22 | EO38: 8.8 | EP38: =EM38*EN38*EO38 -> 0 | EQ38: 0 | ER38: 22 | ES38: 8.8 | ET38: =EQ38*ER38*ES38 -> 0 | EU38: 0 | EV38: 22 | EW38: 8.8 | EX38: =EU38*EV38*EW38 -> 0 | EZ38: 4000
B39: =IFERROR(VLOOKUP(AE39,'Tabela ICMS'!$C$5:$D$32,2,0),"") | C39: =IFERROR(HLOOKUP(Dashboard!$F$9,'Tabela ICMS'!$E$3:$AF$4,2,0),"") -> 25 | E39: 7 | F39: Técnico de Segurança | G39: mês | H39: =HISTOGRAMA!C15 -> 10 | K39: =SUMIFS(BT39:FK39,$BT$28:$FK$28,">=1",$BT$28:$FK$28,"<=18") -> 208.92667 | L39: =IFERROR(_xlfn.XLOOKUP(N39,$G$3:$G$22,$L$3:$L$22),0) -> 0 | M39: =K39*(1+L39) -> 208.92667 | N39: Equipe_06 | O39: =H39*M39 -> 2089.2667 | R39: =IFERROR(M39*VLOOKUP(N39,$G$3:$T$22,14,0),0) -> 11512.465 | S39: =H39*R39 -> 115124.65 | T39: =R39*(1+Dashboard!$D$35) -> 16843.402 | U39: =H39*T39 -> 168434.02 | X39: =SUMIFS(EZ39:FK39,$EZ$28:$FK$28,">=19",$EZ$28:$FK$28,"<=30") -> 3000 | AA39: Serviço | AB39: =X39*(1-Y39) -> 3000 | AC39: =H39*AB39 -> 30000 | AF39: {=IFERROR(INDEX('Tabela ICMS'!$E$5:$AF$32,Tarefas!B39,Tarefas!C39),0)} -> 0 | AG39: =IF(AA39="FD",(Dashboard!$D$43+Dashboard!$D$44),(Dashboard!$D$30+Dashboard!$D$31)) -> 0.0365 | AH39: =IF(AA39="FD",(Dashboard!$D$46),(Dashboard!$D$33)) -> 0 | AI39: =IF(AA39="FD",(Dashboard!$D$45),(Dashboard!$D$32)) -> 0.05 | AM39: =IF(AA39="FD",AB39*(1+Dashboard!$D$48),AB39*(1+Dashboard!$D$35)) -> 4389.1734 | AN39: =H39*AM39 -> 43891.734 | AQ39: =T39 -> 16843.402 | AR39: =AM39 -> 4389.1734 | AS39: =ROUND(T39+AM39,2) -> 21232.58 | AT39: =ROUND(U39+AN39,2) -> 212325.75 | AU39: =IFERROR(AT39/$AT$28,0) -> 0.1382045 | AZ39: =SUM(BA39:BC39) -> 14569.543 | BA39: =(Dashboard!$D$30+Dashboard!$D$31)*U39 -> 6147.8418 | BB39: =Dashboard!$D$33*U39 -> 0 | BC39: =Dashboard!$D$32*U39 -> 8421.701 | BE39: =SUM(BF39:BK39) -> 3796.635 | BF39: =AF39*$AN39 -> 0 | BG39: =IF(AA39="FD",($AN39-$AC39)*AG39,AG39*$AN39) -> 1602.0483 | BH39: =IF(AB39="FD",($AN39-$AC39)*AH39,AH39*$AN39) -> 0 | BI39: =IF(AC39="FD",($AN39-$AC39)*AI39,AI39*$AN39) -> 2194.5867 | BJ39: =IF(AD39="FD",($AN39-$AC39)*AJ39,AJ39*$AN39) -> 0 | BK39: =IF(AE39="FD",($AN39-$AC39)*AK39,AK39*$AN39) -> 0 | BQ39: 1 | BR39: =22*0.05*1/3 -> 0.36666667 | BS39: 8.8 | BT39: =BQ39*BR39*BS39 -> 3.2266667 | BU39: 0 | BV39: 22 | BW39: 8.8 | BX39: =BU39*BV39*BW39 -> 0 | BZ39: 0 | CA39: 22 | CB39: 8.8 | CC39: =BZ39*CA39*CB39 -> 0 | CE39: 1 | CF39: =0.05*22*1/4 -> 0.275 | CG39: 8.8 | CH39: =CE39*CF39*CG39 -> 2.42 | CI39: 0 | CJ39: =0.15*22 -> 3.3 | CK39: 8.8 | CL39: =CI39*CJ39*CK39 -> 0 | CM39: 0 | CN39: 22 | CO39: 8.8 | CP39: =CM39*CN39*CO39 -> 0 | CR39: 0 | CS39: 22 | CT39: 8.8 | CU39: =CR39*CS39*CT39 -> 0 | CV39: 0 | CW39: 22 | CX39: 8.8 | CY39: =CV39*CW39*CX39 -> 0 | CZ39: 0 | DA39: 22 | DB39: 8.8 | DC39: =CZ39*DA39*DB39 -> 0 | DE39: 1 | DF39: =5%*22 -> 1.1 | DG39: 8.8 | DH39: =DE39*DF39*DG39 -> 9.68 | DI39: 0 | DJ39: 22 | DK39: 8.8 | DL39: =DI39*DJ39*DK39 -> 0 | DM39: 0 | DN39: 22 | DO39: 8.8 | DP39: =DM39*DN39*DO39 -> 0 | DR39: 1 | DS39: 22 | DT39: 8.8 | DU39: =DR39*DS39*DT39 -> 193.6 | DV39: 0 | DW39: 22 | DX39: 8.8 | DY39: =DV39*DW39*DX39 -> 0 | DZ39: 0 | EA39: 22 | EB39: 8.8 | EC39: =DZ39*EA39*EB39 -> 0 | EE39: 0 | EF39: 22 | EG39: 8.8 | EH39: =EE39*EF39*EG39 -> 0 | EI39: 0 | EJ39: 22 | EK39: 8.8 | EL39: =EI39*EJ39*EK39 -> 0 | EM39: 0 | EN39: 22 | EO39: 8.8 | EP39: =EM39*EN39*EO39 -> 0 | EQ39: 0 | ER39: 22 | ES39: 8.8 | ET39: =EQ39*ER39*ES39 -> 0 | EU39: 0 | EV39: 22 | EW39: 8.8 | EX39: =EU39*EV39*EW39 -> 0 | EZ39: =3000 -> 3000
B40: =IFERROR(VLOOKUP(AE40,'Tabela ICMS'!$C$5:$D$32,2,0),"") | C40: =IFERROR(HLOOKUP(Dashboard!$F$9,'Tabela ICMS'!$E$3:$AF$4,2,0),"") -> 25 | E40: 8 | F40: Gerrente de Obras - 5% - Considerado equipe diluida nas linhas com 10 meses | G40: mês | H40: =HISTOGRAMA!C16 -> 10 | K40: =SUMIFS(BT40:FK40,$BT$28:$FK$28,">=1",$BT$28:$FK$28,"<=18") -> 0 | L40: =IFERROR(_xlfn.XLOOKUP(N40,$G$3:$G$22,$L$3:$L$22),0) -> 0 | M40: =K40*(1+L40) -> 0 | N40: Equipe_07 | O40: =H40*M40 -> 0 | R40: =IFERROR(M40*VLOOKUP(N40,$G$3:$T$22,14,0),0) -> 0 | S40: =H40*R40 -> 0 | T40: =R40*(1+Dashboard!$D$35) -> 0 | U40: =H40*T40 -> 0 | X40: =SUMIFS(EZ40:FK40,$EZ$28:$FK$28,">=19",$EZ$28:$FK$28,"<=30") -> 0 | AA40: Serviço | AB40: =X40*(1-Y40) -> 0 | AC40: =H40*AB40 -> 0 | AF40: {=IFERROR(INDEX('Tabela ICMS'!$E$5:$AF$32,Tarefas!B40,Tarefas!C40),0)} -> 0 | AG40: =IF(AA40="FD",(Dashboard!$D$43+Dashboard!$D$44),(Dashboard!$D$30+Dashboard!$D$31)) -> 0.0365 | AH40: =IF(AA40="FD",(Dashboard!$D$46),(Dashboard!$D$33)) -> 0 | AI40: =IF(AA40="FD",(Dashboard!$D$45),(Dashboard!$D$32)) -> 0.05 | AM40: =IF(AA40="FD",AB40*(1+Dashboard!$D$48),AB40*(1+Dashboard!$D$35)) -> 0 | AN40: =H40*AM40 -> 0 | AQ40: =T40 -> 0 | AR40: =AM40 -> 0 | AS40: =ROUND(T40+AM40,2) -> 0 | AT40: =ROUND(U40+AN40,2) -> 0 | AU40: =IFERROR(AT40/$AT$28,0) -> 0 | AZ40: =SUM(BA40:BC40) -> 0 | BA40: =(Dashboard!$D$30+Dashboard!$D$31)*U40 -> 0 | BB40: =Dashboard!$D$33*U40 -> 0 | BC40: =Dashboard!$D$32*U40 -> 0 | BE40: =SUM(BF40:BK40) -> 0 | BF40: =AF40*$AN40 -> 0 | BG40: =IF(AA40="FD",($AN40-$AC40)*AG40,AG40*$AN40) -> 0 | BH40: =IF(AB40="FD",($AN40-$AC40)*AH40,AH40*$AN40) -> 0 | BI40: =IF(AC40="FD",($AN40-$AC40)*AI40,AI40*$AN40) -> 0 | BJ40: =IF(AD40="FD",($AN40-$AC40)*AJ40,AJ40*$AN40) -> 0 | BK40: =IF(AE40="FD",($AN40-$AC40)*AK40,AK40*$AN40) -> 0 | BQ40: 0 | BR40: =22*0.05 -> 1.1 | BS40: 8.8 | BT40: =BQ40*BR40*BS40 -> 0 | BU40: 0 | BV40: 22 | BW40: 8.8 | BX40: =BU40*BV40*BW40 -> 0 | BZ40: 0 | CA40: 22 | CB40: 8.8 | CC40: =BZ40*CA40*CB40 -> 0 | CE40: 0 | CF40: 22 | CG40: 8.8 | CH40: =CE40*CF40*CG40 -> 0 | CI40: 0 | CJ40: 22 | CK40: 8.8 | CL40: =CI40*CJ40*CK40 -> 0 | CM40: 0 | CN40: 22 | CO40: 8.8 | CP40: =CM40*CN40*CO40 -> 0 | CR40: 0 | CS40: 22 | CT40: 8.8 | CU40: =CR40*CS40*CT40 -> 0 | CV40: 0 | CW40: 22 | CX40: 8.8 | CY40: =CV40*CW40*CX40 -> 0 | CZ40: 0 | DA40: 22 | DB40: 8.8 | DC40: =CZ40*DA40*DB40 -> 0 | DE40: 0 | DF40: 22 | DG40: 8.8 | DH40: =DE40*DF40*DG40 -> 0 | DI40: 0 | DJ40: 22 | DK40: 8.8 | DL40: =DI40*DJ40*DK40 -> 0 | DM40: 0 | DN40: 22 | DO40: 8.8 | DP40: =DM40*DN40*DO40 -> 0 | DR40: 0 | DS40: 22 | DT40: 8.8 | DU40: =DR40*DS40*DT40 -> 0 | DV40: 0 | DW40: 22 | DX40: 8.8 | DY40: =DV40*DW40*DX40 -> 0 | DZ40: 0 | EA40: 22 | EB40: 8.8 | EC40: =DZ40*EA40*EB40 -> 0 | EE40: 0 | EF40: 22 | EG40: 8.8 | EH40: =EE40*EF40*EG40 -> 0 | EI40: 0 | EJ40: 22 | EK40: 8.8 | EL40: =EI40*EJ40*EK40 -> 0 | EM40: 0 | EN40: 22 | EO40: 8.8 | EP40: =EM40*EN40*EO40 -> 0 | EQ40: 0 | ER40: 22 | ES40: 8.8 | ET40: =EQ40*ER40*ES40 -> 0 | EU40: 0 | EV40: 22 | EW40: 8.8 | EX40: =EU40*EV40*EW40 -> 0 | EZ40: 0
B41: =IFERROR(VLOOKUP(AE41,'Tabela ICMS'!$C$5:$D$32,2,0),"") | C41: =IFERROR(HLOOKUP(Dashboard!$F$9,'Tabela ICMS'!$E$3:$AF$4,2,0),"") -> 25 | E41: 9 | F41: Engenheiro de Segurança - 5% - Considerado equipe diluida nas linhas com 10 meses | G41: mês | H41: =HISTOGRAMA!C17 -> 10 | K41: =SUMIFS(BT41:FK41,$BT$28:$FK$28,">=1",$BT$28:$FK$28,"<=18") -> 0 | L41: =IFERROR(_xlfn.XLOOKUP(N41,$G$3:$G$22,$L$3:$L$22),0) -> 0 | M41: =K41*(1+L41) -> 0 | N41: Equipe_08 | O41: =H41*M41 -> 0 | R41: =IFERROR(M41*VLOOKUP(N41,$G$3:$T$22,14,0),0) -> 0 | S41: =H41*R41 -> 0 | T41: =R41*(1+Dashboard!$D$35) -> 0 | U41: =H41*T41 -> 0 | X41: =SUMIFS(EZ41:FK41,$EZ$28:$FK$28,">=19",$EZ$28:$FK$28,"<=30") -> 0 | AA41: Serviço | AB41: =X41*(1-Y41) -> 0 | AC41: =H41*AB41 -> 0 | AF41: {=IFERROR(INDEX('Tabela ICMS'!$E$5:$AF$32,Tarefas!B41,Tarefas!C41),0)} -> 0 | AG41: =IF(AA41="FD",(Dashboard!$D$43+Dashboard!$D$44),(Dashboard!$D$30+Dashboard!$D$31)) -> 0.0365 | AH41: =IF(AA41="FD",(Dashboard!$D$46),(Dashboard!$D$33)) -> 0 | AI41: =IF(AA41="FD",(Dashboard!$D$45),(Dashboard!$D$32)) -> 0.05 | AM41: =IF(AA41="FD",AB41*(1+Dashboard!$D$48),AB41*(1+Dashboard!$D$35)) -> 0 | AN41: =H41*AM41 -> 0 | AQ41: =T41 -> 0 | AR41: =AM41 -> 0 | AS41: =ROUND(T41+AM41,2) -> 0 | AT41: =ROUND(U41+AN41,2) -> 0 | AU41: =IFERROR(AT41/$AT$28,0) -> 0 | AZ41: =SUM(BA41:BC41) -> 0 | BA41: =(Dashboard!$D$30+Dashboard!$D$31)*U41 -> 0 | BB41: =Dashboard!$D$33*U41 -> 0 | BC41: =Dashboard!$D$32*U41 -> 0 | BE41: =SUM(BF41:BK41) -> 0 | BF41: =AF41*$AN41 -> 0 | BG41: =IF(AA41="FD",($AN41-$AC41)*AG41,AG41*$AN41) -> 0 | BH41: =IF(AB41="FD",($AN41-$AC41)*AH41,AH41*$AN41) -> 0 | BI41: =IF(AC41="FD",($AN41-$AC41)*AI41,AI41*$AN41) -> 0 | BJ41: =IF(AD41="FD",($AN41-$AC41)*AJ41,AJ41*$AN41) -> 0 | BK41: =IF(AE41="FD",($AN41-$AC41)*AK41,AK41*$AN41) -> 0 | BQ41: 0 | BR41: 22 | BS41: 8.8 | BT41: =BQ41*BR41*BS41 -> 0 | BU41: 0 | BV41: 22 | BW41: 8.8 | BX41: =BU41*BV41*BW41 -> 0 | BZ41: 0 | CA41: 22 | CB41: 8.8 | CC41: =BZ41*CA41*CB41 -> 0 | CE41: 0 | CF41: 22 | CG41: 8.8 | CH41: =CE41*CF41*CG41 -> 0 | CI41: 0 | CJ41: =0.05*22 -> 1.1 | CK41: 8.8 | CL41: =CI41*CJ41*CK41 -> 0 | CM41: 0 | CN41: 22 | CO41: 8.8 | CP41: =CM41*CN41*CO41 -> 0 | CR41: 0 | CS41: 22 | CT41: 8.8 | CU41: =CR41*CS41*CT41 -> 0 | CV41: 0 | CW41: 22 | CX41: 8.8 | CY41: =CV41*CW41*CX41 -> 0 | CZ41: 0 | DA41: 22 | DB41: 8.8 | DC41: =CZ41*DA41*DB41 -> 0 | DE41: 0 | DF41: 22 | DG41: 8.8 | DH41: =DE41*DF41*DG41 -> 0 | DI41: 0 | DJ41: 22 | DK41: 8.8 | DL41: =DI41*DJ41*DK41 -> 0 | DM41: 0 | DN41: 22 | DO41: 8.8 | DP41: =DM41*DN41*DO41 -> 0 | DR41: 0 | DS41: 22 | DT41: 8.8 | DU41: =DR41*DS41*DT41 -> 0 | DV41: 0 | DW41: 22 | DX41: 8.8 | DY41: =DV41*DW41*DX41 -> 0 | DZ41: 0 | EA41: 22 | EB41: 8.8 | EC41: =DZ41*EA41*EB41 -> 0 | EE41: 0 | EF41: 22 | EG41: 8.8 | EH41: =EE41*EF41*EG41 -> 0 | EI41: 0 | EJ41: 22 | EK41: 8.8 | EL41: =EI41*EJ41*EK41 -> 0 | EM41: 0 | EN41: 22 | EO41: 8.8 | EP41: =EM41*EN41*EO41 -> 0 | EQ41: 0 | ER41: 22 | ES41: 8.8 | ET41: =EQ41*ER41*ES41 -> 0 | EU41: 0 | EV41: 22 | EW41: 8.8 | EX41: =EU41*EV41*EW41 -> 0 | EZ41: 0
B42: =IFERROR(VLOOKUP(AE42,'Tabela ICMS'!$C$5:$D$32,2,0),"") | C42: =IFERROR(HLOOKUP(Dashboard!$F$9,'Tabela ICMS'!$E$3:$AF$4,2,0),"") -> 25 | E42: 10 | F42: Coordenador de Arquitetura - Excluso | G42: mês | H42: =HISTOGRAMA!C18 -> 0 | K42: =SUMIFS(BT42:FK42,$BT$28:$FK$28,">=1",$BT$28:$FK$28,"<=18") -> 29.04 | L42: =IFERROR(_xlfn.XLOOKUP(N42,$G$3:$G$22,$L$3:$L$22),0) -> 0 | M42: =K42*(1+L42) -> 29.04 | N42: Equipe_09 | O42: =H42*M42 -> 0 | R42: =IFERROR(M42*VLOOKUP(N42,$G$3:$T$22,14,0),0) -> 0 | S42: =H42*R42 -> 0 | T42: =R42*(1+Dashboard!$D$35) -> 0 | U42: =H42*T42 -> 0 | X42: =SUMIFS(EZ42:FK42,$EZ$28:$FK$28,">=19",$EZ$28:$FK$28,"<=30") -> 0 | AA42: Serviço | AB42: =X42*(1-Y42) -> 0 | AC42: =H42*AB42 -> 0 | AF42: {=IFERROR(INDEX('Tabela ICMS'!$E$5:$AF$32,Tarefas!B42,Tarefas!C42),0)} -> 0 | AG42: =IF(AA42="FD",(Dashboard!$D$43+Dashboard!$D$44),(Dashboard!$D$30+Dashboard!$D$31)) -> 0.0365 | AH42: =IF(AA42="FD",(Dashboard!$D$46),(Dashboard!$D$33)) -> 0 | AI42: =IF(AA42="FD",(Dashboard!$D$45),(Dashboard!$D$32)) -> 0.05 | AM42: =IF(AA42="FD",AB42*(1+Dashboard!$D$48),AB42*(1+Dashboard!$D$35)) -> 0 | AN42: =H42*AM42 -> 0 | AQ42: =T42 -> 0 | AR42: =AM42 -> 0 | AS42: =ROUND(T42+AM42,2) -> 0 | AT42: =ROUND(U42+AN42,2) -> 0 | AU42: =IFERROR(AT42/$AT$28,0) -> 0 | AZ42: =SUM(BA42:BC42) -> 0 | BA42: =(Dashboard!$D$30+Dashboard!$D$31)*U42 -> 0 | BB42: =Dashboard!$D$33*U42 -> 0 | BC42: =Dashboard!$D$32*U42 -> 0 | BE42: =SUM(BF42:BK42) -> 0 | BF42: =AF42*$AN42 -> 0 | BG42: =IF(AA42="FD",($AN42-$AC42)*AG42,AG42*$AN42) -> 0 | BH42: =IF(AB42="FD",($AN42-$AC42)*AH42,AH42*$AN42) -> 0 | BI42: =IF(AC42="FD",($AN42-$AC42)*AI42,AI42*$AN42) -> 0 | BJ42: =IF(AD42="FD",($AN42-$AC42)*AJ42,AJ42*$AN42) -> 0 | BK42: =IF(AE42="FD",($AN42-$AC42)*AK42,AK42*$AN42) -> 0 | BQ42: 0 | BR42: 22 | BS42: 8.8 | BT42: =BQ42*BR42*BS42 -> 0 | BU42: 1 | BV42: =0.15*22 -> 3.3 | BW42: 8.8 | BX42: =BU42*BV42*BW42 -> 29.04 | BZ42: 0 | CA42: 22 | CB42: 8.8 | CC42: =BZ42*CA42*CB42 -> 0 | CE42: 0 | CF42: 22 | CG42: 8.8 | CH42: =CE42*CF42*CG42 -> 0 | CI42: 0 | CJ42: 22 | CK42: 8.8 | CL42: =CI42*CJ42*CK42 -> 0 | CM42: 0 | CN42: 22 | CO42: 8.8 | CP42: =CM42*CN42*CO42 -> 0 | CR42: 0 | CS42: 22 | CT42: 8.8 | CU42: =CR42*CS42*CT42 -> 0 | CV42: 0 | CW42: 22 | CX42: 8.8 | CY42: =CV42*CW42*CX42 -> 0 | CZ42: 0 | DA42: 22 | DB42: 8.8 | DC42: =CZ42*DA42*DB42 -> 0 | DE42: 0 | DF42: 22 | DG42: 8.8 | DH42: =DE42*DF42*DG42 -> 0 | DI42: 0 | DJ42: 22 | DK42: 8.8 | DL42: =DI42*DJ42*DK42 -> 0 | DM42: 0 | DN42: 22 | DO42: 8.8 | DP42: =DM42*DN42*DO42 -> 0 | DR42: 0 | DS42: 22 | DT42: 8.8 | DU42: =DR42*DS42*DT42 -> 0 | DV42: 0 | DW42: 22 | DX42: 8.8 | DY42: =DV42*DW42*DX42 -> 0 | DZ42: 0 | EA42: 22 | EB42: 8.8 | EC42: =DZ42*EA42*EB42 -> 0 | EE42: 0 | EF42: 22 | EG42: 8.8 | EH42: =EE42*EF42*EG42 -> 0 | EI42: 0 | EJ42: 22 | EK42: 8.8 | EL42: =EI42*EJ42*EK42 -> 0 | EM42: 0 | EN42: 22 | EO42: 8.8 | EP42: =EM42*EN42*EO42 -> 0 | EQ42: 0 | ER42: 22 | ES42: 8.8 | ET42: =EQ42*ER42*ES42 -> 0 | EU42: 0 | EV42: 22 | EW42: 8.8 | EX42: =EU42*EV42*EW42 -> 0 | EZ42: 0
B43: =IFERROR(VLOOKUP(AE43,'Tabela ICMS'!$C$5:$D$32,2,0),"") | C43: =IFERROR(HLOOKUP(Dashboard!$F$9,'Tabela ICMS'!$E$3:$AF$4,2,0),"") -> 25 | E43: 11 | F43: N/A | G43: mês | H43: =HISTOGRAMA!C19 -> 0 | K43: =SUMIFS(BT43:FK43,$BT$28:$FK$28,">=1",$BT$28:$FK$28,"<=18") -> 0 | L43: =IFERROR(_xlfn.XLOOKUP(N43,$G$3:$G$22,$L$3:$L$22),0) -> 0 | M43: =K43*(1+L43) -> 0 | N43: Equipe_10 | O43: =H43*M43 -> 0 | R43: =IFERROR(M43*VLOOKUP(N43,$G$3:$T$22,14,0),0) -> 0 | S43: =H43*R43 -> 0 | T43: =R43*(1+Dashboard!$D$35) -> 0 | U43: =H43*T43 -> 0 | X43: =SUMIFS(EZ43:FK43,$EZ$28:$FK$28,">=19",$EZ$28:$FK$28,"<=30") -> 0 | AA43: Serviço | AB43: =X43*(1-Y43) -> 0 | AC43: =H43*AB43 -> 0 | AF43: {=IFERROR(INDEX('Tabela ICMS'!$E$5:$AF$32,Tarefas!B43,Tarefas!C43),0)} -> 0 | AG43: =IF(AA43="FD",(Dashboard!$D$43+Dashboard!$D$44),(Dashboard!$D$30+Dashboard!$D$31)) -> 0.0365 | AH43: =IF(AA43="FD",(Dashboard!$D$46),(Dashboard!$D$33)) -> 0 | AI43: =IF(AA43="FD",(Dashboard!$D$45),(Dashboard!$D$32)) -> 0.05 | AM43: =IF(AA43="FD",AB43*(1+Dashboard!$D$48),AB43*(1+Dashboard!$D$35)) -> 0 | AN43: =H43*AM43 -> 0 | AQ43: =T43 -> 0 | AR43: =AM43 -> 0 | AS43: =ROUND(T43+AM43,2) -> 0 | AT43: =ROUND(U43+AN43,2) -> 0 | AU43: =IFERROR(AT43/$AT$28,0) -> 0 | AZ43: =SUM(BA43:BC43) -> 0 | BA43: =(Dashboard!$D$30+Dashboard!$D$31)*U43 -> 0 | BB43: =Dashboard!$D$33*U43 -> 0 | BC43: =Dashboard!$D$32*U43 -> 0 | BE43: =SUM(BF43:BK43) -> 0 | BF43: =AF43*$AN43 -> 0 | BG43: =IF(AA43="FD",($AN43-$AC43)*AG43,AG43*$AN43) -> 0 | BH43: =IF(AB43="FD",($AN43-$AC43)*AH43,AH43*$AN43) -> 0 | BI43: =IF(AC43="FD",($AN43-$AC43)*AI43,AI43*$AN43) -> 0 | BJ43: =IF(AD43="FD",($AN43-$AC43)*AJ43,AJ43*$AN43) -> 0 | BK43: =IF(AE43="FD",($AN43-$AC43)*AK43,AK43*$AN43) -> 0 | BQ43: 0 | BR43: 22 | BS43: 8.8 | BT43: =BQ43*BR43*BS43 -> 0 | BU43: 0 | BV43: 22 | BW43: 8.8 | BX43: =BU43*BV43*BW43 -> 0 | BZ43: 0 | CA43: 22 | CB43: 8.8 | CC43: =BZ43*CA43*CB43 -> 0 | CE43: 0 | CF43: 22 | CG43: 8.8 | CH43: =CE43*CF43*CG43 -> 0 | CI43: 0 | CJ43: 22 | CK43: 8.8 | CL43: =CI43*CJ43*CK43 -> 0 | CM43: 0 | CN43: 22 | CO43: 8.8 | CP43: =CM43*CN43*CO43 -> 0 | CR43: 0 | CS43: 22 | CT43: 8.8 | CU43: =CR43*CS43*CT43 -> 0 | CV43: 0 | CW43: 22 | CX43: 8.8 | CY43: =CV43*CW43*CX43 -> 0 | CZ43: 0 | DA43: 22 | DB43: 8.8 | DC43: =CZ43*DA43*DB43 -> 0 | DE43: 0 | DF43: 22 | DG43: 8.8 | DH43: =DE43*DF43*DG43 -> 0 | DI43: 0 | DJ43: 22 | DK43: 8.8 | DL43: =DI43*DJ43*DK43 -> 0 | DM43: 0 | DN43: 22 | DO43: 8.8 | DP43: =DM43*DN43*DO43 -> 0 | DR43: 0 | DS43: 22 | DT43: 8.8 | DU43: =DR43*DS43*DT43 -> 0 | DV43: 0 | DW43: 22 | DX43: 8.8 | DY43: =DV43*DW43*DX43 -> 0 | DZ43: 0 | EA43: 22 | EB43: 8.8 | EC43: =DZ43*EA43*EB43 -> 0 | EE43: 0 | EF43: 22 | EG43: 8.8 | EH43: =EE43*EF43*EG43 -> 0 | EI43: 0 | EJ43: 22 | EK43: 8.8 | EL43: =EI43*EJ43*EK43 -> 0 | EM43: 0 | EN43: 22 | EO43: 8.8 | EP43: =EM43*EN43*EO43 -> 0 | EQ43: 0 | ER43: 22 | ES43: 8.8 | ET43: =EQ43*ER43*ES43 -> 0 | EU43: 0 | EV43: 22 | EW43: 8.8 | EX43: =EU43*EV43*EW43 -> 0
B44: =IFERROR(VLOOKUP(AE44,'Tabela ICMS'!$C$5:$D$32,2,0),"") | C44: =IFERROR(HLOOKUP(Dashboard!$F$9,'Tabela ICMS'!$E$3:$AF$4,2,0),"") -> 25 | E44: 12 | F44: N/A | G44: mês | H44: =HISTOGRAMA!C20 -> 0 | K44: =SUMIFS(BT44:FK44,$BT$28:$FK$28,">=1",$BT$28:$FK$28,"<=18") -> 0 | L44: =IFERROR(_xlfn.XLOOKUP(N44,$G$3:$G$22,$L$3:$L$22),0) -> 0 | M44: =K44*(1+L44) -> 0 | N44: Equipe_11 | O44: =H44*M44 -> 0 | R44: =IFERROR(M44*VLOOKUP(N44,$G$3:$T$22,14,0),0) -> 0 | S44: =H44*R44 -> 0 | T44: =R44*(1+Dashboard!$D$35) -> 0 | U44: =H44*T44 -> 0 | X44: =SUMIFS(EZ44:FK44,$EZ$28:$FK$28,">=19",$EZ$28:$FK$28,"<=30") -> 0 | AA44: Serviço | AB44: =X44*(1-Y44) -> 0 | AC44: =H44*AB44 -> 0 | AF44: {=IFERROR(INDEX('Tabela ICMS'!$E$5:$AF$32,Tarefas!B44,Tarefas!C44),0)} -> 0 | AG44: =IF(AA44="FD",(Dashboard!$D$43+Dashboard!$D$44),(Dashboard!$D$30+Dashboard!$D$31)) -> 0.0365 | AH44: =IF(AA44="FD",(Dashboard!$D$46),(Dashboard!$D$33)) -> 0 | AI44: =IF(AA44="FD",(Dashboard!$D$45),(Dashboard!$D$32)) -> 0.05 | AM44: =IF(AA44="FD",AB44*(1+Dashboard!$D$48),AB44*(1+Dashboard!$D$35)) -> 0 | AN44: =H44*AM44 -> 0 | AQ44: =T44 -> 0 | AR44: =AM44 -> 0 | AS44: =ROUND(T44+AM44,2) -> 0 | AT44: =ROUND(U44+AN44,2) -> 0 | AU44: =IFERROR(AT44/$AT$28,0) -> 0 | AZ44: =SUM(BA44:BC44) -> 0 | BA44: =(Dashboard!$D$30+Dashboard!$D$31)*U44 -> 0 | BB44: =Dashboard!$D$33*U44 -> 0 | BC44: =Dashboard!$D$32*U44 -> 0 | BE44: =SUM(BF44:BK44) -> 0 | BF44: =AF44*$AN44 -> 0 | BG44: =IF(AA44="FD",($AN44-$AC44)*AG44,AG44*$AN44) -> 0 | BH44: =IF(AB44="FD",($AN44-$AC44)*AH44,AH44*$AN44) -> 0 | BI44: =IF(AC44="FD",($AN44-$AC44)*AI44,AI44*$AN44) -> 0 | BJ44: =IF(AD44="FD",($AN44-$AC44)*AJ44,AJ44*$AN44) -> 0 | BK44: =IF(AE44="FD",($AN44-$AC44)*AK44,AK44*$AN44) -> 0 | BQ44: 0 | BR44: 22 | BS44: 8.8 | BT44: =BQ44*BR44*BS44 -> 0 | BU44: 0 | BV44: 22 | BW44: 8.8 | BX44: =BU44*BV44*BW44 -> 0 | BZ44: 0 | CA44: 22 | CB44: 8.8 | CC44: =BZ44*CA44*CB44 -> 0 | CE44: 0 | CF44: 22 | CG44: 8.8 | CH44: =CE44*CF44*CG44 -> 0 | CI44: 0 | CJ44: 22 | CK44: 8.8 | CL44: =CI44*CJ44*CK44 -> 0 | CM44: 0 | CN44: 22 | CO44: 8.8 | CP44: =CM44*CN44*CO44 -> 0 | CR44: 0 | CS44: 22 | CT44: 8.8 | CU44: =CR44*CS44*CT44 -> 0 | CV44: 0 | CW44: 22 | CX44: 8.8 | CY44: =CV44*CW44*CX44 -> 0 | CZ44: 0 | DA44: 22 | DB44: 8.8 | DC44: =CZ44*DA44*DB44 -> 0 | DE44: 0 | DF44: 22 | DG44: 8.8 | DH44: =DE44*DF44*DG44 -> 0 | DI44: 0 | DJ44: 22 | DK44: 8.8 | DL44: =DI44*DJ44*DK44 -> 0 | DM44: 0 | DN44: 22 | DO44: 8.8 | DP44: =DM44*DN44*DO44 -> 0 | DR44: 0 | DS44: 22 | DT44: 8.8 | DU44: =DR44*DS44*DT44 -> 0 | DV44: 0 | DW44: 22 | DX44: 8.8 | DY44: =DV44*DW44*DX44 -> 0 | DZ44: 0 | EA44: 22 | EB44: 8.8 | EC44: =DZ44*EA44*EB44 -> 0 | EE44: 0 | EF44: 22 | EG44: 8.8 | EH44: =EE44*EF44*EG44 -> 0 | EI44: 0 | EJ44: 22 | EK44: 8.8 | EL44: =EI44*EJ44*EK44 -> 0 | EM44: 0 | EN44: 22 | EO44: 8.8 | EP44: =EM44*EN44*EO44 -> 0 | EQ44: 0 | ER44: 22 | ES44: 8.8 | ET44: =EQ44*ER44*ES44 -> 0 | EU44: 0 | EV44: 22 | EW44: 8.8 | EX44: =EU44*EV44*EW44 -> 0
B45: =IFERROR(VLOOKUP(AE45,'Tabela ICMS'!$C$5:$D$32,2,0),"") | C45: =IFERROR(HLOOKUP(Dashboard!$F$9,'Tabela ICMS'!$E$3:$AF$4,2,0),"") -> 25 | E45: 13 | F45: N/A | G45: mês | H45: =HISTOGRAMA!C21 -> 0 | K45: =SUMIFS(BT45:FK45,$BT$28:$FK$28,">=1",$BT$28:$FK$28,"<=18") -> 0 | L45: =IFERROR(_xlfn.XLOOKUP(N45,$G$3:$G$22,$L$3:$L$22),0) -> 0 | M45: =K45*(1+L45) -> 0 | N45: Equipe_12 | O45: =H45*M45 -> 0 | R45: =IFERROR(M45*VLOOKUP(N45,$G$3:$T$22,14,0),0) -> 0 | S45: =H45*R45 -> 0 | T45: =R45*(1+Dashboard!$D$35) -> 0 | U45: =H45*T45 -> 0 | X45: =SUMIFS(EZ45:FK45,$EZ$28:$FK$28,">=19",$EZ$28:$FK$28,"<=30") -> 0 | AA45: Serviço | AB45: =X45*(1-Y45) -> 0 | AC45: =H45*AB45 -> 0 | AF45: {=IFERROR(INDEX('Tabela ICMS'!$E$5:$AF$32,Tarefas!B45,Tarefas!C45),0)} -> 0 | AG45: =IF(AA45="FD",(Dashboard!$D$43+Dashboard!$D$44),(Dashboard!$D$30+Dashboard!$D$31)) -> 0.0365 | AH45: =IF(AA45="FD",(Dashboard!$D$46),(Dashboard!$D$33)) -> 0 | AI45: =IF(AA45="FD",(Dashboard!$D$45),(Dashboard!$D$32)) -> 0.05 | AM45: =IF(AA45="FD",AB45*(1+Dashboard!$D$48),AB45*(1+Dashboard!$D$35)) -> 0 | AN45: =H45*AM45 -> 0 | AQ45: =T45 -> 0 | AR45: =AM45 -> 0 | AS45: =ROUND(T45+AM45,2) -> 0 | AT45: =ROUND(U45+AN45,2) -> 0 | AU45: =IFERROR(AT45/$AT$28,0) -> 0 | AZ45: =SUM(BA45:BC45) -> 0 | BA45: =(Dashboard!$D$30+Dashboard!$D$31)*U45 -> 0 | BB45: =Dashboard!$D$33*U45 -> 0 | BC45: =Dashboard!$D$32*U45 -> 0 | BE45: =SUM(BF45:BK45) -> 0 | BF45: =AF45*$AN45 -> 0 | BG45: =IF(AA45="FD",($AN45-$AC45)*AG45,AG45*$AN45) -> 0 | BH45: =IF(AB45="FD",($AN45-$AC45)*AH45,AH45*$AN45) -> 0 | BI45: =IF(AC45="FD",($AN45-$AC45)*AI45,AI45*$AN45) -> 0 | BJ45: =IF(AD45="FD",($AN45-$AC45)*AJ45,AJ45*$AN45) -> 0 | BK45: =IF(AE45="FD",($AN45-$AC45)*AK45,AK45*$AN45) -> 0 | BQ45: 0 | BR45: 22 | BS45: 8.8 | BT45: =BQ45*BR45*BS45 -> 0 | BU45: 0 | BV45: 22 | BW45: 8.8 | BX45: =BU45*BV45*BW45 -> 0 | BZ45: 0 | CA45: 22 | CB45: 8.8 | CC45: =BZ45*CA45*CB45 -> 0 | CE45: 0 | CF45: 22 | CG45: 8.8 | CH45: =CE45*CF45*CG45 -> 0 | CI45: 0 | CJ45: 22 | CK45: 8.8 | CL45: =CI45*CJ45*CK45 -> 0 | CM45: 0 | CN45: 22 | CO45: 8.8 | CP45: =CM45*CN45*CO45 -> 0 | CR45: 0 | CS45: 22 | CT45: 8.8 | CU45: =CR45*CS45*CT45 -> 0 | CV45: 0 | CW45: 22 | CX45: 8.8 | CY45: =CV45*CW45*CX45 -> 0 | CZ45: 0 | DA45: 22 | DB45: 8.8 | DC45: =CZ45*DA45*DB45 -> 0 | DE45: 0 | DF45: 22 | DG45: 8.8 | DH45: =DE45*DF45*DG45 -> 0 | DI45: 0 | DJ45: 22 | DK45: 8.8 | DL45: =DI45*DJ45*DK45 -> 0 | DM45: 0 | DN45: 22 | DO45: 8.8 | DP45: =DM45*DN45*DO45 -> 0 | DR45: 0 | DS45: 22 | DT45: 8.8 | DU45: =DR45*DS45*DT45 -> 0 | DV45: 0 | DW45: 22 | DX45: 8.8 | DY45: =DV45*DW45*DX45 -> 0 | DZ45: 0 | EA45: 22 | EB45: 8.8 | EC45: =DZ45*EA45*EB45 -> 0 | EE45: 0 | EF45: 22 | EG45: 8.8 | EH45: =EE45*EF45*EG45 -> 0 | EI45: 0 | EJ45: 22 | EK45: 8.8 | EL45: =EI45*EJ45*EK45 -> 0 | EM45: 0 | EN45: 22 | EO45: 8.8 | EP45: =EM45*EN45*EO45 -> 0 | EQ45: 0 | ER45: 22 | ES45: 8.8 | ET45: =EQ45*ER45*ES45 -> 0 | EU45: 0 | EV45: 22 | EW45: 8.8 | EX45: =EU45*EV45*EW45 -> 0
B46: =IFERROR(VLOOKUP(AE46,'Tabela ICMS'!$C$5:$D$32,2,0),"") | C46: =IFERROR(HLOOKUP(Dashboard!$F$9,'Tabela ICMS'!$E$3:$AF$4,2,0),"") -> 25 | E46: 14 | F46: N/A | G46: mês | H46: =HISTOGRAMA!C22 -> 0 | K46: =SUMIFS(BT46:FK46,$BT$28:$FK$28,">=1",$BT$28:$FK$28,"<=18") -> 0 | L46: =IFERROR(_xlfn.XLOOKUP(N46,$G$3:$G$22,$L$3:$L$22),0) -> 0 | M46: =K46*(1+L46) -> 0 | N46: Equipe_13 | O46: =H46*M46 -> 0 | R46: =IFERROR(M46*VLOOKUP(N46,$G$3:$T$22,14,0),0) -> 0 | S46: =H46*R46 -> 0 | T46: =R46*(1+Dashboard!$D$35) -> 0 | U46: =H46*T46 -> 0 | X46: =SUMIFS(EZ46:FK46,$EZ$28:$FK$28,">=19",$EZ$28:$FK$28,"<=30") -> 0 | AA46: Serviço | AB46: =X46*(1-Y46) -> 0 | AC46: =H46*AB46 -> 0 | AF46: {=IFERROR(INDEX('Tabela ICMS'!$E$5:$AF$32,Tarefas!B46,Tarefas!C46),0)} -> 0 | AG46: =IF(AA46="FD",(Dashboard!$D$43+Dashboard!$D$44),(Dashboard!$D$30+Dashboard!$D$31)) -> 0.0365 | AH46: =IF(AA46="FD",(Dashboard!$D$46),(Dashboard!$D$33)) -> 0 | AI46: =IF(AA46="FD",(Dashboard!$D$45),(Dashboard!$D$32)) -> 0.05 | AM46: =IF(AA46="FD",AB46*(1+Dashboard!$D$48),AB46*(1+Dashboard!$D$35)) -> 0 | AN46: =H46*AM46 -> 0 | AQ46: =T46 -> 0 | AR46: =AM46 -> 0 | AS46: =ROUND(T46+AM46,2) -> 0 | AT46: =ROUND(U46+AN46,2) -> 0 | AU46: =IFERROR(AT46/$AT$28,0) -> 0 | AZ46: =SUM(BA46:BC46) -> 0 | BA46: =(Dashboard!$D$30+Dashboard!$D$31)*U46 -> 0 | BB46: =Dashboard!$D$33*U46 -> 0 | BC46: =Dashboard!$D$32*U46 -> 0 | BE46: =SUM(BF46:BK46) -> 0 | BF46: =AF46*$AN46 -> 0 | BG46: =IF(AA46="FD",($AN46-$AC46)*AG46,AG46*$AN46) -> 0 | BH46: =IF(AB46="FD",($AN46-$AC46)*AH46,AH46*$AN46) -> 0 | BI46: =IF(AC46="FD",($AN46-$AC46)*AI46,AI46*$AN46) -> 0 | BJ46: =IF(AD46="FD",($AN46-$AC46)*AJ46,AJ46*$AN46) -> 0 | BK46: =IF(AE46="FD",($AN46-$AC46)*AK46,AK46*$AN46) -> 0 | BQ46: 0 | BR46: 22 | BS46: 8.8 | BT46: =BQ46*BR46*BS46 -> 0 | BU46: 0 | BV46: 22 | BW46: 8.8 | BX46: =BU46*BV46*BW46 -> 0 | BZ46: 0 | CA46: 22 | CB46: 8.8 | CC46: =BZ46*CA46*CB46 -> 0 | CE46: 0 | CF46: 22 | CG46: 8.8 | CH46: =CE46*CF46*CG46 -> 0 | CI46: 0 | CJ46: 22 | CK46: 8.8 | CL46: =CI46*CJ46*CK46 -> 0 | CM46: 0 | CN46: 22 | CO46: 8.8 | CP46: =CM46*CN46*CO46 -> 0 | CR46: 0 | CS46: 22 | CT46: 8.8 | CU46: =CR46*CS46*CT46 -> 0 | CV46: 0 | CW46: 22 | CX46: 8.8 | CY46: =CV46*CW46*CX46 -> 0 | CZ46: 0 | DA46: 22 | DB46: 8.8 | DC46: =CZ46*DA46*DB46 -> 0 | DE46: 0 | DF46: 22 | DG46: 8.8 | DH46: =DE46*DF46*DG46 -> 0 | DI46: 0 | DJ46: 22 | DK46: 8.8 | DL46: =DI46*DJ46*DK46 -> 0 | DM46: 0 | DN46: 22 | DO46: 8.8 | DP46: =DM46*DN46*DO46 -> 0 | DR46: 0 | DS46: 22 | DT46: 8.8 | DU46: =DR46*DS46*DT46 -> 0 | DV46: 0 | DW46: 22 | DX46: 8.8 | DY46: =DV46*DW46*DX46 -> 0 | DZ46: 0 | EA46: 22 | EB46: 8.8 | EC46: =DZ46*EA46*EB46 -> 0 | EE46: 0 | EF46: 22 | EG46: 8.8 | EH46: =EE46*EF46*EG46 -> 0 | EI46: 0 | EJ46: 22 | EK46: 8.8 | EL46: =EI46*EJ46*EK46 -> 0 | EM46: 0 | EN46: 22 | EO46: 8.8 | EP46: =EM46*EN46*EO46 -> 0 | EQ46: 0 | ER46: 22 | ES46: 8.8 | ET46: =EQ46*ER46*ES46 -> 0 | EU46: 0 | EV46: 22 | EW46: 8.8 | EX46: =EU46*EV46*EW46 -> 0
B47: =IFERROR(VLOOKUP(AE47,'Tabela ICMS'!$C$5:$D$32,2,0),"") | C47: =IFERROR(HLOOKUP(Dashboard!$F$9,'Tabela ICMS'!$E$3:$AF$4,2,0),"") -> 25 | E47: 15 | F47: N/A | G47: mês | H47: =HISTOGRAMA!C24 -> 0 | K47: =SUMIFS(BT47:FK47,$BT$28:$FK$28,">=1",$BT$28:$FK$28,"<=18") -> 0 | L47: =IFERROR(_xlfn.XLOOKUP(N47,$G$3:$G$22,$L$3:$L$22),0) -> 0 | M47: =K47*(1+L47) -> 0 | N47: Equipe_14 | O47: =H47*M47 -> 0 | R47: =IFERROR(M47*VLOOKUP(N47,$G$3:$T$22,14,0),0) -> 0 | S47: =H47*R47 -> 0 | T47: =R47*(1+Dashboard!$D$35) -> 0 | U47: =H47*T47 -> 0 | X47: =SUMIFS(EZ47:FK47,$EZ$28:$FK$28,">=19",$EZ$28:$FK$28,"<=30") -> 0 | AA47: Serviço | AB47: =X47*(1-Y47) -> 0 | AC47: =H47*AB47 -> 0 | AF47: {=IFERROR(INDEX('Tabela ICMS'!$E$5:$AF$32,Tarefas!B47,Tarefas!C47),0)} -> 0 | AG47: =IF(AA47="FD",(Dashboard!$D$43+Dashboard!$D$44),(Dashboard!$D$30+Dashboard!$D$31)) -> 0.0365 | AH47: =IF(AA47="FD",(Dashboard!$D$46),(Dashboard!$D$33)) -> 0 | AI47: =IF(AA47="FD",(Dashboard!$D$45),(Dashboard!$D$32)) -> 0.05 | AM47: =IF(AA47="FD",AB47*(1+Dashboard!$D$48),AB47*(1+Dashboard!$D$35)) -> 0 | AN47: =H47*AM47 -> 0 | AQ47: =T47 -> 0 | AR47: =AM47 -> 0 | AS47: =ROUND(T47+AM47,2) -> 0 | AT47: =ROUND(U47+AN47,2) -> 0 | AU47: =IFERROR(AT47/$AT$28,0) -> 0 | AZ47: =SUM(BA47:BC47) -> 0 | BA47: =(Dashboard!$D$30+Dashboard!$D$31)*U47 -> 0 | BB47: =Dashboard!$D$33*U47 -> 0 | BC47: =Dashboard!$D$32*U47 -> 0 | BE47: =SUM(BF47:BK47) -> 0 | BF47: =AF47*$AN47 -> 0 | BG47: =IF(AA47="FD",($AN47-$AC47)*AG47,AG47*$AN47) -> 0 | BH47: =IF(AB47="FD",($AN47-$AC47)*AH47,AH47*$AN47) -> 0 | BI47: =IF(AC47="FD",($AN47-$AC47)*AI47,AI47*$AN47) -> 0 | BJ47: =IF(AD47="FD",($AN47-$AC47)*AJ47,AJ47*$AN47) -> 0 | BK47: =IF(AE47="FD",($AN47-$AC47)*AK47,AK47*$AN47) -> 0 | BQ47: 0 | BR47: 22 | BS47: 8.8 | BT47: =BQ47*BR47*BS47 -> 0 | BU47: 0 | BV47: 22 | BW47: 8.8 | BX47: =BU47*BV47*BW47 -> 0 | BZ47: 0 | CA47: 22 | CB47: 8.8 | CC47: =BZ47*CA47*CB47 -> 0 | CE47: 0 | CF47: 22 | CG47: 8.8 | CH47: =CE47*CF47*CG47 -> 0 | CI47: 0 | CJ47: 22 | CK47: 8.8 | CL47: =CI47*CJ47*CK47 -> 0 | CM47: 0 | CN47: 22 | CO47: 8.8 | CP47: =CM47*CN47*CO47 -> 0 | CR47: 0 | CS47: 22 | CT47: 8.8 | CU47: =CR47*CS47*CT47 -> 0 | CV47: 0 | CW47: 22 | CX47: 8.8 | CY47: =CV47*CW47*CX47 -> 0 | CZ47: 0 | DA47: 22 | DB47: 8.8 | DC47: =CZ47*DA47*DB47 -> 0 | DE47: 0 | DF47: 22 | DG47: 8.8 | DH47: =DE47*DF47*DG47 -> 0 | DI47: 0 | DJ47: 22 | DK47: 8.8 | DL47: =DI47*DJ47*DK47 -> 0 | DM47: 0 | DN47: 22 | DO47: 8.8 | DP47: =DM47*DN47*DO47 -> 0 | DR47: 0 | DS47: 22 | DT47: 8.8 | DU47: =DR47*DS47*DT47 -> 0 | DV47: 0 | DW47: 22 | DX47: 8.8 | DY47: =DV47*DW47*DX47 -> 0 | DZ47: 0 | EA47: 22 | EB47: 8.8 | EC47: =DZ47*EA47*EB47 -> 0 | EE47: 0 | EF47: 22 | EG47: 8.8 | EH47: =EE47*EF47*EG47 -> 0 | EI47: 0 | EJ47: 22 | EK47: 8.8 | EL47: =EI47*EJ47*EK47 -> 0 | EM47: 0 | EN47: 22 | EO47: 8.8 | EP47: =EM47*EN47*EO47 -> 0 | EQ47: 0 | ER47: 22 | ES47: 8.8 | ET47: =EQ47*ER47*ES47 -> 0 | EU47: 0 | EV47: 22 | EW47: 8.8 | EX47: =EU47*EV47*EW47 -> 0
B48: =IFERROR(VLOOKUP(AE48,'Tabela ICMS'!$C$5:$D$32,2,0),"") | C48: =IFERROR(HLOOKUP(Dashboard!$F$9,'Tabela ICMS'!$E$3:$AF$4,2,0),"") -> 25 | E48: 16 | F48: N/A | G48: mês | H48: =HISTOGRAMA!C25 -> 0 | K48: =SUMIFS(BT48:FK48,$BT$28:$FK$28,">=1",$BT$28:$FK$28,"<=18") -> 0 | L48: =IFERROR(_xlfn.XLOOKUP(N48,$G$3:$G$22,$L$3:$L$22),0) -> 0 | M48: =K48*(1+L48) -> 0 | N48: Equipe_15 | O48: =H48*M48 -> 0 | R48: =IFERROR(M48*VLOOKUP(N48,$G$3:$T$22,14,0),0) -> 0 | S48: =H48*R48 -> 0 | T48: =R48*(1+Dashboard!$D$35) -> 0 | U48: =H48*T48 -> 0 | X48: =SUMIFS(EZ48:FK48,$EZ$28:$FK$28,">=19",$EZ$28:$FK$28,"<=30") -> 0 | AA48: Serviço | AB48: =X48*(1-Y48) -> 0 | AC48: =H48*AB48 -> 0 | AF48: {=IFERROR(INDEX('Tabela ICMS'!$E$5:$AF$32,Tarefas!B48,Tarefas!C48),0)} -> 0 | AG48: =IF(AA48="FD",(Dashboard!$D$43+Dashboard!$D$44),(Dashboard!$D$30+Dashboard!$D$31)) -> 0.0365 | AH48: =IF(AA48="FD",(Dashboard!$D$46),(Dashboard!$D$33)) -> 0 | AI48: =IF(AA48="FD",(Dashboard!$D$45),(Dashboard!$D$32)) -> 0.05 | AM48: =IF(AA48="FD",AB48*(1+Dashboard!$D$48),AB48*(1+Dashboard!$D$35)) -> 0 | AN48: =H48*AM48 -> 0 | AQ48: =T48 -> 0 | AR48: =AM48 -> 0 | AS48: =ROUND(T48+AM48,2) -> 0 | AT48: =ROUND(U48+AN48,2) -> 0 | AU48: =IFERROR(AT48/$AT$28,0) -> 0 | AZ48: =SUM(BA48:BC48) -> 0 | BA48: =(Dashboard!$D$30+Dashboard!$D$31)*U48 -> 0 | BB48: =Dashboard!$D$33*U48 -> 0 | BC48: =Dashboard!$D$32*U48 -> 0 | BE48: =SUM(BF48:BK48) -> 0 | BF48: =AF48*$AN48 -> 0 | BG48: =IF(AA48="FD",($AN48-$AC48)*AG48,AG48*$AN48) -> 0 | BH48: =IF(AB48="FD",($AN48-$AC48)*AH48,AH48*$AN48) -> 0 | BI48: =IF(AC48="FD",($AN48-$AC48)*AI48,AI48*$AN48) -> 0 | BJ48: =IF(AD48="FD",($AN48-$AC48)*AJ48,AJ48*$AN48) -> 0 | BK48: =IF(AE48="FD",($AN48-$AC48)*AK48,AK48*$AN48) -> 0 | BQ48: 0 | BR48: 22 | BS48: 8.8 | BT48: =BQ48*BR48*BS48 -> 0 | BU48: 0 | BV48: 22 | BW48: 8.8 | BX48: =BU48*BV48*BW48 -> 0 | BZ48: 0 | CA48: 22 | CB48: 8.8 | CC48: =BZ48*CA48*CB48 -> 0 | CE48: 0 | CF48: 22 | CG48: 8.8 | CH48: =CE48*CF48*CG48 -> 0 | CI48: 0 | CJ48: 22 | CK48: 8.8 | CL48: =CI48*CJ48*CK48 -> 0 | CM48: 0 | CN48: 22 | CO48: 8.8 | CP48: =CM48*CN48*CO48 -> 0 | CR48: 0 | CS48: 22 | CT48: 8.8 | CU48: =CR48*CS48*CT48 -> 0 | CV48: 0 | CW48: 22 | CX48: 8.8 | CY48: =CV48*CW48*CX48 -> 0 | CZ48: 0 | DA48: 22 | DB48: 8.8 | DC48: =CZ48*DA48*DB48 -> 0 | DE48: 0 | DF48: 22 | DG48: 8.8 | DH48: =DE48*DF48*DG48 -> 0 | DI48: 0 | DJ48: 22 | DK48: 8.8 | DL48: =DI48*DJ48*DK48 -> 0 | DM48: 0 | DN48: 22 | DO48: 8.8 | DP48: =DM48*DN48*DO48 -> 0 | DR48: 0 | DS48: 22 | DT48: 8.8 | DU48: =DR48*DS48*DT48 -> 0 | DV48: 0 | DW48: 22 | DX48: 8.8 | DY48: =DV48*DW48*DX48 -> 0 | DZ48: 0 | EA48: 22 | EB48: 8.8 | EC48: =DZ48*EA48*EB48 -> 0 | EE48: 0 | EF48: 22 | EG48: 8.8 | EH48: =EE48*EF48*EG48 -> 0 | EI48: 0 | EJ48: 22 | EK48: 8.8 | EL48: =EI48*EJ48*EK48 -> 0 | EM48: 0 | EN48: 22 | EO48: 8.8 | EP48: =EM48*EN48*EO48 -> 0 | EQ48: 0 | ER48: 22 | ES48: 8.8 | ET48: =EQ48*ER48*ES48 -> 0 | EU48: 0 | EV48: 22 | EW48: 8.8 | EX48: =EU48*EV48*EW48 -> 0
F49: PRÉ-OBRA
B50: =IFERROR(VLOOKUP(AE50,'Tabela ICMS'!$C$5:$D$32,2,0),"") | C50: =IFERROR(HLOOKUP(Dashboard!$F$9,'Tabela ICMS'!$E$3:$AF$4,2,0),"") -> 25 | E50: 16 | F50: Coordenador de Orçamentos - Part time - 50% mês | G50: mês | H50: =HISTOGRAMA!C26 -> 2 | K50: =SUMIFS(BT50:FK50,$BT$28:$FK$28,">=1",$BT$28:$FK$28,"<=18") -> 96.8 | L50: =IFERROR(_xlfn.XLOOKUP(N50,$G$3:$G$22,$L$3:$L$22),0) -> 0 | M50: =K50*(1+L50) -> 96.8 | N50: Equipe_16 | O50: =H50*M50 -> 193.6 | R50: =IFERROR(M50*VLOOKUP(N50,$G$3:$T$22,14,0),0) -> 14959.434 | S50: =H50*R50 -> 29918.868 | T50: =R50*(1+Dashboard!$D$35) -> 21886.516 | U50: =H50*T50 -> 43773.032 | X50: =SUMIFS(EZ50:FK50,$EZ$28:$FK$28,">=19",$EZ$28:$FK$28,"<=30") -> 1000 | AA50: Serviço | AB50: =X50*(1-Y50) -> 1000 | AC50: =H50*AB50 -> 2000 | AF50: {=IFERROR(INDEX('Tabela ICMS'!$E$5:$AF$32,Tarefas!B50,Tarefas!C50),0)} -> 0 | AG50: =IF(AA50="FD",(Dashboard!$D$43+Dashboard!$D$44),(Dashboard!$D$30+Dashboard!$D$31)) -> 0.0365 | AH50: =IF(AA50="FD",(Dashboard!$D$46),(Dashboard!$D$33)) -> 0 | AI50: =IF(AA50="FD",(Dashboard!$D$45),(Dashboard!$D$32)) -> 0.05 | AM50: =IF(AA50="FD",AB50*(1+Dashboard!$D$48),AB50*(1+Dashboard!$D$35)) -> 1463.0578 | AN50: =H50*AM50 -> 2926.1156 | AQ50: =T50 -> 21886.516 | AR50: =AM50 -> 1463.0578 | AS50: =ROUND(T50+AM50,2) -> 23349.57 | AT50: =ROUND(U50+AN50,2) -> 46699.15 | AU50: =IFERROR(AT50/$AT$28,0) -> 0.030396843 | AZ50: =SUM(BA50:BC50) -> 3786.3673 | BA50: =(Dashboard!$D$30+Dashboard!$D$31)*U50 -> 1597.7157 | BB50: =Dashboard!$D$33*U50 -> 0 | BC50: =Dashboard!$D$32*U50 -> 2188.6516 | BE50: =SUM(BF50:BK50) -> 253.109 | BF50: =AF50*$AN50 -> 0 | BG50: =IF(AA50="FD",($AN50-$AC50)*AG50,AG50*$AN50) -> 106.80322 | BH50: =IF(AB50="FD",($AN50-$AC50)*AH50,AH50*$AN50) -> 0 | BI50: =IF(AC50="FD",($AN50-$AC50)*AI50,AI50*$AN50) -> 146.30578 | BJ50: =IF(AD50="FD",($AN50-$AC50)*AJ50,AJ50*$AN50) -> 0 | BK50: =IF(AE50="FD",($AN50-$AC50)*AK50,AK50*$AN50) -> 0 | BQ50: 0 | BR50: 22 | BS50: 8.8 | BT50: =BQ50*BR50*BS50 -> 0 | BU50: 1 | BV50: =50%*22 -> 11 | BW50: 8.8 | BX50: =BU50*BV50*BW50 -> 96.8 | BZ50: 0 | CA50: 22 | CB50: 8.8 | CC50: =BZ50*CA50*CB50 -> 0 | CE50: 0 | CF50: 22 | CG50: 8.8 | CH50: =CE50*CF50*CG50 -> 0 | CI50: 0 | CJ50: 22 | CK50: 8.8 | CL50: =CI50*CJ50*CK50 -> 0 | CM50: 0 | CN50: 22 | CO50: 8.8 | CP50: =CM50*CN50*CO50 -> 0 | CR50: 0 | CS50: 22 | CT50: 8.8 | CU50: =CR50*CS50*CT50 -> 0 | CV50: 0 | CW50: 22 | CX50: 8.8 | CY50: =CV50*CW50*CX50 -> 0 | CZ50: 0 | DA50: 22 | DB50: 8.8 | DC50: =CZ50*DA50*DB50 -> 0 | DE50: 0 | DF50: 22 | DG50: 8.8 | DH50: =DE50*DF50*DG50 -> 0 | DI50: 0 | DJ50: 22 | DK50: 8.8 | DL50: =DI50*DJ50*DK50 -> 0 | DM50: 0 | DN50: 22 | DO50: 8.8 | DP50: =DM50*DN50*DO50 -> 0 | DR50: 0 | DS50: 22 | DT50: 8.8 | DU50: =DR50*DS50*DT50 -> 0 | DV50: 0 | DW50: 22 | DX50: 8.8 | DY50: =DV50*DW50*DX50 -> 0 | DZ50: 0 | EA50: 22 | EB50: 8.8 | EC50: =DZ50*EA50*EB50 -> 0 | EE50: 0 | EF50: 22 | EG50: 8.8 | EH50: =EE50*EF50*EG50 -> 0 | EI50: 0 | EJ50: 22 | EK50: 8.8 | EL50: =EI50*EJ50*EK50 -> 0 | EM50: 0 | EN50: 22 | EO50: 8.8 | EP50: =EM50*EN50*EO50 -> 0 | EQ50: 0 | ER50: 22 | ES50: 8.8 | ET50: =EQ50*ER50*ES50 -> 0 | EU50: 0 | EV50: 22 | EW50: 8.8 | EX50: =EU50*EV50*EW50 -> 0 | EZ50: 1000
B51: =IFERROR(VLOOKUP(AE51,'Tabela ICMS'!$C$5:$D$32,2,0),"") | C51: =IFERROR(HLOOKUP(Dashboard!$F$9,'Tabela ICMS'!$E$3:$AF$4,2,0),"") -> 25 | E51: 17 | F51: Arquiteto Pl. ( Gestão de projetos) - Remoto ( Supervisor) - 20% mês | G51: mês | H51: =HISTOGRAMA!C27 -> 2 | K51: =SUMIFS(BT51:FK51,$BT$28:$FK$28,">=1",$BT$28:$FK$28,"<=18") -> 38.72 | L51: =IFERROR(_xlfn.XLOOKUP(N51,$G$3:$G$22,$L$3:$L$22),0) -> 0 | M51: =K51*(1+L51) -> 38.72 | N51: Equipe_17 | O51: =H51*M51 -> 77.44 | R51: =IFERROR(M51*VLOOKUP(N51,$G$3:$T$22,14,0),0) -> 4409.0963 | S51: =H51*R51 -> 8818.1926 | T51: =R51*(1+Dashboard!$D$35) -> 6450.7627 | U51: =H51*T51 -> 12901.525 | X51: =SUMIFS(EZ51:FK51,$EZ$28:$FK$28,">=19",$EZ$28:$FK$28,"<=30") -> 0 | AA51: Serviço | AB51: =X51*(1-Y51) -> 0 | AC51: =H51*AB51 -> 0 | AF51: {=IFERROR(INDEX('Tabela ICMS'!$E$5:$AF$32,Tarefas!B51,Tarefas!C51),0)} -> 0 | AG51: =IF(AA51="FD",(Dashboard!$D$43+Dashboard!$D$44),(Dashboard!$D$30+Dashboard!$D$31)) -> 0.0365 | AH51: =IF(AA51="FD",(Dashboard!$D$46),(Dashboard!$D$33)) -> 0 | AI51: =IF(AA51="FD",(Dashboard!$D$45),(Dashboard!$D$32)) -> 0.05 | AM51: =IF(AA51="FD",AB51*(1+Dashboard!$D$48),AB51*(1+Dashboard!$D$35)) -> 0 | AN51: =H51*AM51 -> 0 | AQ51: =T51 -> 6450.7627 | AR51: =AM51 -> 0 | AS51: =ROUND(T51+AM51,2) -> 6450.76 | AT51: =ROUND(U51+AN51,2) -> 12901.53 | AU51: =IFERROR(AT51/$AT$28,0) -> 0.008397707 | AZ51: =SUM(BA51:BC51) -> 1115.9819 | BA51: =(Dashboard!$D$30+Dashboard!$D$31)*U51 -> 470.90567 | BB51: =Dashboard!$D$33*U51 -> 0 | BC51: =Dashboard!$D$32*U51 -> 645.07627 | BE51: =SUM(BF51:BK51) -> 0 | BF51: =AF51*$AN51 -> 0 | BG51: =IF(AA51="FD",($AN51-$AC51)*AG51,AG51*$AN51) -> 0 | BH51: =IF(AB51="FD",($AN51-$AC51)*AH51,AH51*$AN51) -> 0 | BI51: =IF(AC51="FD",($AN51-$AC51)*AI51,AI51*$AN51) -> 0 | BJ51: =IF(AD51="FD",($AN51-$AC51)*AJ51,AJ51*$AN51) -> 0 | BK51: =IF(AE51="FD",($AN51-$AC51)*AK51,AK51*$AN51) -> 0 | BQ51: 0 | BR51: 22 | BS51: 8.8 | BT51: =BQ51*BR51*BS51 -> 0 | BU51: 0 | BV51: 22 | BW51: 8.8 | BX51: =BU51*BV51*BW51 -> 0 | BZ51: 0 | CA51: 22 | CB51: 8.8 | CC51: =BZ51*CA51*CB51 -> 0 | CE51: 0 | CF51: 22 | CG51: 8.8 | CH51: =CE51*CF51*CG51 -> 0 | CI51: 1 | CJ51: =20%*22 -> 4.4 | CK51: 8.8 | CL51: =CI51*CJ51*CK51 -> 38.72 | CM51: 0 | CN51: 22 | CO51: 8.8 | CP51: =CM51*CN51*CO51 -> 0 | CR51: 0 | CS51: 22 | CT51: 8.8 | CU51: =CR51*CS51*CT51 -> 0 | CV51: 0 | CW51: 22 | CX51: 8.8 | CY51: =CV51*CW51*CX51 -> 0 | CZ51: 0 | DA51: 22 | DB51: 8.8 | DC51: =CZ51*DA51*DB51 -> 0 | DE51: 0 | DF51: 22 | DG51: 8.8 | DH51: =DE51*DF51*DG51 -> 0 | DI51: 0 | DJ51: 22 | DK51: 8.8 | DL51: =DI51*DJ51*DK51 -> 0 | DM51: 0 | DN51: 22 | DO51: 8.8 | DP51: =DM51*DN51*DO51 -> 0 | DR51: 0 | DS51: 22 | DT51: 8.8 | DU51: =DR51*DS51*DT51 -> 0 | DV51: 0 | DW51: 22 | DX51: 8.8 | DY51: =DV51*DW51*DX51 -> 0 | DZ51: 0 | EA51: 22 | EB51: 8.8 | EC51: =DZ51*EA51*EB51 -> 0 | EE51: 0 | EF51: 22 | EG51: 8.8 | EH51: =EE51*EF51*EG51 -> 0 | EI51: 0 | EJ51: 22 | EK51: 8.8 | EL51: =EI51*EJ51*EK51 -> 0 | EM51: 0 | EN51: 22 | EO51: 8.8 | EP51: =EM51*EN51*EO51 -> 0 | EQ51: 0 | ER51: 22 | ES51: 8.8 | ET51: =EQ51*ER51*ES51 -> 0 | EU51: 0 | EV51: 22 | EW51: 8.8 | EX51: =EU51*EV51*EW51 -> 0
B52: =IFERROR(VLOOKUP(AE52,'Tabela ICMS'!$C$5:$D$32,2,0),"") | C52: =IFERROR(HLOOKUP(Dashboard!$F$9,'Tabela ICMS'!$E$3:$AF$4,2,0),"") -> 25 | E52: 18 | F52: Engenheiro Pl. de Planejamento, Qualidade e Custos ( Supervisor) - 10% - mês | G52: mês | H52: =HISTOGRAMA!C28 -> 2 | K52: =SUMIFS(BT52:FK52,$BT$28:$FK$28,">=1",$BT$28:$FK$28,"<=18") -> 19.36 | L52: =IFERROR(_xlfn.XLOOKUP(N52,$G$3:$G$22,$L$3:$L$22),0) -> 0 | M52: =K52*(1+L52) -> 19.36 | N52: Equipe_18 | O52: =H52*M52 -> 38.72 | R52: =IFERROR(M52*VLOOKUP(N52,$G$3:$T$22,14,0),0) -> 2204.5481 | S52: =H52*R52 -> 4409.0963 | T52: =R52*(1+Dashboard!$D$35) -> 3225.3813 | U52: =H52*T52 -> 6450.7627 | X52: =SUMIFS(EZ52:FK52,$EZ$28:$FK$28,">=19",$EZ$28:$FK$28,"<=30") -> 1000 | AA52: Serviço | AB52: =X52*(1-Y52) -> 1000 | AC52: =H52*AB52 -> 2000 | AF52: {=IFERROR(INDEX('Tabela ICMS'!$E$5:$AF$32,Tarefas!B52,Tarefas!C52),0)} -> 0 | AG52: =IF(AA52="FD",(Dashboard!$D$43+Dashboard!$D$44),(Dashboard!$D$30+Dashboard!$D$31)) -> 0.0365 | AH52: =IF(AA52="FD",(Dashboard!$D$46),(Dashboard!$D$33)) -> 0 | AI52: =IF(AA52="FD",(Dashboard!$D$45),(Dashboard!$D$32)) -> 0.05 | AM52: =IF(AA52="FD",AB52*(1+Dashboard!$D$48),AB52*(1+Dashboard!$D$35)) -> 1463.0578 | AN52: =H52*AM52 -> 2926.1156 | AQ52: =T52 -> 3225.3813 | AR52: =AM52 -> 1463.0578 | AS52: =ROUND(T52+AM52,2) -> 4688.44 | AT52: =ROUND(U52+AN52,2) -> 9376.88 | AU52: =IFERROR(AT52/$AT$28,0) -> 0.0061034847 | AZ52: =SUM(BA52:BC52) -> 557.99097 | BA52: =(Dashboard!$D$30+Dashboard!$D$31)*U52 -> 235.45284 | BB52: =Dashboard!$D$33*U52 -> 0 | BC52: =Dashboard!$D$32*U52 -> 322.53813 | BE52: =SUM(BF52:BK52) -> 253.109 | BF52: =AF52*$AN52 -> 0 | BG52: =IF(AA52="FD",($AN52-$AC52)*AG52,AG52*$AN52) -> 106.80322 | BH52: =IF(AB52="FD",($AN52-$AC52)*AH52,AH52*$AN52) -> 0 | BI52: =IF(AC52="FD",($AN52-$AC52)*AI52,AI52*$AN52) -> 146.30578 | BJ52: =IF(AD52="FD",($AN52-$AC52)*AJ52,AJ52*$AN52) -> 0 | BK52: =IF(AE52="FD",($AN52-$AC52)*AK52,AK52*$AN52) -> 0 | BQ52: 0 | BR52: 22 | BS52: 8.8 | BT52: =BQ52*BR52*BS52 -> 0 | BU52: 0 | BV52: 22 | BW52: 8.8 | BX52: =BU52*BV52*BW52 -> 0 | BZ52: 0 | CA52: 22 | CB52: 8.8 | CC52: =BZ52*CA52*CB52 -> 0 | CE52: 0 | CF52: 22 | CG52: 8.8 | CH52: =CE52*CF52*CG52 -> 0 | CI52: 1 | CJ52: =10%*22 -> 2.2 | CK52: 8.8 | CL52: =CI52*CJ52*CK52 -> 19.36 | CM52: 0 | CN52: 22 | CO52: 8.8 | CP52: =CM52*CN52*CO52 -> 0 | CR52: 0 | CS52: 22 | CT52: 8.8 | CU52: =CR52*CS52*CT52 -> 0 | CV52: 0 | CW52: 22 | CX52: 8.8 | CY52: =CV52*CW52*CX52 -> 0 | CZ52: 0 | DA52: 22 | DB52: 8.8 | DC52: =CZ52*DA52*DB52 -> 0 | DE52: 0 | DF52: 22 | DG52: 8.8 | DH52: =DE52*DF52*DG52 -> 0 | DI52: 0 | DJ52: 22 | DK52: 8.8 | DL52: =DI52*DJ52*DK52 -> 0 | DM52: 0 | DN52: 22 | DO52: 8.8 | DP52: =DM52*DN52*DO52 -> 0 | DR52: 0 | DS52: 22 | DT52: 8.8 | DU52: =DR52*DS52*DT52 -> 0 | DV52: 0 | DW52: 22 | DX52: 8.8 | DY52: =DV52*DW52*DX52 -> 0 | DZ52: 0 | EA52: 22 | EB52: 8.8 | EC52: =DZ52*EA52*EB52 -> 0 | EE52: 0 | EF52: 22 | EG52: 8.8 | EH52: =EE52*EF52*EG52 -> 0 | EI52: 0 | EJ52: 22 | EK52: 8.8 | EL52: =EI52*EJ52*EK52 -> 0 | EM52: 0 | EN52: 22 | EO52: 8.8 | EP52: =EM52*EN52*EO52 -> 0 | EQ52: 0 | ER52: 22 | ES52: 8.8 | ET52: =EQ52*ER52*ES52 -> 0 | EU52: 0 | EV52: 22 | EW52: 8.8 | EX52: =EU52*EV52*EW52 -> 0 | EZ52: 1000
B53: =IFERROR(VLOOKUP(AE53,'Tabela ICMS'!$C$5:$D$32,2,0),"") | C53: =IFERROR(HLOOKUP(Dashboard!$F$9,'Tabela ICMS'!$E$3:$AF$4,2,0),"") -> 25 | E53: 19 | F53: Analista de Financeiro - An. Sr. 50% ( Análise financeira das empresas) | G53: mês | H53: =HISTOGRAMA!C29 -> 1 | K53: =SUMIFS(BT53:FK53,$BT$28:$FK$28,">=1",$BT$28:$FK$28,"<=18") -> 96.8 | L53: =IFERROR(_xlfn.XLOOKUP(N53,$G$3:$G$22,$L$3:$L$22),0) -> 0 | M53: =K53*(1+L53) -> 96.8 | N53: Equipe_19 | O53: =H53*M53 -> 96.8 | R53: =IFERROR(M53*VLOOKUP(N53,$G$3:$T$22,14,0),0) -> 5842.0526 | S53: =H53*R53 -> 5842.0526 | T53: =R53*(1+Dashboard!$D$35) -> 8547.2605 | U53: =H53*T53 -> 8547.2605 | X53: =SUMIFS(EZ53:FK53,$EZ$28:$FK$28,">=19",$EZ$28:$FK$28,"<=30") -> 0 | AA53: Serviço | AB53: =X53*(1-Y53) -> 0 | AC53: =H53*AB53 -> 0 | AF53: {=IFERROR(INDEX('Tabela ICMS'!$E$5:$AF$32,Tarefas!B53,Tarefas!C53),0)} -> 0 | AG53: =IF(AA53="FD",(Dashboard!$D$43+Dashboard!$D$44),(Dashboard!$D$30+Dashboard!$D$31)) -> 0.0365 | AH53: =IF(AA53="FD",(Dashboard!$D$46),(Dashboard!$D$33)) -> 0 | AI53: =IF(AA53="FD",(Dashboard!$D$45),(Dashboard!$D$32)) -> 0.05 | AM53: =IF(AA53="FD",AB53*(1+Dashboard!$D$48),AB53*(1+Dashboard!$D$35)) -> 0 | AN53: =H53*AM53 -> 0 | AQ53: =T53 -> 8547.2605 | AR53: =AM53 -> 0 | AS53: =ROUND(T53+AM53,2) -> 8547.26 | AT53: =ROUND(U53+AN53,2) -> 8547.26 | AU53: =IFERROR(AT53/$AT$28,0) -> 0.0055634786 | AZ53: =SUM(BA53:BC53) -> 739.33804 | BA53: =(Dashboard!$D$30+Dashboard!$D$31)*U53 -> 311.97501 | BB53: =Dashboard!$D$33*U53 -> 0 | BC53: =Dashboard!$D$32*U53 -> 427.36303 | BE53: =SUM(BF53:BK53) -> 0 | BF53: =AF53*$AN53 -> 0 | BG53: =IF(AA53="FD",($AN53-$AC53)*AG53,AG53*$AN53) -> 0 | BH53: =IF(AB53="FD",($AN53-$AC53)*AH53,AH53*$AN53) -> 0 | BI53: =IF(AC53="FD",($AN53-$AC53)*AI53,AI53*$AN53) -> 0 | BJ53: =IF(AD53="FD",($AN53-$AC53)*AJ53,AJ53*$AN53) -> 0 | BK53: =IF(AE53="FD",($AN53-$AC53)*AK53,AK53*$AN53) -> 0 | BQ53: 0 | BR53: 22 | BS53: 8.8 | BT53: =BQ53*BR53*BS53 -> 0 | BU53: 0 | BV53: 22 | BW53: 8.8 | BX53: =BU53*BV53*BW53 -> 0 | BZ53: 0 | CA53: 22 | CB53: 8.8 | CC53: =BZ53*CA53*CB53 -> 0 | CE53: 0 | CF53: 22 | CG53: 8.8 | CH53: =CE53*CF53*CG53 -> 0 | CI53: 0 | CJ53: 22 | CK53: 8.8 | CL53: =CI53*CJ53*CK53 -> 0 | CM53: 0 | CN53: 22 | CO53: 8.8 | CP53: =CM53*CN53*CO53 -> 0 | CR53: 0 | CS53: 22 | CT53: 8.8 | CU53: =CR53*CS53*CT53 -> 0 | CV53: 0 | CW53: 22 | CX53: 8.8 | CY53: =CV53*CW53*CX53 -> 0 | CZ53: 0 | DA53: 22 | DB53: 8.8 | DC53: =CZ53*DA53*DB53 -> 0 | DE53: 1 | DF53: =22/2 -> 11 | DG53: 8.8 | DH53: =DE53*DF53*DG53 -> 96.8 | DI53: 0 | DJ53: 22 | DK53: 8.8 | DL53: =DI53*DJ53*DK53 -> 0 | DM53: 0 | DN53: 22 | DO53: 8.8 | DP53: =DM53*DN53*DO53 -> 0 | DR53: 0 | DS53: 22 | DT53: 8.8 | DU53: =DR53*DS53*DT53 -> 0 | DV53: 0 | DW53: 22 | DX53: 8.8 | DY53: =DV53*DW53*DX53 -> 0 | DZ53: 0 | EA53: 22 | EB53: 8.8 | EC53: =DZ53*EA53*EB53 -> 0 | EE53: 0 | EF53: 22 | EG53: 8.8 | EH53: =EE53*EF53*EG53 -> 0 | EI53: 0 | EJ53: 22 | EK53: 8.8 | EL53: =EI53*EJ53*EK53 -> 0 | EM53: 0 | EN53: 22 | EO53: 8.8 | EP53: =EM53*EN53*EO53 -> 0 | EQ53: 0 | ER53: 22 | ES53: 8.8 | ET53: =EQ53*ER53*ES53 -> 0 | EU53: 0 | EV53: 22 | EW53: 8.8 | EX53: =EU53*EV53*EW53 -> 0
B54: =IFERROR(VLOOKUP(AE54,'Tabela ICMS'!$C$5:$D$32,2,0),"") | C54: =IFERROR(HLOOKUP(Dashboard!$F$9,'Tabela ICMS'!$E$3:$AF$4,2,0),"") -> 25 | E54: 20 | G54: mês | H54: =HISTOGRAMA!C30 -> 0 | K54: =SUMIFS(BT54:FK54,$BT$28:$FK$28,">=1",$BT$28:$FK$28,"<=18") -> 0 | L54: =IFERROR(_xlfn.XLOOKUP(N54,$G$3:$G$22,$L$3:$L$22),0) -> 0 | M54: =K54*(1+L54) -> 0 | O54: =H54*M54 -> 0 | R54: =IFERROR(M54*VLOOKUP(N54,$G$3:$T$22,14,0),0) -> 0 | S54: =H54*R54 -> 0 | T54: =R54*(1+Dashboard!$D$35) -> 0 | U54: =H54*T54 -> 0 | X54: =SUMIFS(EZ54:FK54,$EZ$28:$FK$28,">=19",$EZ$28:$FK$28,"<=30") -> 0 | AA54: Serviço | AB54: =X54*(1-Y54) -> 0 | AC54: =H54*AB54 -> 0 | AF54: {=IFERROR(INDEX('Tabela ICMS'!$E$5:$AF$32,Tarefas!B54,Tarefas!C54),0)} -> 0 | AG54: =IF(AA54="FD",(Dashboard!$D$43+Dashboard!$D$44),(Dashboard!$D$30+Dashboard!$D$31)) -> 0.0365 | AH54: =IF(AA54="FD",(Dashboard!$D$46),(Dashboard!$D$33)) -> 0 | AI54: =IF(AA54="FD",(Dashboard!$D$45),(Dashboard!$D$32)) -> 0.05 | AM54: =IF(AA54="FD",AB54*(1+Dashboard!$D$48),AB54*(1+Dashboard!$D$35)) -> 0 | AN54: =H54*AM54 -> 0 | AQ54: =T54 -> 0 | AR54: =AM54 -> 0 | AS54: =ROUND(T54+AM54,2) -> 0 | AT54: =ROUND(U54+AN54,2) -> 0 | AU54: =IFERROR(AT54/$AT$28,0) -> 0 | AZ54: =SUM(BA54:BC54) -> 0 | BA54: =(Dashboard!$D$30+Dashboard!$D$31)*U54 -> 0 | BB54: =Dashboard!$D$33*U54 -> 0 | BC54: =Dashboard!$D$32*U54 -> 0 | BE54: =SUM(BF54:BK54) -> 0 | BF54: =AF54*$AN54 -> 0 | BG54: =IF(AA54="FD",($AN54-$AC54)*AG54,AG54*$AN54) -> 0 | BH54: =IF(AB54="FD",($AN54-$AC54)*AH54,AH54*$AN54) -> 0 | BI54: =IF(AC54="FD",($AN54-$AC54)*AI54,AI54*$AN54) -> 0 | BJ54: =IF(AD54="FD",($AN54-$AC54)*AJ54,AJ54*$AN54) -> 0 | BK54: =IF(AE54="FD",($AN54-$AC54)*AK54,AK54*$AN54) -> 0 | BQ54: 0 | BR54: 22 | BS54: 8.8 | BT54: =BQ54*BR54*BS54 -> 0 | BU54: 0 | BV54: 22 | BW54: 8.8 | BX54: =BU54*BV54*BW54 -> 0 | BZ54: 0 | CA54: 22 | CB54: 8.8 | CC54: =BZ54*CA54*CB54 -> 0 | CE54: 0 | CF54: 22 | CG54: 8.8 | CH54: =CE54*CF54*CG54 -> 0 | CI54: 0 | CJ54: 22 | CK54: 8.8 | CL54: =CI54*CJ54*CK54 -> 0 | CM54: 0 | CN54: 22 | CO54: 8.8 | CP54: =CM54*CN54*CO54 -> 0 | CR54: 0 | CS54: 22 | CT54: 8.8 | CU54: =CR54*CS54*CT54 -> 0 | CV54: 0 | CW54: 22 | CX54: 8.8 | CY54: =CV54*CW54*CX54 -> 0 | CZ54: 0 | DA54: 22 | DB54: 8.8 | DC54: =CZ54*DA54*DB54 -> 0 | DE54: 0 | DF54: =22/2 -> 11 | DG54: 8.8 | DH54: =DE54*DF54*DG54 -> 0 | DI54: 0 | DJ54: 22 | DK54: 8.8 | DL54: =DI54*DJ54*DK54 -> 0 | DM54: 0 | DN54: 22 | DO54: 8.8 | DP54: =DM54*DN54*DO54 -> 0 | DR54: 0 | DS54: 22 | DT54: 8.8 | DU54: =DR54*DS54*DT54 -> 0 | DV54: 0 | DW54: 22 | DX54: 8.8 | DY54: =DV54*DW54*DX54 -> 0 | DZ54: 0 | EA54: 22 | EB54: 8.8 | EC54: =DZ54*EA54*EB54 -> 0 | EE54: 0 | EF54: 22 | EG54: 8.8 | EH54: =EE54*EF54*EG54 -> 0 | EI54: 0 | EJ54: 22 | EK54: 8.8 | EL54: =EI54*EJ54*EK54 -> 0 | EM54: 0 | EN54: 22 | EO54: 8.8 | EP54: =EM54*EN54*EO54 -> 0 | EQ54: 0 | ER54: 22 | ES54: 8.8 | ET54: =EQ54*ER54*ES54 -> 0 | EU54: 0 | EV54: 22 | EW54: 8.8 | EX54: =EU54*EV54*EW54 -> 0
W55: caso o prazo da obra ultrapasse o previsto | BQ55: 0 | BR55: 22 | BS55: 8.8 | BT55: =BQ55*BR55*BS55 -> 0 | BU55: 0 | BV55: 22 | BW55: 8.8 | BX55: =BU55*BV55*BW55 -> 0 | BZ55: 0 | CA55: 22 | CB55: 8.8 | CC55: =BZ55*CA55*CB55 -> 0 | CE55: 0 | CF55: 22 | CG55: 8.8 | CH55: =CE55*CF55*CG55 -> 0 | CI55: 0 | CJ55: 22 | CK55: 8.8 | CL55: =CI55*CJ55*CK55 -> 0 | CM55: 0 | CN55: 22 | CO55: 8.8 | CP55: =CM55*CN55*CO55 -> 0 | CR55: 0 | CS55: 22 | CT55: 8.8 | CU55: =CR55*CS55*CT55 -> 0 | CV55: 0 | CW55: 22 | CX55: 8.8 | CY55: =CV55*CW55*CX55 -> 0 | CZ55: 0 | DA55: 22 | DB55: 8.8 | DC55: =CZ55*DA55*DB55 -> 0 | DE55: 0 | DF55: 22 | DG55: 8.8 | DH55: =DE55*DF55*DG55 -> 0 | DI55: 0 | DJ55: 22 | DK55: 8.8 | DL55: =DI55*DJ55*DK55 -> 0 | DM55: 0 | DN55: 22 | DO55: 8.8 | DP55: =DM55*DN55*DO55 -> 0 | DR55: 0 | DS55: 22 | DT55: 8.8 | DU55: =DR55*DS55*DT55 -> 0 | DV55: 0 | DW55: 22 | DX55: 8.8 | DY55: =DV55*DW55*DX55 -> 0 | DZ55: 0 | EA55: 22 | EB55: 8.8 | EC55: =DZ55*EA55*EB55 -> 0 | EE55: 0 | EF55: 22 | EG55: 8.8 | EH55: =EE55*EF55*EG55 -> 0 | EI55: 0 | EJ55: 22 | EK55: 8.8 | EL55: =EI55*EJ55*EK55 -> 0 | EM55: 0 | EN55: 22 | EO55: 8.8 | EP55: =EM55*EN55*EO55 -> 0 | EQ55: 0 | ER55: 22 | ES55: 8.8 | ET55: =EQ55*ER55*ES55 -> 0 | EU55: 0 | EV55: 22 | EW55: 8.8 | EX55: =EU55*EV55*EW55 -> 0

Sheet PPU
B2: Item | C2: Descrição | D2: Unidade | E2: Qtd. | F2: Preço Unitário | G2: Preço Total
B3: 1 | C3: =INDEX(Tarefas!F32:F54,MATCH(B3,Tarefas!E32:E54,0)) -> Coordenador de Obras - Full time 100% | D3: =INDEX(Tarefas!G32:G54,MATCH(B3,Tarefas!E32:E54,0)) -> mês | E3: =INDEX(Tarefas!H32:H54,MATCH(B3,Tarefas!E32:E54,0)) -> 10 | F3: =INDEX(Tarefas!AS32:AS54,MATCH(B3,Tarefas!E32:E54,0)) -> 50961.49 | G3: =E3*F3 -> 509614.9
B4: 2 | C4: =INDEX(Tarefas!F33:F55,MATCH(B4,Tarefas!E33:E55,0)) -> Engenheiro Pl. de Planejamento, Qualidade e Custos ( Supervisor) - Full time | D4: =INDEX(Tarefas!G33:G55,MATCH(B4,Tarefas!E33:E55,0)) -> mês | E4: =INDEX(Tarefas!H33:H55,MATCH(B4,Tarefas!E33:E55,0)) -> 7 | F4: =INDEX(Tarefas!AS33:AS55,MATCH(B4,Tarefas!E33:E55,0)) -> 39784.56 | G4: =E4*F4 -> 278491.92
B5: 3 | C5: =INDEX(Tarefas!F35:F56,MATCH(B5,Tarefas!E35:E56,0)) -> #N/A | D5: =INDEX(Tarefas!G35:G56,MATCH(B5,Tarefas!E35:E56,0)) -> #N/A | E5: =INDEX(Tarefas!H35:H56,MATCH(B5,Tarefas!E35:E56,0)) -> #N/A | F5: =INDEX(Tarefas!AS35:AS56,MATCH(B5,Tarefas!E35:E56,0)) -> #N/A | G5: =E5*F5 -> #N/A
B6: 4 | C6: =INDEX(Tarefas!F36:F57,MATCH(B6,Tarefas!E36:E57,0)) -> #N/A | D6: =INDEX(Tarefas!G36:G57,MATCH(B6,Tarefas!E36:E57,0)) -> #N/A | E6: =INDEX(Tarefas!H36:H57,MATCH(B6,Tarefas!E36:E57,0)) -> #N/A | F6: =INDEX(Tarefas!AS36:AS57,MATCH(B6,Tarefas!E36:E57,0)) -> #N/A | G6: =E6*F6 -> #N/A
B7: 5 | C7: =INDEX(Tarefas!F37:F58,MATCH(B7,Tarefas!E37:E58,0)) -> #N/A | D7: =INDEX(Tarefas!G37:G58,MATCH(B7,Tarefas!E37:E58,0)) -> #N/A | E7: =INDEX(Tarefas!H37:H58,MATCH(B7,Tarefas!E37:E58,0)) -> #N/A | F7: =INDEX(Tarefas!AS37:AS58,MATCH(B7,Tarefas!E37:E58,0)) -> #N/A | G7: =E7*F7 -> #N/A
B8: 6 | C8: =INDEX(Tarefas!F39:F59,MATCH(B8,Tarefas!E39:E59,0)) -> #N/A | D8: =INDEX(Tarefas!G39:G59,MATCH(B8,Tarefas!E39:E59,0)) -> #N/A | E8: =INDEX(Tarefas!H39:H59,MATCH(B8,Tarefas!E39:E59,0)) -> #N/A | F8: =INDEX(Tarefas!AS39:AS59,MATCH(B8,Tarefas!E39:E59,0)) -> #N/A | G8: =E8*F8 -> #N/A
B9: 7 | C9: =INDEX(Tarefas!F40:F60,MATCH(B9,Tarefas!E40:E60,0)) -> #N/A | D9: =INDEX(Tarefas!G40:G60,MATCH(B9,Tarefas!E40:E60,0)) -> #N/A | E9: =INDEX(Tarefas!H40:H60,MATCH(B9,Tarefas!E40:E60,0)) -> #N/A | F9: =INDEX(Tarefas!AS40:AS60,MATCH(B9,Tarefas!E40:E60,0)) -> #N/A | G9: =E9*F9 -> #N/A
B10: 8 | C10: =INDEX(Tarefas!F41:F61,MATCH(B10,Tarefas!E41:E61,0)) -> #N/A | D10: =INDEX(Tarefas!G41:G61,MATCH(B10,Tarefas!E41:E61,0)) -> #N/A | E10: =INDEX(Tarefas!H41:H61,MATCH(B10,Tarefas!E41:E61,0)) -> #N/A | F10: =INDEX(Tarefas!AS41:AS61,MATCH(B10,Tarefas!E41:E61,0)) -> #N/A | G10: =E10*F10 -> #N/A
B11: 9 | C11: =INDEX(Tarefas!F42:F62,MATCH(B11,Tarefas!E42:E62,0)) -> #N/A | D11: =INDEX(Tarefas!G42:G62,MATCH(B11,Tarefas!E42:E62,0)) -> #N/A | E11: =INDEX(Tarefas!H42:H62,MATCH(B11,Tarefas!E42:E62,0)) -> #N/A | F11: =INDEX(Tarefas!AS42:AS62,MATCH(B11,Tarefas!E42:E62,0)) -> #N/A | G11: =E11*F11 -> #N/A
B12: 10 | C12: =INDEX(Tarefas!F43:F63,MATCH(B12,Tarefas!E43:E63,0)) -> #N/A | D12: =INDEX(Tarefas!G43:G63,MATCH(B12,Tarefas!E43:E63,0)) -> #N/A | E12: =INDEX(Tarefas!H43:H63,MATCH(B12,Tarefas!E43:E63,0)) -> #N/A | F12: =INDEX(Tarefas!AS43:AS63,MATCH(B12,Tarefas!E43:E63,0)) -> #N/A | G12: =E12*F12 -> #N/A
F14: Total | G14: =SUM(G3:G12) -> #N/A

Sheet Cronog. e Histog.
K2: M1 | L2: M2 | M2: M3 | N2: M4 | O2: M5 | P2: M6 | Q2: M7 | R2: M8 | S2: M9 | T2: M10 | U2: M11 | V2: M12 | W2: M13 | X2: M14 | Y2: M15 | Z2: M16 | AA2: M17 | AB2: M18 | AC2: M19 | AD2: M20 | AE2: M21 | AF2: M22 | AG2: M23 | AH2: M24 | AI2: M25 | AJ2: M26 | AK2: M27 | AL2: M28 | AM2: M29 | AN2: M30 | AO2: M31 | AP2: M32 | AQ2: M33 | AR2: M34 | AS2: M35 | AT2: M36 | AU2: M37 | AV2: M38 | AW2: M39 | AX2: M40 | AY2: M41 | AZ2: M42 | BA2: M43 | BB2: M44 | BC2: M45 | BD2: M46 | BE2: M47 | BF2: M48 | BG2: M49 | BH2: M50 | BI2: M51 | BJ2: M52 | BK2: M53 | BL2: M54 | BM2: M55 | BN2: M56 | BO2: M57 | BP2: M58 | BQ2: M59 | BR2: M60
K3: =IF(K51="x",1,0) -> 1 | L3: =IF(L51="x",1,0) -> 1 | M3: =IF(M51="x",1,0) -> 1 | N3: =IF(N51="x",1,0) -> 1 | O3: =IF(O51="x",1,0) -> 1 | P3: =IF(P51="x",1,0) -> 1 | Q3: =IF(Q51="x",1,0) -> 1 | R3: =IF(R51="x",1,0) -> 1 | ... BR3: =IF(BR51="x",1,0) -> 0
K4: =IF(K52="x",1,0) -> 1 | L4: =IF(L52="x",1,0) -> 1 | M4: =IF(M52="x",1,0) -> 1 | N4: =IF(N52="x",1,0) -> 1 | O4: =IF(O52="x",1,0) -> 1 | P4: =IF(P52="x",1,0) -> 1 | Q4: =IF(Q52="x",1,0) -> 1 | R4: =IF(R52="x",1,0) -> 1 | ... BR4: =IF(BR52="x",1,0) -> 0
K5: =IF(K53="x",1,0) -> 1 | L5: =IF(L53="x",1,0) -> 1 | M5: =IF(M53="x",1,0) -> 1 | N5: =IF(N53="x",1,0) -> 1 | O5: =IF(O53="x",1,0) -> 1 | P5: =IF(P53="x",1,0) -> 1 | Q5: =IF(Q53="x",1,0) -> 1 | R5: =IF(R53="x",1,0) -> 1 | ... BR5: =IF(BR53="x",1,0) -> 0
K6: =IF(K54="x",1,0) -> 1 | L6: =IF(L54="x",1,0) -> 1 | M6: =IF(M54="x",1,0) -> 1 | N6: =IF(N54="x",1,0) -> 1 | O6: =IF(O54="x",1,0) -> 1 | P6: =IF(P54="x",1,0) -> 1 | Q6: =IF(Q54="x",1,0) -> 1 | R6: =IF(R54="x",1,0) -> 1 | ... BR6: =IF(BR54="x",1,0) -> 0
K7: =IF(K55="x",1,0) -> 1 | L7: =IF(L55="x",1,0) -> 1 | M7: =IF(M55="x",1,0) -> 1 | N7: =IF(N55="x",1,0) -> 1 | O7: =IF(O55="x",1,0) -> 1 | P7: =IF(P55="x",1,0) -> 1 | Q7: =IF(Q55="x",1,0) -> 1 | R7: =IF(R55="x",1,0) -> 1 | ... BR7: =IF(BR55="x",1,0) -> 0
K8: =IF(K56="x",1,0) -> 1 | L8: =IF(L56="x",1,0) -> 1 | M8: =IF(M56="x",1,0) -> 1 | N8: =IF(N56="x",1,0) -> 1 | O8: =IF(O56="x",1,0) -> 1 | P8: =IF(P56="x",1,0) -> 1 | Q8: =IF(Q56="x",1,0) -> 1 | R8: =IF(R56="x",1,0) -> 1 | ... BR8: =IF(BR56="x",1,0) -> 0
K9: =IF(K57="x",1,0) -> 1 | L9: =IF(L57="x",1,0) -> 1 | M9: =IF(M57="x",1,0) -> 1 | N9: =IF(N57="x",1,0) -> 1 | O9: =IF(O57="x",1,0) -> 1 | P9: =IF(P57="x",1,0) -> 1 | Q9: =IF(Q57="x",1,0) -> 1 | R9: =IF(R57="x",1,0) -> 1 | ... BR9: =IF(BR57="x",1,0) -> 0
K10: =IF(K58="x",1,0) -> 1 | L10: =IF(L58="x",1,0) -> 1 | M10: =IF(M58="x",1,0) -> 1 | N10: =IF(N58="x",1,0) -> 1 | O10: =IF(O58="x",1,0) -> 1 | P10: =IF(P58="x",1,0) -> 1 | Q10: =IF(Q58="x",1,0) -> 1 | R10: =IF(R58="x",1,0) -> 1 | ... BR10: =IF(BR58="x",1,0) -> 0
K11: =IF(K59="x",1,0) -> 1 | L11: =IF(L59="x",1,0) -> 1 | M11: =IF(M59="x",1,0) -> 1 | N11: =IF(N59="x",1,0) -> 1 | O11: =IF(O59="x",1,0) -> 1 | P11: =IF(P59="x",1,0) -> 1 | Q11: =IF(Q59="x",1,0) -> 1 | R11: =IF(R59="x",1,0) -> 1 | ... BR11: =IF(BR59="x",1,0) -> 0
K12: =IF(K60="x",1,0) -> 1 | L12: =IF(L60="x",1,0) -> 1 | M12: =IF(M60="x",1,0) -> 1 | N12: =IF(N60="x",1,0) -> 1 | O12: =IF(O60="x",1,0) -> 1 | P12: =IF(P60="x",1,0) -> 1 | Q12: =IF(Q60="x",1,0) -> 1 | R12: =IF(R60="x",1,0) -> 1 | ... BR12: =IF(BR60="x",1,0) -> 0
K13: =IF(K61="x",1,0) -> 1 | L13: =IF(L61="x",1,0) -> 1 | M13: =IF(M61="x",1,0) -> 1 | N13: =IF(N61="x",1,0) -> 1 | O13: =IF(O61="x",1,0) -> 1 | P13: =IF(P61="x",1,0) -> 1 | Q13: =IF(Q61="x",1,0) -> 1 | R13: =IF(R61="x",1,0) -> 1 | ... BR13: =IF(BR61="x",1,0) -> 0
K14: =IF(K62="x",1,0) -> 1 | L14: =IF(L62="x",1,0) -> 1 | M14: =IF(M62="x",1,0) -> 1 | N14: =IF(N62="x",1,0) -> 1 | O14: =IF(O62="x",1,0) -> 1 | P14: =IF(P62="x",1,0) -> 1 | Q14: =IF(Q62="x",1,0) -> 1 | R14: =IF(R62="x",1,0) -> 1 | ... BR14: =IF(BR62="x",1,0) -> 0
... K22: =IF(K70="x",1,0) -> 1 | L22: =IF(L70="x",1,0) -> 1 | M22: =IF(M70="x",1,0) -> 1 | N22: =IF(N70="x",1,0) -> 1 | O22: =IF(O70="x",1,0) -> 1 | P22: =IF(P70="x",1,0) -> 1 | Q22: =IF(Q70="x",1,0) -> 1 | R22: =IF(R70="x",1,0) -> 1 | ... BR22: =IF(BR70="x",1,0) -> 0
H24: Período Máximo | I24: Linha Índice | K24: M1 | L24: M2 | M24: M3 | N24: M4 | O24: M5 | P24: M6 | Q24: M7 | R24: M8 | S24: M9 | T24: M10 | U24: M11 | V24: M12 | W24: M13 | X24: M14 | Y24: M15 | Z24: M16 | AA24: M17 | AB24: M18 | AC24: M19 | AD24: M20 | AE24: M21 | AF24: M22 | AG24: M23 | AH24: M24 | AI24: M25 | AJ24: M26 | AK24: M27 | AL24: M28 | AM24: M29 | AN24: M30 | AO24: M31 | AP24: M32 | AQ24: M33 | AR24: M34 | AS24: M35 | AT24: M36 | AU24: M37 | AV24: M38 | AW24: M39 | AX24: M40 | AY24: M41 | AZ24: M42 | BA24: M43 | BB24: M44 | BC24: M45 | BD24: M46 | BE24: M47 | BF24: M48 | BG24: M49 | BH24: M50 | BI24: M51 | BJ24: M52 | BK24: M53 | BL24: M54 | BM24: M55 | BN24: M56 | BO24: M57 | BP24: M58 | BQ24: M59 | BR24: M60
H25: =MAX(K25:BR25) -> 10 | I25: =IFERROR(VLOOKUP(CONCATENATE(I77,".",H25),'Curva S'!$A$2:$B$301,2,0),0) -> 250 | K25: =IF(K3>0,SUM($K3:K3),0) -> 1 | L25: =IF(L3>0,SUM($K3:L3),0) -> 2 | M25: =IF(M3>0,SUM($K3:M3),0) -> 3 | N25: =IF(N3>0,SUM($K3:N3),0) -> 4 | O25: =IF(O3>0,SUM($K3:O3),0) -> 5 | P25: =IF(P3>0,SUM($K3:P3),0) -> 6 | Q25: =IF(Q3>0,SUM($K3:Q3),0) -> 7 | R25: =IF(R3>0,SUM($K3:R3),0) -> 8 | ... BR25: =IF(BR3>0,SUM($K3:BR3),0) -> 0
H26: =MAX(K26:BR26) -> 10 | I26: =IFERROR(VLOOKUP(CONCATENATE(I78,".",H26),'Curva S'!$A$2:$B$301,2,0),0) -> 250 | K26: =IF(K4>0,SUM($K4:K4),0) -> 1 | L26: =IF(L4>0,SUM($K4:L4),0) -> 2 | M26: =IF(M4>0,SUM($K4:M4),0) -> 3 | N26: =IF(N4>0,SUM($K4:N4),0) -> 4 | O26: =IF(O4>0,SUM($K4:O4),0) -> 5 | P26: =IF(P4>0,SUM($K4:P4),0) -> 6 | Q26: =IF(Q4>0,SUM($K4:Q4),0) -> 7 | R26: =IF(R4>0,SUM($K4:R4),0) -> 8 | ... BR26: =IF(BR4>0,SUM($K4:BR4),0) -> 0
H27: =MAX(K27:BR27) -> 10 | I27: =IFERROR(VLOOKUP(CONCATENATE(I79,".",H27),'Curva S'!$A$2:$B$301,2,0),0) -> 250 | K27: =IF(K5>0,SUM($K5:K5),0) -> 1 | L27: =IF(L5>0,SUM($K5:L5),0) -> 2 | M27: =IF(M5>0,SUM($K5:M5),0) -> 3 | N27: =IF(N5>0,SUM($K5:N5),0) -> 4 | O27: =IF(O5>0,SUM($K5:O5),0) -> 5 | P27: =IF(P5>0,SUM($K5:P5),0) -> 6 | Q27: =IF(Q5>0,SUM($K5:Q5),0) -> 7 | R27: =IF(R5>0,SUM($K5:R5),0) -> 8 | ... BR27: =IF(BR5>0,SUM($K5:BR5),0) -> 0
H28: =MAX(K28:BR28) -> 10 | I28: =IFERROR(VLOOKUP(CONCATENATE(I80,".",H28),'Curva S'!$A$2:$B$301,2,0),0) -> 250 | K28: =IF(K6>0,SUM($K6:K6),0) -> 1 | L28: =IF(L6>0,SUM($K6:L6),0) -> 2 | M28: =IF(M6>0,SUM($K6:M6),0) -> 3 | N28: =IF(N6>0,SUM($K6:N6),0) -> 4 | O28: =IF(O6>0,SUM($K6:O6),0) -> 5 | P28: =IF(P6>0,SUM($K6:P6),0) -> 6 | Q28: =IF(Q6>0,SUM($K6:Q6),0) -> 7 | R28: =IF(R6>0,SUM($K6:R6),0) -> 8 | ... BR28: =IF(BR6>0,SUM($K6:BR6),0) -> 0
H29: =MAX(K29:BR29) -> 10 | I29: =IFERROR(VLOOKUP(CONCATENATE(I81,".",H29),'Curva S'!$A$2:$B$301,2,0),0) -> 250 | K29: =IF(K7>0,SUM($K7:K7),0) -> 1 | L29: =IF(L7>0,SUM($K7:L7),0) -> 2 | M29: =IF(M7>0,SUM($K7:M7),0) -> 3 | N29: =IF(N7>0,SUM($K7:N7),0) -> 4 | O29: =IF(O7>0,SUM($K7:O7),0) -> 5 | P29: =IF(P7>0,SUM($K7:P7),0) -> 6 | Q29: =IF(Q7>0,SUM($K7:Q7),0) -> 7 | R29: =IF(R7>0,SUM($K7:R7),0) -> 8 | ... BR29: =IF(BR7>0,SUM($K7:BR7),0) -> 0
H30: =MAX(K30:BR30) -> 10 | I30: =IFERROR(VLOOKUP(CONCATENATE(I82,".",H30),'Curva S'!$A$2:$B$301,2,0),0) -> 250 | K30: =IF(K8>0,SUM($K8:K8),0) -> 1 | L30: =IF(L8>0,SUM($K8:L8),0) -> 2 | M30: =IF(M8>0,SUM($K8:M8),0) -> 3 | N30: =IF(N8>0,SUM($K8:N8),0) -> 4 | O30: =IF(O8>0,SUM($K8:O8),0) -> 5 | P30: =IF(P8>0,SUM($K8:P8),0) -> 6 | Q30: =IF(Q8>0,SUM($K8:Q8),0) -> 7 | R30: =IF(R8>0,SUM($K8:R8),0) -> 8 | ... BR30: =IF(BR8>0,SUM($K8:BR8),0) -> 0
H31: =MAX(K31:BR31) -> 10 | I31: =IFERROR(VLOOKUP(CONCATENATE(I83,".",H31),'Curva S'!$A$2:$B$301,2,0),0) -> 250 | K31: =IF(K9>0,SUM($K9:K9),0) -> 1 | L31: =IF(L9>0,SUM($K9:L9),0) -> 2 | M31: =IF(M9>0,SUM($K9:M9),0) -> 3 | N31: =IF(N9>0,SUM($K9:N9),0) -> 4 | O31: =IF(O9>0,SUM($K9:O9),0) -> 5 | P31: =IF(P9>0,SUM($K9:P9),0) -> 6 | Q31: =IF(Q9>0,SUM($K9:Q9),0) -> 7 | R31: =IF(R9>0,SUM($K9:R9),0) -> 8 | ... BR31: =IF(BR9>0,SUM($K9:BR9),0) -> 0
H32: =MAX(K32:BR32) -> 10 | I32: =IFERROR(VLOOKUP(CONCATENATE(I84,".",H32),'Curva S'!$A$2:$B$301,2,0),0) -> 250 | K32: =IF(K10>0,SUM($K10:K10),0) -> 1 | L32: =IF(L10>0,SUM($K10:L10),0) -> 2 | M32: =IF(M10>0,SUM($K10:M10),0) -> 3 | N32: =IF(N10>0,SUM($K10:N10),0) -> 4 | O32: =IF(O10>0,SUM($K10:O10),0) -> 5 | P32: =IF(P10>0,SUM($K10:P10),0) -> 6 | Q32: =IF(Q10>0,SUM($K10:Q10),0) -> 7 | R32: =IF(R10>0,SUM($K10:R10),0) -> 8 | ... BR32: =IF(BR10>0,SUM($K10:BR10),0) -> 0
H33: =MAX(K33:BR33) -> 10 | I33: =IFERROR(VLOOKUP(CONCATENATE(I85,".",H33),'Curva S'!$A$2:$B$301,2,0),0) -> 250 | K33: =IF(K11>0,SUM($K11:K11),0) -> 1 | L33: =IF(L11>0,SUM($K11:L11),0) -> 2 | M33: =IF(M11>0,SUM($K11:M11),0) -> 3 | N33: =IF(N11>0,SUM($K11:N11),0) -> 4 | O33: =IF(O11>0,SUM($K11:O11),0) -> 5 | P33: =IF(P11>0,SUM($K11:P11),0) -> 6 | Q33: =IF(Q11>0,SUM($K11:Q11),0) -> 7 | R33: =IF(R11>0,SUM($K11:R11),0) -> 8 | ... BR33: =IF(BR11>0,SUM($K11:BR11),0) -> 0
H34: =MAX(K34:BR34) -> 10 | I34: =IFERROR(VLOOKUP(CONCATENATE(I86,".",H34),'Curva S'!$A$2:$B$301,2,0),0) -> 250 | K34: =IF(K12>0,SUM($K12:K12),0) -> 1 | L34: =IF(L12>0,SUM($K12:L12),0) -> 2 | M34: =IF(M12>0,SUM($K12:M12),0) -> 3 | N34: =IF(N12>0,SUM($K12:N12),0) -> 4 | O34: =IF(O12>0,SUM($K12:O12),0) -> 5 | P34: =IF(P12>0,SUM($K12:P12),0) -> 6 | Q34: =IF(Q12>0,SUM($K12:Q12),0) -> 7 | R34: =IF(R12>0,SUM($K12:R12),0) -> 8 | ... BR34: =IF(BR12>0,SUM($K12:BR12),0) -> 0
H35: =MAX(K35:BR35) -> 10 | I35: =IFERROR(VLOOKUP(CONCATENATE(I87,".",H35),'Curva S'!$A$2:$B$301,2,0),0) -> 250 | K35: =IF(K13>0,SUM($K13:K13),0) -> 1 | L35: =IF(L13>0,SUM($K13:L13),0) -> 2 | M35: =IF(M13>0,SUM($K13:M13),0) -> 3 | N35: =IF(N13>0,SUM($K13:N13),0) -> 4 | O35: =IF(O13>0,SUM($K13:O13),0) -> 5 | P35: =IF(P13>0,SUM($K13:P13),0) -> 6 | Q35: =IF(Q13>0,SUM($K13:Q13),0) -> 7 | R35: =IF(R13>0,SUM($K13:R13),0) -> 8 | ... BR35: =IF(BR13>0,SUM($K13:BR13),0) -> 0
H36: =MAX(K36:BR36) -> 10 | I36: =IFERROR(VLOOKUP(CONCATENATE(I88,".",H36),'Curva S'!$A$2:$B$301,2,0),0) -> 250 | K36: =IF(K14>0,SUM($K14:K14),0) -> 1 | L36: =IF(L14>0,SUM($K14:L14),0) -> 2 | M36: =IF(M14>0,SUM($K14:M14),0) -> 3 | N36: =IF(N14>0,SUM($K14:N14),0) -> 4 | O36: =IF(O14>0,SUM($K14:O14),0) -> 5 | P36: =IF(P14>0,SUM($K14:P14),0) -> 6 | Q36: =IF(Q14>0,SUM($K14:Q14),0) -> 7 | R36: =IF(R14>0,SUM($K14:R14),0) -> 8 | ... BR36: =IF(BR14>0,SUM($K14:BR14),0) -> 0
... H44: =MAX(K44:BR44) -> 10 | I44: =IFERROR(VLOOKUP(CONCATENATE(I96,".",H44),'Curva S'!$A$2:$B$301,2,0),0) -> 250 | K44: =IF(K22>0,SUM($K22:K22),0) -> 1 | L44: =IF(L22>0,SUM($K22:L22),0) -> 2 | M44: =IF(M22>0,SUM($K22:M22),0) -> 3 | N44: =IF(N22>0,SUM($K22:N22),0) -> 4 | O44: =IF(O22>0,SUM($K22:O22),0) -> 5 | P44: =IF(P22>0,SUM($K22:P22),0) -> 6 | Q44: =IF(Q22>0,SUM($K22:Q22),0) -> 7 | R44: =IF(R22>0,SUM($K22:R22),0) -> 8 | ... BR44: =IF(BR22>0,SUM($K22:BR22),0) -> 0
D46: Cronograma e Histograma | K46: Ano 1 | W46: Ano 2 | AI46: Ano 3 | AU46: Ano 4 | BG46: Ano 5
K47: 1 | L47: 2 | M47: 3 | N47: 4 | O47: 5 | P47: 6 | Q47: 7 | R47: 8 | S47: 9 | T47: 10 | U47: 11 | V47: 12 | W47: 13 | X47: 14 | Y47: 15 | Z47: 16 | AA47: 17 | AB47: 18 | AC47: 19 | AD47: 20 | AE47: 21 | AF47: 22 | AG47: 23 | AH47: 24 | AI47: 25 | AJ47: 26 | AK47: 27 | AL47: 28 | AM47: 29 | AN47: 30 | AO47: 31 | AP47: 32 | AQ47: 33 | AR47: 34 | AS47: 35 | AT47: 36 | AU47: 37 | AV47: 38 | AW47: 39 | AX47: 40 | AY47: 41 | AZ47: 42 | BA47: 43 | BB47: 44 | BC47: 45 | BD47: 46 | BE47: 47 | BF47: 48 | BG47: 49 | BH47: 50 | BI47: 51 | BJ47: 52 | BK47: 53 | BL47: 54 | BM47: 55 | BN47: 56 | BO47: 57 | BP47: 58 | BQ47: 59 | BR47: 60
D49: Etapa 01 | F49: Cronograma de execução
F50: Sigla | G50: Equipe | H50: Horas Calculadas | I50: Período Total
D51: Orientação de Preenchimento 1. Somente preencher os campos em branco 2. Deverá ser preenchido com "X" cada mês que a discipina estará em atuação no projeto | F51: =Tarefas!G3 -> Equipe_01 | G51: =Tarefas!F3 -> Equipe01 | H51: =Tarefas!O3 -> 1992.4667 | I51: =COUNTIF(K51:BR51,"X") -> 10 | K51: =IF(COLUMN()-COLUMN($K51)+1<=Dashboard!$D$14,"X","") -> X | L51: =IF(COLUMN()-COLUMN($K51)+1<=Dashboard!$D$14,"X","") -> X | M51: =IF(COLUMN()-COLUMN($K51)+1<=Dashboard!$D$14,"X","") -> X | N51: =IF(COLUMN()-COLUMN($K51)+1<=Dashboard!$D$14,"X","") -> X | O51: =IF(COLUMN()-COLUMN($K51)+1<=Dashboard!$D$14,"X","") -> X | P51: =IF(COLUMN()-COLUMN($K51)+1<=Dashboard!$D$14,"X","") -> X | Q51: =IF(COLUMN()-COLUMN($K51)+1<=Dashboard!$D$14,"X","") -> X | R51: =IF(COLUMN()-COLUMN($K51)+1<=Dashboard!$D$14,"X","") -> X | ... BR51: =IF(COLUMN()-COLUMN($K51)+1<=Dashboard!$D$14,"X","")
F52: =Tarefas!G4 -> Equipe_02 | G52: =Tarefas!F4 -> Equipe02 | H52: =Tarefas!O4 -> 1394.7267 | I52: =COUNTIF(K52:BR52,"X") -> 10 | K52: =IF(COLUMN()-COLUMN($K52)+1<=Dashboard!$D$14,"X","") -> X | L52: =IF(COLUMN()-COLUMN($K52)+1<=Dashboard!$D$14,"X","") -> X | M52: =IF(COLUMN()-COLUMN($K52)+1<=Dashboard!$D$14,"X","") -> X | N52: =IF(COLUMN()-COLUMN($K52)+1<=Dashboard!$D$14,"X","") -> X | O52: =IF(COLUMN()-COLUMN($K52)+1<=Dashboard!$D$14,"X","") -> X | P52: =IF(COLUMN()-COLUMN($K52)+1<=Dashboard!$D$14,"X","") -> X | Q52: =IF(COLUMN()-COLUMN($K52)+1<=Dashboard!$D$14,"X","") -> X | R52: =IF(COLUMN()-COLUMN($K52)+1<=Dashboard!$D$14,"X","") -> X | ... BR52: =IF(COLUMN()-COLUMN($K52)+1<=Dashboard!$D$14,"X","")
F53: =Tarefas!G5 -> Equipe_03 | G53: =Tarefas!F5 -> Equipe03 | H53: =Tarefas!O5 -> 242 | I53: =COUNTIF(K53:BR53,"X") -> 10 | K53: =IF(COLUMN()-COLUMN($K53)+1<=Dashboard!$D$14,"X","") -> X | L53: =IF(COLUMN()-COLUMN($K53)+1<=Dashboard!$D$14,"X","") -> X | M53: =IF(COLUMN()-COLUMN($K53)+1<=Dashboard!$D$14,"X","") -> X | N53: =IF(COLUMN()-COLUMN($K53)+1<=Dashboard!$D$14,"X","") -> X | O53: =IF(COLUMN()-COLUMN($K53)+1<=Dashboard!$D$14,"X","") -> X | P53: =IF(COLUMN()-COLUMN($K53)+1<=Dashboard!$D$14,"X","") -> X | Q53: =IF(COLUMN()-COLUMN($K53)+1<=Dashboard!$D$14,"X","") -> X | R53: =IF(COLUMN()-COLUMN($K53)+1<=Dashboard!$D$14,"X","") -> X | ... BR53: =IF(COLUMN()-COLUMN($K53)+1<=Dashboard!$D$14,"X","")
F54: =Tarefas!G6 -> Equipe_04 | G54: =Tarefas!F6 -> Equipe04 | H54: =Tarefas!O6 -> 580.8 | I54: =COUNTIF(K54:BR54,"X") -> 10 | K54: =IF(COLUMN()-COLUMN($K54)+1<=Dashboard!$D$14,"X","") -> X | L54: =IF(COLUMN()-COLUMN($K54)+1<=Dashboard!$D$14,"X","") -> X | M54: =IF(COLUMN()-COLUMN($K54)+1<=Dashboard!$D$14,"X","") -> X | N54: =IF(COLUMN()-COLUMN($K54)+1<=Dashboard!$D$14,"X","") -> X | O54: =IF(COLUMN()-COLUMN($K54)+1<=Dashboard!$D$14,"X","") -> X | P54: =IF(COLUMN()-COLUMN($K54)+1<=Dashboard!$D$14,"X","") -> X | Q54: =IF(COLUMN()-COLUMN($K54)+1<=Dashboard!$D$14,"X","") -> X | R54: =IF(COLUMN()-COLUMN($K54)+1<=Dashboard!$D$14,"X","") -> X | ... BR54: =IF(COLUMN()-COLUMN($K54)+1<=Dashboard!$D$14,"X","")
F55: =Tarefas!G7 -> Equipe_05 | G55: =Tarefas!F7 -> Equipe05 | H55: =Tarefas!O7 -> 1176.12 | I55: =COUNTIF(K55:BR55,"X") -> 10 | K55: =IF(COLUMN()-COLUMN($K55)+1<=Dashboard!$D$14,"X","") -> X | L55: =IF(COLUMN()-COLUMN($K55)+1<=Dashboard!$D$14,"X","") -> X | M55: =IF(COLUMN()-COLUMN($K55)+1<=Dashboard!$D$14,"X","") -> X | N55: =IF(COLUMN()-COLUMN($K55)+1<=Dashboard!$D$14,"X","") -> X | O55: =IF(COLUMN()-COLUMN($K55)+1<=Dashboard!$D$14,"X","") -> X | P55: =IF(COLUMN()-COLUMN($K55)+1<=Dashboard!$D$14,"X","") -> X | Q55: =IF(COLUMN()-COLUMN($K55)+1<=Dashboard!$D$14,"X","") -> X | R55: =IF(COLUMN()-COLUMN($K55)+1<=Dashboard!$D$14,"X","") -> X | ... BR55: =IF(COLUMN()-COLUMN($K55)+1<=Dashboard!$D$14,"X","")
F56: =Tarefas!G8 -> Equipe_06 | G56: =Tarefas!F8 -> Equipe06 | H56: =Tarefas!O8 -> 2089.2667 | I56: =COUNTIF(K56:BR56,"X") -> 10 | K56: =IF(COLUMN()-COLUMN($K56)+1<=Dashboard!$D$14,"X","") -> X | L56: =IF(COLUMN()-COLUMN($K56)+1<=Dashboard!$D$14,"X","") -> X | M56: =IF(COLUMN()-COLUMN($K56)+1<=Dashboard!$D$14,"X","") -> X | N56: =IF(COLUMN()-COLUMN($K56)+1<=Dashboard!$D$14,"X","") -> X | O56: =IF(COLUMN()-COLUMN($K56)+1<=Dashboard!$D$14,"X","") -> X | P56: =IF(COLUMN()-COLUMN($K56)+1<=Dashboard!$D$14,"X","") -> X | Q56: =IF(COLUMN()-COLUMN($K56)+1<=Dashboard!$D$14,"X","") -> X | R56: =IF(COLUMN()-COLUMN($K56)+1<=Dashboard!$D$14,"X","") -> X | ... BR56: =IF(COLUMN()-COLUMN($K56)+1<=Dashboard!$D$14,"X","")
F57: =Tarefas!G9 -> Equipe_07 | G57: =Tarefas!F9 -> Equipe07 | H57: =Tarefas!O9 -> 0 | I57: =COUNTIF(K57:BR57,"X") -> 10 | K57: =IF(COLUMN()-COLUMN($K57)+1<=Dashboard!$D$14,"X","") -> X | L57: =IF(COLUMN()-COLUMN($K57)+1<=Dashboard!$D$14,"X","") -> X | M57: =IF(COLUMN()-COLUMN($K57)+1<=Dashboard!$D$14,"X","") -> X | N57: =IF(COLUMN()-COLUMN($K57)+1<=Dashboard!$D$14,"X","") -> X | O57: =IF(COLUMN()-COLUMN($K57)+1<=Dashboard!$D$14,"X","") -> X | P57: =IF(COLUMN()-COLUMN($K57)+1<=Dashboard!$D$14,"X","") -> X | Q57: =IF(COLUMN()-COLUMN($K57)+1<=Dashboard!$D$14,"X","") -> X | R57: =IF(COLUMN()-COLUMN($K57)+1<=Dashboard!$D$14,"X","") -> X | ... BR57: =IF(COLUMN()-COLUMN($K57)+1<=Dashboard!$D$14,"X","")
F58: =Tarefas!G10 -> Equipe_08 | G58: =Tarefas!F10 -> Equipe08 | H58: =Tarefas!O10 -> 0 | I58: =COUNTIF(K58:BR58,"X") -> 10 | K58: =IF(COLUMN()-COLUMN($K58)+1<=Dashboard!$D$14,"X","") -> X | L58: =IF(COLUMN()-COLUMN($K58)+1<=Dashboard!$D$14,"X","") -> X | M58: =IF(COLUMN()-COLUMN($K58)+1<=Dashboard!$D$14,"X","") -> X | N58: =IF(COLUMN()-COLUMN($K58)+1<=Dashboard!$D$14,"X","") -> X | O58: =IF(COLUMN()-COLUMN($K58)+1<=Dashboard!$D$14,"X","") -> X | P58: =IF(COLUMN()-COLUMN($K58)+1<=Dashboard!$D$14,"X","") -> X | Q58: =IF(COLUMN()-COLUMN($K58)+1<=Dashboard!$D$14,"X","") -> X | R58: =IF(COLUMN()-COLUMN($K58)+1<=Dashboard!$D$14,"X","") -> X | ... BR58: =IF(COLUMN()-COLUMN($K58)+1<=Dashboard!$D$14,"X","")
F59: =Tarefas!G11 -> Equipe_09 | G59: =Tarefas!F11 -> Equipe09 | H59: =Tarefas!O11 -> 0 | I59: =COUNTIF(K59:BR59,"X") -> 10 | K59: =IF(COLUMN()-COLUMN($K59)+1<=Dashboard!$D$14,"X","") -> X | L59: =IF(COLUMN()-COLUMN($K59)+1<=Dashboard!$D$14,"X","") -> X | M59: =IF(COLUMN()-COLUMN($K59)+1<=Dashboard!$D$14,"X","") -> X | N59: =IF(COLUMN()-COLUMN($K59)+1<=Dashboard!$D$14,"X","") -> X | O59: =IF(COLUMN()-COLUMN($K59)+1<=Dashboard!$D$14,"X","") -> X | P59: =IF(COLUMN()-COLUMN($K59)+1<=Dashboard!$D$14,"X","") -> X | Q59: =IF(COLUMN()-COLUMN($K59)+1<=Dashboard!$D$14,"X","") -> X | R59: =IF(COLUMN()-COLUMN($K59)+1<=Dashboard!$D$14,"X","") -> X | ... BR59: =IF(COLUMN()-COLUMN($K59)+1<=Dashboard!$D$14,"X","")
F60: =Tarefas!G12 -> Equipe_10 | G60: =Tarefas!F12 -> Equipe10 | H60: =Tarefas!O12 -> 133.1 | I60: =COUNTIF(K60:BR60,"X") -> 10 | K60: =IF(COLUMN()-COLUMN($K60)+1<=Dashboard!$D$14,"X","") -> X | L60: =IF(COLUMN()-COLUMN($K60)+1<=Dashboard!$D$14,"X","") -> X | M60: =IF(COLUMN()-COLUMN($K60)+1<=Dashboard!$D$14,"X","") -> X | N60: =IF(COLUMN()-COLUMN($K60)+1<=Dashboard!$D$14,"X","") -> X | O60: =IF(COLUMN()-COLUMN($K60)+1<=Dashboard!$D$14,"X","") -> X | P60: =IF(COLUMN()-COLUMN($K60)+1<=Dashboard!$D$14,"X","") -> X | Q60: =IF(COLUMN()-COLUMN($K60)+1<=Dashboard!$D$14,"X","") -> X | R60: =IF(COLUMN()-COLUMN($K60)+1<=Dashboard!$D$14,"X","") -> X | ... BR60: =IF(COLUMN()-COLUMN($K60)+1<=Dashboard!$D$14,"X","")
F61: =Tarefas!G13 -> Equipe_11 | G61: =Tarefas!F13 -> Equipe11 | H61: =Tarefas!O13 -> 0 | I61: =COUNTIF(K61:BR61,"X") -> 10 | K61: =IF(COLUMN()-COLUMN($K61)+1<=Dashboard!$D$14,"X","") -> X | L61: =IF(COLUMN()-COLUMN($K61)+1<=Dashboard!$D$14,"X","") -> X | M61: =IF(COLUMN()-COLUMN($K61)+1<=Dashboard!$D$14,"X","") -> X | N61: =IF(COLUMN()-COLUMN($K61)+1<=Dashboard!$D$14,"X","") -> X | O61: =IF(COLUMN()-COLUMN($K61)+1<=Dashboard!$D$14,"X","") -> X | P61: =IF(COLUMN()-COLUMN($K61)+1<=Dashboard!$D$14,"X","") -> X | Q61: =IF(COLUMN()-COLUMN($K61)+1<=Dashboard!$D$14,"X","") -> X | R61: =IF(COLUMN()-COLUMN($K61)+1<=Dashboard!$D$14,"X","") -> X | ... BR61: =IF(COLUMN()-COLUMN($K61)+1<=Dashboard!$D$14,"X","")
F62: =Tarefas!G14 -> Equipe_12 | G62: =Tarefas!F14 -> Equipe12 | H62: =Tarefas!O14 -> 0 | I62: =COUNTIF(K62:BR62,"X") -> 10 | K62: =IF(COLUMN()-COLUMN($K62)+1<=Dashboard!$D$14,"X","") -> X | L62: =IF(COLUMN()-COLUMN($K62)+1<=Dashboard!$D$14,"X","") -> X | M62: =IF(COLUMN()-COLUMN($K62)+1<=Dashboard!$D$14,"X","") -> X | N62: =IF(COLUMN()-COLUMN($K62)+1<=Dashboard!$D$14,"X","") -> X | O62: =IF(COLUMN()-COLUMN($K62)+1<=Dashboard!$D$14,"X","") -> X | P62: =IF(COLUMN()-COLUMN($K62)+1<=Dashboard!$D$14,"X","") -> X | Q62: =IF(COLUMN()-COLUMN($K62)+1<=Dashboard!$D$14,"X","") -> X | R62: =IF(COLUMN()-COLUMN($K62)+1<=Dashboard!$D$14,"X","") -> X | ... BR62: =IF(COLUMN()-COLUMN($K62)+1<=Dashboard!$D$14,"X","")
F63: =Tarefas!G15 -> Equipe_13 | G63: =Tarefas!F15 -> Equipe13 | H63: =Tarefas!O15 -> 0 | I63: =COUNTIF(K63:BR63,"X") -> 10 | K63: =IF(COLUMN()-COLUMN($K63)+1<=Dashboard!$D$14,"X","") -> X | L63: =IF(COLUMN()-COLUMN($K63)+1<=Dashboard!$D$14,"X","") -> X | M63: =IF(COLUMN()-COLUMN($K63)+1<=Dashboard!$D$14,"X","") -> X | N63: =IF(COLUMN()-COLUMN($K63)+1<=Dashboard!$D$14,"X","") -> X | O63: =IF(COLUMN()-COLUMN($K63)+1<=Dashboard!$D$14,"X","") -> X | P63: =IF(COLUMN()-COLUMN($K63)+1<=Dashboard!$D$14,"X","") -> X | Q63: =IF(COLUMN()-COLUMN($K63)+1<=Dashboard!$D$14,"X","") -> X | R63: =IF(COLUMN()-COLUMN($K63)+1<=Dashboard!$D$14,"X","") -> X | ... BR63: =IF(COLUMN()-COLUMN($K63)+1<=Dashboard!$D$14,"X","")
... F70: =Tarefas!G22 -> Equipe_20 | G70: =Tarefas!F22 -> Equipe20 | H70: =Tarefas!O22 -> 198.44 | I70: =COUNTIF(K70:BR70,"X") -> 10 | K70: =IF(COLUMN()-COLUMN($K70)+1<=Dashboard!$D$14,"X","") -> X | L70: =IF(COLUMN()-COLUMN($K70)+1<=Dashboard!$D$14,"X","") -> X | M70: =IF(COLUMN()-COLUMN($K70)+1<=Dashboard!$D$14,"X","") -> X | N70: =IF(COLUMN()-COLUMN($K70)+1<=Dashboard!$D$14,"X","") -> X | O70: =IF(COLUMN()-COLUMN($K70)+1<=Dashboard!$D$14,"X","") -> X | P70: =IF(COLUMN()-COLUMN($K70)+1<=Dashboard!$D$14,"X","") -> X | Q70: =IF(COLUMN()-COLUMN($K70)+1<=Dashboard!$D$14,"X","") -> X | R70: =IF(COLUMN()-COLUMN($K70)+1<=Dashboard!$D$14,"X","") -> X | ... BR70: =IF(COLUMN()-COLUMN($K70)+1<=Dashboard!$D$14,"X","")
F71: Período de Execução Total (meses) | I71: =COUNTIF(K71:BR71,"X") -> 10 | K71: =IF(SUM(K3:K22)>0,"x","") -> x | L71: =IF(SUM(L3:L22)>0,"x","") -> x | M71: =IF(SUM(M3:M22)>0,"x","") -> x | N71: =IF(SUM(N3:N22)>0,"x","") -> x | O71: =IF(SUM(O3:O22)>0,"x","") -> x | P71: =IF(SUM(P3:P22)>0,"x","") -> x | Q71: =IF(SUM(Q3:Q22)>0,"x","") -> x | R71: =IF(SUM(R3:R22)>0,"x","") -> x | ... BR71: =IF(SUM(BR3:BR22)>0,"x","")
D75: Etapa 02 | F75: Avanço da Obra - Curva S
F76: Sigla | G76: Equipe | H76: Percentual | I76: Curva S
D77: Orientação de Preenchimento 1. Somente preencher os campos em branco 2. Selecionar o tipo de curva que deverá ser aplicada no planejamento da mão de obra de cada uma das disciplinas presentes no projeto | F77: =F51 -> Equipe_01 | G77: =G51 -> Equipe01 | H77: =SUM(K77:BR77) -> 1 | I77: Lin | K77: {=IFERROR(IF(K3=1,INDEX('Curva S'!$C$2:$BJ$301,$I25,K25),0),0)} -> 0.1 | L77: {=IFERROR(IF(L3=1,INDEX('Curva S'!$C$2:$BJ$301,$I25,L25),0),0)} -> 0.1 | M77: {=IFERROR(IF(M3=1,INDEX('Curva S'!$C$2:$BJ$301,$I25,M25),0),0)} -> 0.1 | N77: {=IFERROR(IF(N3=1,INDEX('Curva S'!$C$2:$BJ$301,$I25,N25),0),0)} -> 0.1 | O77: {=IFERROR(IF(O3=1,INDEX('Curva S'!$C$2:$BJ$301,$I25,O25),0),0)} -> 0.1 | P77: {=IFERROR(IF(P3=1,INDEX('Curva S'!$C$2:$BJ$301,$I25,P25),0),0)} -> 0.1 | Q77: {=IFERROR(IF(Q3=1,INDEX('Curva S'!$C$2:$BJ$301,$I25,Q25),0),0)} -> 0.1 | R77: {=IFERROR(IF(R3=1,INDEX('Curva S'!$C$2:$BJ$301,$I25,R25),0),0)} -> 0.1 | ... BR77: {=IFERROR(IF(BR3=1,INDEX('Curva S'!$C$2:$BJ$301,$I25,BR25),0),0)} -> 0
F78: =F52 -> Equipe_02 | G78: =G52 -> Equipe02 | H78: =SUM(K78:BR78) -> 1 | I78: Lin | K78: {=IFERROR(IF(K4=1,INDEX('Curva S'!$C$2:$BJ$301,$I26,K26),0),0)} -> 0.1 | L78: {=IFERROR(IF(L4=1,INDEX('Curva S'!$C$2:$BJ$301,$I26,L26),0),0)} -> 0.1 | M78: {=IFERROR(IF(M4=1,INDEX('Curva S'!$C$2:$BJ$301,$I26,M26),0),0)} -> 0.1 | N78: {=IFERROR(IF(N4=1,INDEX('Curva S'!$C$2:$BJ$301,$I26,N26),0),0)} -> 0.1 | O78: {=IFERROR(IF(O4=1,INDEX('Curva S'!$C$2:$BJ$301,$I26,O26),0),0)} -> 0.1 | P78: {=IFERROR(IF(P4=1,INDEX('Curva S'!$C$2:$BJ$301,$I26,P26),0),0)} -> 0.1 | Q78: {=IFERROR(IF(Q4=1,INDEX('Curva S'!$C$2:$BJ$301,$I26,Q26),0),0)} -> 0.1 | R78: {=IFERROR(IF(R4=1,INDEX('Curva S'!$C$2:$BJ$301,$I26,R26),0),0)} -> 0.1 | ... BR78: {=IFERROR(IF(BR4=1,INDEX('Curva S'!$C$2:$BJ$301,$I26,BR26),0),0)} -> 0
F79: =F53 -> Equipe_03 | G79: =G53 -> Equipe03 | H79: =SUM(K79:BR79) -> 1 | I79: Lin | K79: {=IFERROR(IF(K5=1,INDEX('Curva S'!$C$2:$BJ$301,$I27,K27),0),0)} -> 0.1 | L79: {=IFERROR(IF(L5=1,INDEX('Curva S'!$C$2:$BJ$301,$I27,L27),0),0)} -> 0.1 | M79: {=IFERROR(IF(M5=1,INDEX('Curva S'!$C$2:$BJ$301,$I27,M27),0),0)} -> 0.1 | N79: {=IFERROR(IF(N5=1,INDEX('Curva S'!$C$2:$BJ$301,$I27,N27),0),0)} -> 0.1 | O79: {=IFERROR(IF(O5=1,INDEX('Curva S'!$C$2:$BJ$301,$I27,O27),0),0)} -> 0.1 | P79: {=IFERROR(IF(P5=1,INDEX('Curva S'!$C$2:$BJ$301,$I27,P27),0),0)} -> 0.1 | Q79: {=IFERROR(IF(Q5=1,INDEX('Curva S'!$C$2:$BJ$301,$I27,Q27),0),0)} -> 0.1 | R79: {=IFERROR(IF(R5=1,INDEX('Curva S'!$C$2:$BJ$301,$I27,R27),0),0)} -> 0.1 | ... BR79: {=IFERROR(IF(BR5=1,INDEX('Curva S'!$C$2:$BJ$301,$I27,BR27),0),0)} -> 0
F80: =F54 -> Equipe_04 | G80: =G54 -> Equipe04 | H80: =SUM(K80:BR80) -> 1 | I80: Lin | K80: {=IFERROR(IF(K6=1,INDEX('Curva S'!$C$2:$BJ$301,$I28,K28),0),0)} -> 0.1 | L80: {=IFERROR(IF(L6=1,INDEX('Curva S'!$C$2:$BJ$301,$I28,L28),0),0)} -> 0.1 | M80: {=IFERROR(IF(M6=1,INDEX('Curva S'!$C$2:$BJ$301,$I28,M28),0),0)} -> 0.1 | N80: {=IFERROR(IF(N6=1,INDEX('Curva S'!$C$2:$BJ$301,$I28,N28),0),0)} -> 0.1 | O80: {=IFERROR(IF(O6=1,INDEX('Curva S'!$C$2:$BJ$301,$I28,O28),0),0)} -> 0.1 | P80: {=IFERROR(IF(P6=1,INDEX('Curva S'!$C$2:$BJ$301,$I28,P28),0),0)} -> 0.1 | Q80: {=IFERROR(IF(Q6=1,INDEX('Curva S'!$C$2:$BJ$301,$I28,Q28),0),0)} -> 0.1 | R80: {=IFERROR(IF(R6=1,INDEX('Curva S'!$C$2:$BJ$301,$I28,R28),0),0)} -> 0.1 | ... BR80: {=IFERROR(IF(BR6=1,INDEX('Curva S'!$C$2:$BJ$301,$I28,BR28),0),0)} -> 0
F81: =F55 -> Equipe_05 | G81: =G55 -> Equipe05 | H81: =SUM(K81:BR81) -> 1 | I81: Lin | K81: {=IFERROR(IF(K7=1,INDEX('Curva S'!$C$2:$BJ$301,$I29,K29),0),0)} -> 0.1 | L81: {=IFERROR(IF(L7=1,INDEX('Curva S'!$C$2:$BJ$301,$I29,L29),0),0)} -> 0.1 | M81: {=IFERROR(IF(M7=1,INDEX('Curva S'!$C$2:$BJ$301,$I29,M29),0),0)} -> 0.1 | N81: {=IFERROR(IF(N7=1,INDEX('Curva S'!$C$2:$BJ$301,$I29,N29),0),0)} -> 0.1 | O81: {=IFERROR(IF(O7=1,INDEX('Curva S'!$C$2:$BJ$301,$I29,O29),0),0)} -> 0.1 | P81: {=IFERROR(IF(P7=1,INDEX('Curva S'!$C$2:$BJ$301,$I29,P29),0),0)} -> 0.1 | Q81: {=IFERROR(IF(Q7=1,INDEX('Curva S'!$C$2:$BJ$301,$I29,Q29),0),0)} -> 0.1 | R81: {=IFERROR(IF(R7=1,INDEX('Curva S'!$C$2:$BJ$301,$I29,R29),0),0)} -> 0.1 | ... BR81: {=IFERROR(IF(BR7=1,INDEX('Curva S'!$C$2:$BJ$301,$I29,BR29),0),0)} -> 0
F82: =F56 -> Equipe_06 | G82: =G56 -> Equipe06 | H82: =SUM(K82:BR82) -> 1 | I82: Lin | K82: {=IFERROR(IF(K8=1,INDEX('Curva S'!$C$2:$BJ$301,$I30,K30),0),0)} -> 0.1 | L82: {=IFERROR(IF(L8=1,INDEX('Curva S'!$C$2:$BJ$301,$I30,L30),0),0)} -> 0.1 | M82: {=IFERROR(IF(M8=1,INDEX('Curva S'!$C$2:$BJ$301,$I30,M30),0),0)} -> 0.1 | N82: {=IFERROR(IF(N8=1,INDEX('Curva S'!$C$2:$BJ$301,$I30,N30),0),0)} -> 0.1 | O82: {=IFERROR(IF(O8=1,INDEX('Curva S'!$C$2:$BJ$301,$I30,O30),0),0)} -> 0.1 | P82: {=IFERROR(IF(P8=1,INDEX('Curva S'!$C$2:$BJ$301,$I30,P30),0),0)} -> 0.1 | Q82: {=IFERROR(IF(Q8=1,INDEX('Curva S'!$C$2:$BJ$301,$I30,Q30),0),0)} -> 0.1 | R82: {=IFERROR(IF(R8=1,INDEX('Curva S'!$C$2:$BJ$301,$I30,R30),0),0)} -> 0.1 | ... BR82: {=IFERROR(IF(BR8=1,INDEX('Curva S'!$C$2:$BJ$301,$I30,BR30),0),0)} -> 0
F83: =F57 -> Equipe_07 | G83: =G57 -> Equipe07 | H83: =SUM(K83:BR83) -> 1 | I83: Lin | K83: {=IFERROR(IF(K9=1,INDEX('Curva S'!$C$2:$BJ$301,$I31,K31),0),0)} -> 0.1 | L83: {=IFERROR(IF(L9=1,INDEX('Curva S'!$C$2:$BJ$301,$I31,L31),0),0)} -> 0.1 | M83: {=IFERROR(IF(M9=1,INDEX('Curva S'!$C$2:$BJ$301,$I31,M31),0),0)} -> 0.1 | N83: {=IFERROR(IF(N9=1,INDEX('Curva S'!$C$2:$BJ$301,$I31,N31),0),0)} -> 0.1 | O83: {=IFERROR(IF(O9=1,INDEX('Curva S'!$C$2:$BJ$301,$I31,O31),0),0)} -> 0.1 | P83: {=IFERROR(IF(P9=1,INDEX('Curva S'!$C$2:$BJ$301,$I31,P31),0),0)} -> 0.1 | Q83: {=IFERROR(IF(Q9=1,INDEX('Curva S'!$C$2:$BJ$301,$I31,Q31),0),0)} -> 0.1 | R83: {=IFERROR(IF(R9=1,INDEX('Curva S'!$C$2:$BJ$301,$I31,R31),0),0)} -> 0.1 | ... BR83: {=IFERROR(IF(BR9=1,INDEX('Curva S'!$C$2:$BJ$301,$I31,BR31),0),0)} -> 0
F84: =F58 -> Equipe_08 | G84: =G58 -> Equipe08 | H84: =SUM(K84:BR84) -> 1 | I84: Lin | K84: {=IFERROR(IF(K10=1,INDEX('Curva S'!$C$2:$BJ$301,$I32,K32),0),0)} -> 0.1 | L84: {=IFERROR(IF(L10=1,INDEX('Curva S'!$C$2:$BJ$301,$I32,L32),0),0)} -> 0.1 | M84: {=IFERROR(IF(M10=1,INDEX('Curva S'!$C$2:$BJ$301,$I32,M32),0),0)} -> 0.1 | N84: {=IFERROR(IF(N10=1,INDEX('Curva S'!$C$2:$BJ$301,$I32,N32),0),0)} -> 0.1 | O84: {=IFERROR(IF(O10=1,INDEX('Curva S'!$C$2:$BJ$301,$I32,O32),0),0)} -> 0.1 | P84: {=IFERROR(IF(P10=1,INDEX('Curva S'!$C$2:$BJ$301,$I32,P32),0),0)} -> 0.1 | Q84: {=IFERROR(IF(Q10=1,INDEX('Curva S'!$C$2:$BJ$301,$I32,Q32),0),0)} -> 0.1 | R84: {=IFERROR(IF(R10=1,INDEX('Curva S'!$C$2:$BJ$301,$I32,R32),0),0)} -> 0.1 | ... BR84: {=IFERROR(IF(BR10=1,INDEX('Curva S'!$C$2:$BJ$301,$I32,BR32),0),0)} -> 0
F85: =F59 -> Equipe_09 | G85: =G59 -> Equipe09 | H85: =SUM(K85:BR85) -> 1 | I85: Lin | K85: {=IFERROR(IF(K11=1,INDEX('Curva S'!$C$2:$BJ$301,$I33,K33),0),0)} -> 0.1 | L85: {=IFERROR(IF(L11=1,INDEX('Curva S'!$C$2:$BJ$301,$I33,L33),0),0)} -> 0.1 | M85: {=IFERROR(IF(M11=1,INDEX('Curva S'!$C$2:$BJ$301,$I33,M33),0),0)} -> 0.1 | N85: {=IFERROR(IF(N11=1,INDEX('Curva S'!$C$2:$BJ$301,$I33,N33),0),0)} -> 0.1 | O85: {=IFERROR(IF(O11=1,INDEX('Curva S'!$C$2:$BJ$301,$I33,O33),0),0)} -> 0.1 | P85: {=IFERROR(IF(P11=1,INDEX('Curva S'!$C$2:$BJ$301,$I33,P33),0),0)} -> 0.1 | Q85: {=IFERROR(IF(Q11=1,INDEX('Curva S'!$C$2:$BJ$301,$I33,Q33),0),0)} -> 0.1 | R85: {=IFERROR(IF(R11=1,INDEX('Curva S'!$C$2:$BJ$301,$I33,R33),0),0)} -> 0.1 | ... BR85: {=IFERROR(IF(BR11=1,INDEX('Curva S'!$C$2:$BJ$301,$I33,BR33),0),0)} -> 0
F86: =F60 -> Equipe_10 | G86: =G60 -> Equipe10 | H86: =SUM(K86:BR86) -> 1 | I86: Lin | K86: {=IFERROR(IF(K12=1,INDEX('Curva S'!$C$2:$BJ$301,$I34,K34),0),0)} -> 0.1 | L86: {=IFERROR(IF(L12=1,INDEX('Curva S'!$C$2:$BJ$301,$I34,L34),0),0)} -> 0.1 | M86: {=IFERROR(IF(M12=1,INDEX('Curva S'!$C$2:$BJ$301,$I34,M34),0),0)} -> 0.1 | N86: {=IFERROR(IF(N12=1,INDEX('Curva S'!$C$2:$BJ$301,$I34,N34),0),0)} -> 0.1 | O86: {=IFERROR(IF(O12=1,INDEX('Curva S'!$C$2:$BJ$301,$I34,O34),0),0)} -> 0.1 | P86: {=IFERROR(IF(P12=1,INDEX('Curva S'!$C$2:$BJ$301,$I34,P34),0),0)} -> 0.1 | Q86: {=IFERROR(IF(Q12=1,INDEX('Curva S'!$C$2:$BJ$301,$I34,Q34),0),0)} -> 0.1 | R86: {=IFERROR(IF(R12=1,INDEX('Curva S'!$C$2:$BJ$301,$I34,R34),0),0)} -> 0.1 | ... BR86: {=IFERROR(IF(BR12=1,INDEX('Curva S'!$C$2:$BJ$301,$I34,BR34),0),0)} -> 0
F87: =F61 -> Equipe_11 | G87: =G61 -> Equipe11 | H87: =SUM(K87:BR87) -> 1 | I87: Lin | K87: {=IFERROR(IF(K13=1,INDEX('Curva S'!$C$2:$BJ$301,$I35,K35),0),0)} -> 0.1 | L87: {=IFERROR(IF(L13=1,INDEX('Curva S'!$C$2:$BJ$301,$I35,L35),0),0)} -> 0.1 | M87: {=IFERROR(IF(M13=1,INDEX('Curva S'!$C$2:$BJ$301,$I35,M35),0),0)} -> 0.1 | N87: {=IFERROR(IF(N13=1,INDEX('Curva S'!$C$2:$BJ$301,$I35,N35),0),0)} -> 0.1 | O87: {=IFERROR(IF(O13=1,INDEX('Curva S'!$C$2:$BJ$301,$I35,O35),0),0)} -> 0.1 | P87: {=IFERROR(IF(P13=1,INDEX('Curva S'!$C$2:$BJ$301,$I35,P35),0),0)} -> 0.1 | Q87: {=IFERROR(IF(Q13=1,INDEX('Curva S'!$C$2:$BJ$301,$I35,Q35),0),0)} -> 0.1 | R87: {=IFERROR(IF(R13=1,INDEX('Curva S'!$C$2:$BJ$301,$I35,R35),0),0)} -> 0.1 | ... BR87: {=IFERROR(IF(BR13=1,INDEX('Curva S'!$C$2:$BJ$301,$I35,BR35),0),0)} -> 0
F88: =F62 -> Equipe_12 | G88: =G62 -> Equipe12 | H88: =SUM(K88:BR88) -> 1 | I88: Lin | K88: {=IFERROR(IF(K14=1,INDEX('Curva S'!$C$2:$BJ$301,$I36,K36),0),0)} -> 0.1 | L88: {=IFERROR(IF(L14=1,INDEX('Curva S'!$C$2:$BJ$301,$I36,L36),0),0)} -> 0.1 | M88: {=IFERROR(IF(M14=1,INDEX('Curva S'!$C$2:$BJ$301,$I36,M36),0),0)} -> 0.1 | N88: {=IFERROR(IF(N14=1,INDEX('Curva S'!$C$2:$BJ$301,$I36,N36),0),0)} -> 0.1 | O88: {=IFERROR(IF(O14=1,INDEX('Curva S'!$C$2:$BJ$301,$I36,O36),0),0)} -> 0.1 | P88: {=IFERROR(IF(P14=1,INDEX('Curva S'!$C$2:$BJ$301,$I36,P36),0),0)} -> 0.1 | Q88: {=IFERROR(IF(Q14=1,INDEX('Curva S'!$C$2:$BJ$301,$I36,Q36),0),0)} -> 0.1 | R88: {=IFERROR(IF(R14=1,INDEX('Curva S'!$C$2:$BJ$301,$I36,R36),0),0)} -> 0.1 | ... BR88: {=IFERROR(IF(BR14=1,INDEX('Curva S'!$C$2:$BJ$301,$I36,BR36),0),0)} -> 0
F89: =F63 -> Equipe_13 | G89: =G63 -> Equipe13 | H89: =SUM(K89:BR89) -> 1 | I89: Lin | K89: {=IFERROR(IF(K15=1,INDEX('Curva S'!$C$2:$BJ$301,$I37,K37),0),0)} -> 0.1 | L89: {=IFERROR(IF(L15=1,INDEX('Curva S'!$C$2:$BJ$301,$I37,L37),0),0)} -> 0.1 | M89: {=IFERROR(IF(M15=1,INDEX('Curva S'!$C$2:$BJ$301,$I37,M37),0),0)} -> 0.1 | N89: {=IFERROR(IF(N15=1,INDEX('Curva S'!$C$2:$BJ$301,$I37,N37),0),0)} -> 0.1 | O89: {=IFERROR(IF(O15=1,INDEX('Curva S'!$C$2:$BJ$301,$I37,O37),0),0)} -> 0.1 | P89: {=IFERROR(IF(P15=1,INDEX('Curva S'!$C$2:$BJ$301,$I37,P37),0),0)} -> 0.1 | Q89: {=IFERROR(IF(Q15=1,INDEX('Curva S'!$C$2:$BJ$301,$I37,Q37),0),0)} -> 0.1 | R89: {=IFERROR(IF(R15=1,INDEX('Curva S'!$C$2:$BJ$301,$I37,R37),0),0)} -> 0.1 | ... BR89: {=IFERROR(IF(BR15=1,INDEX('Curva S'!$C$2:$BJ$301,$I37,BR37),0),0)} -> 0
... F96: =F70 -> Equipe_20 | G96: =G70 -> Equipe20 | H96: =SUM(K96:BR96) -> 1 | I96: Lin | K96: {=IFERROR(IF(K22=1,INDEX('Curva S'!$C$2:$BJ$301,$I44,K44),0),0)} -> 0.1 | L96: {=IFERROR(IF(L22=1,INDEX('Curva S'!$C$2:$BJ$301,$I44,L44),0),0)} -> 0.1 | M96: {=IFERROR(IF(M22=1,INDEX('Curva S'!$C$2:$BJ$301,$I44,M44),0),0)} -> 0.1 | N96: {=IFERROR(IF(N22=1,INDEX('Curva S'!$C$2:$BJ$301,$I44,N44),0),0)} -> 0.1 | O96: {=IFERROR(IF(O22=1,INDEX('Curva S'!$C$2:$BJ$301,$I44,O44),0),0)} -> 0.1 | P96: {=IFERROR(IF(P22=1,INDEX('Curva S'!$C$2:$BJ$301,$I44,P44),0),0)} -> 0.1 | Q96: {=IFERROR(IF(Q22=1,INDEX('Curva S'!$C$2:$BJ$301,$I44,Q44),0),0)} -> 0.1 | R96: {=IFERROR(IF(R22=1,INDEX('Curva S'!$C$2:$BJ$301,$I44,R44),0),0)} -> 0.1 | ... BR96: {=IFERROR(IF(BR22=1,INDEX('Curva S'!$C$2:$BJ$301,$I44,BR44),0),0)} -> 0
F97: Avanço por Mês | K97: =IFERROR(SUM(K77:K96)/SUM($K$77:$BR$96),0) -> 0.1 | L97: =IFERROR(SUM(L77:L96)/SUM($K$77:$BR$96),0) -> 0.1 | M97: =IFERROR(SUM(M77:M96)/SUM($K$77:$BR$96),0) -> 0.1 | N97: =IFERROR(SUM(N77:N96)/SUM($K$77:$BR$96),0) -> 0.1 | O97: =IFERROR(SUM(O77:O96)/SUM($K$77:$BR$96),0) -> 0.1 | P97: =IFERROR(SUM(P77:P96)/SUM($K$77:$BR$96),0) -> 0.1 | Q97: =IFERROR(SUM(Q77:Q96)/SUM($K$77:$BR$96),0) -> 0.1 | R97: =IFERROR(SUM(R77:R96)/SUM($K$77:$BR$96),0) -> 0.1 | ... BR97: =IFERROR(SUM(BR77:BR96)/SUM($K$77:$BR$96),0) -> 0
F98: Avanço Acumulado | K98: =K97 -> 0.1 | L98: =IF(L97>0,L97+LARGE($K98:K98,1),0) -> 0.2 | M98: =IF(M97>0,M97+LARGE($K98:L98,1),0) -> 0.3 | N98: =IF(N97>0,N97+LARGE($K98:M98,1),0) -> 0.4 | O98: =IF(O97>0,O97+LARGE($K98:N98,1),0) -> 0.5 | P98: =IF(P97>0,P97+LARGE($K98:O98,1),0) -> 0.6 | Q98: =IF(Q97>0,Q97+LARGE($K98:P98,1),0) -> 0.7 | R98: =IF(R97>0,R97+LARGE($K98:Q98,1),0) -> 0.8 | S98: =IF(S97>0,S97+LARGE($K98:R98,1),0) -> 0.9 | ... BR98: =IF(BR97>0,BR97+LARGE($K98:BQ98,1),0) -> 0
D102: Etapa 03 | F102: Horas Extras
F104: Banco de Horas
F105: Sigla | G105: Equipe | H105: Quantidade Total de Horas | I105: Média por mês
D106: Orientação de Preenchimento 1. Somente preencher os campos em branco 2. Preencher com as horas totais de banco de horas que serão aplicadas em cada disciplina 3. O valor considerado será aplicado para todos os profissionais inseridos | F106: =F51 -> Equipe_01 | G106: =G51 -> Equipe01 | H106: =SUM(K106:BR106) -> 0 | I106: =IFERROR(SUM(K106:BR106)/COUNTIF(K106:BR106,">0"),0) -> 0
F107: =F52 -> Equipe_02 | G107: =G52 -> Equipe02 | H107: =SUM(K107:BR107) -> 0 | I107: =IFERROR(SUM(K107:BR107)/COUNTIF(K107:BR107,">0"),0) -> 0
F108: =F53 -> Equipe_03 | G108: =G53 -> Equipe03 | H108: =SUM(K108:BR108) -> 0 | I108: =IFERROR(SUM(K108:BR108)/COUNTIF(K108:BR108,">0"),0) -> 0
F109: =F54 -> Equipe_04 | G109: =G54 -> Equipe04 | H109: =SUM(K109:BR109) -> 0 | I109: =IFERROR(SUM(K109:BR109)/COUNTIF(K109:BR109,">0"),0) -> 0
F110: =F55 -> Equipe_05 | G110: =G55 -> Equipe05 | H110: =SUM(K110:BR110) -> 0 | I110: =IFERROR(SUM(K110:BR110)/COUNTIF(K110:BR110,">0"),0) -> 0
F111: =F56 -> Equipe_06 | G111: =G56 -> Equipe06 | H111: =SUM(K111:BR111) -> 0 | I111: =IFERROR(SUM(K111:BR111)/COUNTIF(K111:BR111,">0"),0) -> 0
F112: =F57 -> Equipe_07 | G112: =G57 -> Equipe07 | H112: =SUM(K112:BR112) -> 0 | I112: =IFERROR(SUM(K112:BR112)/COUNTIF(K112:BR112,">0"),0) -> 0
F113: =F58 -> Equipe_08 | G113: =G58 -> Equipe08 | H113: =SUM(K113:BR113) -> 0 | I113: =IFERROR(SUM(K113:BR113)/COUNTIF(K113:BR113,">0"),0) -> 0
F114: =F59 -> Equipe_09 | G114: =G59 -> Equipe09 | H114: =SUM(K114:BR114) -> 0 | I114: =IFERROR(SUM(K114:BR114)/COUNTIF(K114:BR114,">0"),0) -> 0
F115: =F60 -> Equipe_10 | G115: =G60 -> Equipe10 | H115: =SUM(K115:BR115) -> 0 | I115: =IFERROR(SUM(K115:BR115)/COUNTIF(K115:BR115,">0"),0) -> 0
F116: =F61 -> Equipe_11 | G116: =G61 -> Equipe11 | H116: =SUM(K116:BR116) -> 0 | I116: =IFERROR(SUM(K116:BR116)/COUNTIF(K116:BR116,">0"),0) -> 0
F117: =F62 -> Equipe_12 | G117: =G62 -> Equipe12 | H117: =SUM(K117:BR117) -> 0 | I117: =IFERROR(SUM(K117:BR117)/COUNTIF(K117:BR117,">0"),0) -> 0
F118: =F63 -> Equipe_13 | G118: =G63 -> Equipe13 | H118: =SUM(K118:BR118) -> 0 | I118: =IFERROR(SUM(K118:BR118)/COUNTIF(K118:BR118,">0"),0) -> 0
... F125: =F70 -> Equipe_20 | G125: =G70 -> Equipe20 | H125: =SUM(K125:BR125) -> 0 | I125: =IFERROR(SUM(K125:BR125)/COUNTIF(K125:BR125,">0"),0) -> 0
F126: Totais | H126: =SUM(H106:H125) -> 0 | I126: =IFERROR(SUM(K126:BR126)/COUNTIF(K126:BR126,">0"),0) -> 0 | K126: =SUM(K106:K125) -> 0 | L126: =SUM(L106:L125) -> 0 | M126: =SUM(M106:M125) -> 0 | N126: =SUM(N106:N125) -> 0 | O126: =SUM(O106:O125) -> 0 | P126: =SUM(P106:P125) -> 0 | Q126: =SUM(Q106:Q125) -> 0 | R126: =SUM(R106:R125) -> 0 | ... BR126: =SUM(BR106:BR125) -> 0 | BT126: =SUM(BT116:BT125) -> 0
F128: Horas Extra 1
F129: Sigla | G129: Equipe | H129: Quantidade Total de Horas | I129: Média por mês
D130: Orientação de Preenchimento 1. Somente preencher os campos em branco 2. Preencher com as horas totais de hora extra 1 que serão aplicadas em cada disciplina 3. O valor considerado será aplicado para todos os profissionais inseridos | F130: =F51 -> Equipe_01 | G130: =G51 -> Equipe01 | H130: =SUM(K130:BR130) -> 0 | I130: =IFERROR(SUM(K130:BR130)/COUNTIF(K130:BR130,">0"),0) -> 0
F131: =F52 -> Equipe_02 | G131: =G52 -> Equipe02 | H131: =SUM(K131:BR131) -> 0 | I131: =IFERROR(SUM(K131:BR131)/COUNTIF(K131:BR131,">0"),0) -> 0
F132: =F53 -> Equipe_03 | G132: =G53 -> Equipe03 | H132: =SUM(K132:BR132) -> 0 | I132: =IFERROR(SUM(K132:BR132)/COUNTIF(K132:BR132,">0"),0) -> 0
F133: =F54 -> Equipe_04 | G133: =G54 -> Equipe04 | H133: =SUM(K133:BR133) -> 0 | I133: =IFERROR(SUM(K133:BR133)/COUNTIF(K133:BR133,">0"),0) -> 0
F134: =F55 -> Equipe_05 | G134: =G55 -> Equipe05 | H134: =SUM(K134:BR134) -> 0 | I134: =IFERROR(SUM(K134:BR134)/COUNTIF(K134:BR134,">0"),0) -> 0
F135: =F56 -> Equipe_06 | G135: =G56 -> Equipe06 | H135: =SUM(K135:BR135) -> 0 | I135: =IFERROR(SUM(K135:BR135)/COUNTIF(K135:BR135,">0"),0) -> 0
F136: =F57 -> Equipe_07 | G136: =G57 -> Equipe07 | H136: =SUM(K136:BR136) -> 0 | I136: =IFERROR(SUM(K136:BR136)/COUNTIF(K136:BR136,">0"),0) -> 0
F137: =F58 -> Equipe_08 | G137: =G58 -> Equipe08 | H137: =SUM(K137:BR137) -> 0 | I137: =IFERROR(SUM(K137:BR137)/COUNTIF(K137:BR137,">0"),0) -> 0
F138: =F59 -> Equipe_09 | G138: =G59 -> Equipe09 | H138: =SUM(K138:BR138) -> 0 | I138: =IFERROR(SUM(K138:BR138)/COUNTIF(K138:BR138,">0"),0) -> 0
F139: =F60 -> Equipe_10 | G139: =G60 -> Equipe10 | H139: =SUM(K139:BR139) -> 0 | I139: =IFERROR(SUM(K139:BR139)/COUNTIF(K139:BR139,">0"),0) -> 0
F140: =F61 -> Equipe_11 | G140: =G61 -> Equipe11 | H140: =SUM(K140:BR140) -> 0 | I140: =IFERROR(SUM(K140:BR140)/COUNTIF(K140:BR140,">0"),0) -> 0
F141: =F62 -> Equipe_12 | G141: =G62 -> Equipe12 | H141: =SUM(K141:BR141) -> 0 | I141: =IFERROR(SUM(K141:BR141)/COUNTIF(K141:BR141,">0"),0) -> 0
F142: =F63 -> Equipe_13 | G142: =G63 -> Equipe13 | H142: =SUM(K142:BR142) -> 0 | I142: =IFERROR(SUM(K142:BR142)/COUNTIF(K142:BR142,">0"),0) -> 0
... F149: =F70 -> Equipe_20 | G149: =G70 -> Equipe20 | H149: =SUM(K149:BR149) -> 0 | I149: =IFERROR(SUM(K149:BR149)/COUNTIF(K149:BR149,">0"),0) -> 0
F150: Totais | H150: =SUM(H130:H149) -> 0 | I150: =IFERROR(SUM(K150:BR150)/COUNTIF(K150:BR150,">0"),0) -> 0 | K150: =SUM(K130:K149) -> 0 | L150: =SUM(L130:L149) -> 0 | M150: =SUM(M130:M149) -> 0 | N150: =SUM(N130:N149) -> 0 | O150: =SUM(O130:O149) -> 0 | P150: =SUM(P130:P149) -> 0 | Q150: =SUM(Q130:Q149) -> 0 | R150: =SUM(R130:R149) -> 0 | ... BR150: =SUM(BR130:BR149) -> 0 | BT150: =SUM(BT140:BT149) -> 0
...

Sheet Curva S
A1: Curva | B1: Referência | C1: 1 | D1: 2 | E1: 3 | F1: 4 | G1: 5 | H1: 6 | I1: 7 | J1: 8 | K1: 9 | L1: 10 | M1: 11 | N1: 12 | O1: 13 | P1: 14 | Q1: 15 | R1: 16 | S1: 17 | T1: 18 | U1: 19 | V1: 20 | W1: 21 | X1: 22 | Y1: 23 | Z1: 24 | AA1: 25 | AB1: 26 | AC1: 27 | AD1: 28 | AE1: 29 | AF1: 30 | AG1: 31 | AH1: 32 | AI1: 33 | AJ1: 34 | AK1: 35 | AL1: 36 | AM1: 37 | AN1: 38 | AO1: 39 | AP1: 40 | AQ1: 41 | AR1: 42 | AS1: 43 | AT1: 44 | AU1: 45 | AV1: 46 | AW1: 47 | AX1: 48 | AY1: 49 | AZ1: 50 | BA1: 51 | BB1: 52 | BC1: 53 | BD1: 54 | BE1: 55 | BF1: 56 | BG1: 57 | BH1: 58 | BI1: 59 | BJ1: 60
A2: 38.1 | B2: 1 | C2: 1
A3: 38.2 | B3: 2 | C3: 0.51957141 | D3: 0.48042859
A4: 38.3 | B4: 3 | C4: 0.29468265 | D4: 0.44545496 | E4: 0.25986239
A5: 38.4 | B5: 4 | C5: 0.19235396 | D5: 0.32721745 | E5: 0.31727512 | F5: 0.16315347
A6: 38.5 | B6: 5 | C6: 0.13711669 | D6: 0.24566394 | E6: 0.27204459 | F6: 0.23266666 | G6: 0.11250812
A7: 38.6 | B7: 6 | C7: 0.10364578 | D7: 0.19103687 | E7: 0.22488876 | F7: 0.2205662 | G7: 0.17723879 | H7: 0.082623604
A8: 38.7 | B8: 7 | C8: 0.081671151 | D8: 0.15319604 | E8: 0.18668835 | F8: 0.19525033 | G8: 0.18023885 | H8: 0.13949193 | I8: 0.063463336
A9: 38.8 | B9: 8 | C9: 0.06637679 | D9: 0.12597717 | E9: 0.1569242 | F9: 0.17029324 | G9: 0.16788211 | H9: 0.149393 | I9: 0.11274292 | J9: 0.05041055
A10: 38.9 | B10: 9 | C10: 0.055249854 | D10: 0.10573441 | E10: 0.13369839 | F10: 0.14857309 | G10: 0.15215934 | H10: 0.14472253 | I10: 0.1256439 | J10: 0.093120268 | K10: 0.041098228
A11: 38.10 | B11: 10 | C11: 0.046868924 | D11: 0.090247763 | E11: 0.11535506 | F11: 0.13030888 | G11: 0.13679078 | H11: 0.13525381 | I11: 0.12557076 | J11: 0.1070959 | K11: 0.078299161 | L11: 0.034208956
A12: 38.11 | B12: 11 | C12: 0.040377644 | D12: 0.078113737 | E12: 0.10065646 | F12: 0.11506951 | G12: 0.12288754 | H12: 0.1246173 | I12: 0.12032786 | J12: 0.10978176 | K12: 0.092381097 | L12: 0.066826164 | M12: 0.028960921
A13: 38.12 | B13: 12 | C13: 0.035233359 | D13: 0.068412418 | E13: 0.088708187 | F13: 0.10232869 | G13: 0.11066473 | H13: 0.11422403 | I13: 0.11315903 | J13: 0.10740716 | K13: 0.096708919 | L13: 0.080529868 | M13: 0.057757948 | N13: 0.024865657
A14: 38.13 | B14: 13 | C14: 0.031077684 | D14: 0.060520985 | E14: 0.07886492 | F14: 0.091614622 | G14: 0.10002975 | H14: 0.10459777 | I14: 0.10550539 | J14: 0.10277264 | K14: 0.096290574 | L14: 0.085807805 | M14: 0.070851464 | N14: 0.050461576 | O14: 0.021604821
A15: 38.14 | B15: 14 | C15: 0.027665622 | D15: 0.054005528 | E15: 0.070656523 | F15: 0.082539519 | G15: 0.090797779 | H15: 0.09589057 | I15: 0.09801587 | J15: 0.097234464 | K15: 0.093512206 | L15: 0.086726648 | M15: 0.076644418 | N15: 0.062847516 | O15: 0.044499831 | P15: 0.018963504
A16: 38.15 | B16: 15 | C16: 0.024824737 | D16: 0.048556067 | E16: 0.063735883 | F16: 0.074794136 | G16: 0.082771827 | H16: 0.08809798 | I16: 0.090970638 | J16: 0.091470608 | K16: 0.089603343 | L16: 0.085312388 | M16: 0.078475275 | N16: 0.068879 | O16: 0.056152999 | P16: 0.03956289 | Q16: 0.016792228
A17: 38.16 | B17: 16 | C17: 0.022430581 | D17: 0.043946209 | E17: 0.057843008 | F17: 0.068134167 | G17: 0.075771084 | H17: 0.08115312 | I17: 0.084472893 | J17: 0.08582035 | K17: 0.085222607 | L17: 0.082659508 | M17: 0.078066467 | N17: 0.071326534 | O17: 0.062246504 | P17: 0.050496418 | Q17: 0.035426229 | R17: 0.014984321
A18: 38.17 | B18: 17 | C18: 0.020391374 | D18: 0.040007349 | E18: 0.052780383 | F18: 0.06236664 | G18: 0.069638917 | H18: 0.074968638 | I18: 0.078540403 | J18: 0.080447378 | K18: 0.080728584 | L18: 0.079384753 | M18: 0.076383911 | N18: 0.071659948 | O18: 0.065103502 | P18: 0.05653955 | Q18: 0.045672833 | R18: 0.031923886 | S18: 0.013461953
A19: 38.18 | B19: 18 | C19: 0.018638128 | D19: 0.036611726 | E19: 0.048395924 | F19: 0.057338486 | G19: 0.064243076 | H19: 0.06945531 | I19: 0.073150712 | J19: 0.075422377 | K19: 0.076315673 | L19: 0.075843664 | M19: 0.07399371 | N19: 0.070728822 | O19: 0.065984481 | P19: 0.059659415 | Q19: 0.051594892 | R19: 0.041525376 | S19: 0.028931012 | T19: 0.012167217
A20: 38.19 | B20: 19 | C20: 0.017118113 | D20: 0.033661019 | E20: 0.044571041 | F20: 0.052927538 | G20: 0.05947314 | H20: 0.064529865 | I20: 0.06826391 | J20: 0.070766474 | K20: 0.072086003 | L20: 0.072242897 | M20: 0.071236372 | N20: 0.069047048 | O20: 0.065636406 | P20: 0.060942938 | Q20: 0.054873261 | R20: 0.047283078 | S20: 0.037932419 | T20: 0.026352198 | U20: 0.01105628
A21: 38.20 | B21: 20 | C21: 0.015790422 | D21: 0.031078502 | E21: 0.041212174 | F21: 0.049035589 | G21: 0.055237277 | H21: 0.060117787 | I21: 0.063834163 | J21: 0.066474717 | K21: 0.068089017 | L21: 0.068701765 | M21: 0.068319601 | N21: 0.066934207 | O21: 0.064523005 | P21: 0.061047759 | Q21: 0.056450544 | R21: 0.050645356 | S21: 0.043500639 | T21: 0.034798522 | U21: 0.024113501 | V21: 0.010095455
A22: 38.21 | B22: 21 | C22: 0.014622889 | D22: 0.028803553 | E22: 0.038244708 | F22: 0.045583106 | G22: 0.051459125 | H22: 0.056153811 | I22: 0.059815457 | J22: 0.062528989 | K22: 0.064343903 | L22: 0.06528732 | M22: 0.065370564 | N22: 0.06459245 | O22: 0.062940583 | P22: 0.060391149 | Q22: 0.056907122 | R22: 0.052434295 | S22: 0.04689343 | T22: 0.040164209 | U22: 0.032047966 | V22: 0.022156878 | W22: 0.0092584914
A23: 38.22 | B23: 22 | C23: 0.013589922 | D23: 0.026787722 | E23: 0.035608538 | F23: 0.042505198 | G23: 0.048075044 | H23: 0.052581413 | I23: 0.056164343 | J23: 0.058905167 | K23: 0.060852591 | L23: 0.062034954 | M23: 0.06246652 | N23: 0.062150783 | O23: 0.061082046 | P23: 0.059245817 | Q23: 0.05661813 | R23: 0.053163629 | S23: 0.048831738 | T23: 0.043549359 | U23: 0.037206098 | V23: 0.029620066 | W23: 0.020436242 | X23: 0.0085246793
A24: 38.23 | B24: 23 | C24: 0.012670932 | D24: 0.024991889 | E24: 0.033254801 | F24: 0.039748537 | G24: 0.045031821 | H24: 0.049351897 | I24: 0.052841083 | J24: 0.055577086 | K24: 0.057607389 | L24: 0.058960779 | M24: 0.059653325 | N24: 0.059691612 | O24: 0.059074444 | P24: 0.057793546 | Q24: 0.055833476 | R24: 0.053170733 | S24: 0.049771813 | T24: 0.045589584 | U24: 0.040556491 | V24: 0.034570925 | W24: 0.027465729 | X24: 0.018914611 | Y24: 0.0078774981
A25: 38.24 | B25: 24 | C25: 0.011849194 | D25: 0.023384165 | E25: 0.03114343 | F25: 0.037268988 | G25: 0.042284782 | H25: 0.046423405 | I25: 0.049809994 | J25: 0.052518692 | K25: 0.054595519 | L25: 0.056069208 | M25: 0.056956878 | N25: 0.057267157 | O25: 0.057001914 | P25: 0.056157121 | Q25: 0.05472308 | R25: 0.052684082 | S25: 0.050017423 | T25: 0.046691496 | U25: 0.042662373 | V25: 0.037867495 | W25: 0.032213055 | X25: 0.025544893 | Y25: 0.017562024 | Z25: 0.0073036331
A26: 38.25 | B26: 25 | C26: 0.011110997 | D26: 0.021938336 | E26: 0.029241312 | F26: 0.035029786 | G26: 0.039796256 | H26: 0.043759957 | I26: 0.047039358 | J26: 0.049705167 | K26: 0.051801812 | L26: 0.05335765 | M26: 0.054390341 | N26: 0.054909846 | O26: 0.054920138 | P26: 0.05442014 | Q26: 0.053404125 | R26: 0.051861682 | S26: 0.049777243 | T26: 0.047129064 | U26: 0.043887398 | V26: 0.040011276 | W26: 0.035442639 | X26: 0.030094626 | Y26: 0.023824604 | Z26: 0.016353995 | AA26: 0.0067922535
A27: 38.26 | B27: 26 | C27: 0.01044501 | D27: 0.020632674 | E27: 0.027520879 | F27: 0.033000107 | G27: 0.037534334 | H27: 0.041330586 | I27: 0.044501155 | J27: 0.047113467 | K27: 0.049210304 | L27: 0.050819447 | M27: 0.051958752 | N27: 0.052639022 | O27: 0.052865676 | P27: 0.052639713 | Q27: 0.051958203 | R27: 0.050814432 | S27: 0.049197714 | T27: 0.04709286 | U27: 0.044479161 | V27: 0.041328644 | W27: 0.03760306 | X27: 0.033248403 | Y27: 0.028184023 | Z27: 0.022277553 | AA27: 0.015270348 | AB27: 0.0063344733
A28: 38.27 | B28: 27 | C28: 0.0098417924 | D28: 0.019449041 | E28: 0.02595902 | F28: 0.031153956 | G28: 0.035471864 | H28: 0.03910859 | I28: 0.042170704 | J28: 0.044722516 | K28: 0.046805167 | L28: 0.048445727 | M28: 0.049662018 | N28: 0.050465344 | O28: 0.05086211 | P28: 0.050854785 | Q28: 0.050442441 | R28: 0.049620994 | S28: 0.04838319 | T28: 0.046718349 | U28: 0.044611791 | V28: 0.042043856 | W28: 0.038988248 | X28: 0.035409203 | Y28: 0.031256377 | Z28: 0.026454688 | AA28: 0.020880949 | AB28: 0.014294335 | AC28: 0.0059229448
A29: 38.28 | B29: 28 | C29: 0.0092934288 | D29: 0.018372194 | E29: 0.024536243 | F29: 0.029469285 | G29: 0.033585639 | H29: 0.037070885 | I29: 0.040026291 | J29: 0.042513228 | K29: 0.044571221 | L29: 0.046226558 | M29: 0.047496863 | N29: 0.048393707 | O29: 0.048924154 | P29: 0.049091716 | Q29: 0.04889691 | R29: 0.048337555 | S29: 0.047408864 | T29: 0.046103342 | U29: 0.044410476 | V29: 0.042316171 | W29: 0.039801797 | X29: 0.036842621 | Y29: 0.033405154 | Z29: 0.029442362 | AA29: 0.024884178 | AB29: 0.019615653 | AC29: 0.013411956 | AD29: 0.0055515483
A30: 38.29 | B30: 29 | C30: 0.0087932359 | D30: 0.017389237 | E30: 0.023236004 | F30: 0.027927297 | G30: 0.031855734 | H30: 0.035197458 | I30: 0.038048818 | J30: 0.040468418 | K30: 0.042494212 | L30: 0.044151669 | M30: 0.045458112 | N30: 0.046425204 | O30: 0.04706044 | P30: 0.047368066 | Q30: 0.04734965 | R30: 0.047004407 | S30: 0.046329351 | T30: 0.045319286 | U30: 0.043966664 | V30: 0.042261246 | W30: 0.04018955 | X30: 0.037733936 | Y30: 0.034871127 | Z30: 0.031569712 | AA30: 0.027785661 | AB30: 0.023453429 | AC30: 0.018465493 | AD30: 0.012611434 | AE30: 0.0052151521
A31: 38.30 | B31: 30 | C31: 0.0083355377 | D31: 0.016489199 | E31: 0.022044187 | F31: 0.02651188 | G31: 0.030264973 | H31: 0.03347091 | I31: 0.036221472 | J31: 0.038572664 | K31: 0.040560928 | L31: 0.042210899 | M31: 0.043539528 | N31: 0.044558453 | O31: 0.045275426 | P31: 0.045695212 | Q31: 0.045820143 | R31: 0.045650465 | S31: 0.045184524 | T31: 0.044418819 | U31: 0.043347951 | V31: 0.041964437 | W31: 0.040258375 | X31: 0.0382169 | Y31: 0.035823313 | Z31: 0.033055687 | AA31: 0.029884513 | AB31: 0.026268487 | AC31: 0.022146161 | AD31: 0.017416729 | AE31: 0.011882802 | AF31: 0.0049094262
A32: 38.31 | B32: 31 | C32: 0.0079154861 | D32: 0.015662698 | E32: 0.020948685 | F32: 0.025209163 | G32: 0.028798488 | H32: 0.031876066 | I32: 0.034529435 | J32: 0.036812158 | K32: 0.03875923 | L32: 0.040394454 | M32: 0.041734365 | N32: 0.04279049 | O32: 0.043570722 | P32: 0.044080174 | Q32: 0.044321737 | R32: 0.044296423 | S32: 0.044003575 | T32: 0.043440957 | U32: 0.042604761 | V32: 0.041489513 | W32: 0.040087875 | X32: 0.038390315 | Y32: 0.036384572 | Z32: 0.034054839 | AA32: 0.031380435 | AB32: 0.028333593 | AC32: 0.024875493 | AD32: 0.020948408 | AE32: 0.016457622 | AF32: 0.011217574 | AG32: 0.004630696
A33: 38.32 | B33: 32 | C33: 0.0075289187 | D33: 0.014901662 | E33: 0.019939061 | F33: 0.024007148 | G33: 0.027443357 | H33: 0.030399651 | I33: 0.032959624 | J33: 0.035174544 | K33: 0.037078027 | L33: 0.038693057 | M33: 0.040035726 | N33: 0.041117394 | O33: 0.041946001 | P33: 0.042526892 | Q33: 0.04286336 | R33: 0.04295699 | S33: 0.042807874 | T33: 0.042414733 | U33: 0.041774953 | V33: 0.040884555 | W33: 0.03973808 | X33: 0.038328387 | Y33: 0.036646321 | Z33: 0.034680213 | AA33: 0.032415087 | AB33: 0.029831417 | AC33: 0.026903034 | AD33: 0.023593384 | AE33: 0.01984813 | AF33: 0.015578099 | AG33: 0.010608495 | AH33: 0.0043758258
A34: 38.33 | B34: 33 | C34: 0.007172244 | D34: 0.014199122 | E34: 0.019006279 | F34: 0.022895413 | G34: 0.026188305 | H34: 0.029030019 | I34: 0.031500467 | J34: 0.033648767 | K34: 0.035507223 | L34: 0.037098019 | M34: 0.038436794 | N34: 0.039534697 | O34: 0.04039965 | P34: 0.041037142 | Q34: 0.041450753 | R34: 0.041642492 | S34: 0.041613022 | T34: 0.041361789 | U34: 0.040887092 | V34: 0.040186078 | W34: 0.039254693 | X34: 0.038087551 | Y34: 0.036677735 | Z34: 0.035016474 | AA34: 0.03309266 | AB34: 0.030892101 | AC34: 0.028396335 | AD34: 0.025580661 | AE34: 0.022410599 | AF34: 0.018834905 | AG34: 0.01476947 | AH34: 0.010049325 | AI34: 0.0041421263
A35: 38.34 | B35: 34 | C35: 0.0068423486 | D35: 0.013549025 | E35: 0.01814248 | F35: 0.021864869 | G35: 0.025023465 | H35: 0.027756918 | I35: 0.030141708 | J35: 0.032224932 | K35: 0.034037649 | L35: 0.035601269 | M35: 0.03693097 | N35: 0.038037668 | O35: 0.038929218 | P35: 0.039611185 | Q35: 0.040087347 | R35: 0.040360031 | S35: 0.040430331 | T35: 0.040298253 | U35: 0.039962792 | V35: 0.039421961 | W35: 0.038672767 | X35: 0.037711144 | Y35: 0.036531823 | Z35: 0.035128125 | AA35: 0.033491657 | AB35: 0.031611845 | AC35: 0.029475225 | AD35: 0.027064325 | AE35: 0.024355789 | AF35: 0.021317043 | AG35: 0.017899676 | AH35: 0.014024209 | AI35: 0.0095346735 | AJ35: 0.0039272799
A36: 38.35 | B36: 35 | C36: 0.0065365226 | D36: 0.012946099 | E36: 0.017340802 | F36: 0.02090756 | G36: 0.023940166 | H36: 0.0265713 | I36: 0.028874237 | J36: 0.030894174 | K36: 0.032660988 | L36: 0.034195344 | M36: 0.035511964 | N36: 0.036621508 | O36: 0.037531734 | P36: 0.038248231 | Q36: 0.038774911 | R36: 0.039114331 | S36: 0.039267916 | T36: 0.039236101 | U36: 0.039018424 | V36: 0.038613562 | W36: 0.038019344 | X36: 0.037232705 | Y36: 0.036249614 | Z36: 0.03506494 | AA36: 0.033672252 | AB36: 0.032063522 | AC36: 0.030228681 | AD36: 0.02815495 | AE36: 0.025825765 | AF36: 0.023219017 | AG36: 0.020303878 | AH36: 0.017034539 | AI36: 0.013335771 | AJ36: 0.0090598665 | AK36: 0.0037292806
A37: 38.36 | B37: 36 | C37: 0.0062523967 | D37: 0.012385731 | E37: 0.016595232 | F37: 0.020016494 | G37: 0.022930766 | H37: 0.025465158 | I37: 0.027689945 | J37: 0.029648541 | K37: 0.031369701 | L37: 0.032873375 | M37: 0.034173835 | N37: 0.035281476 | O37: 0.036203931 | P37: 0.03694678 | Q37: 0.037514015 | R37: 0.037908362 | S37: 0.038131494 | T37: 0.038184179 | U37: 0.038066377 | V37: 0.037777287 | W37: 0.037315371 | X37: 0.03667834 | Y37: 0.035863109 | Z37: 0.034865713 | AA37: 0.033681173 | AB37: 0.032303307 | AC37: 0.030724438 | AD37: 0.028934976 | AE37: 0.026922774 | AF37: 0.024672118 | AG37: 0.022162043 | AH37: 0.019363333 | AI37: 0.016232572 | AJ37: 0.01269844 | AK37: 0.0086208322 | AL37: 0.0035463846
A38: 38.37 | B38: 37 | C38: 0.0059878921 | D38: 0.011863867 | E38: 0.015900478 | F38: 0.019185508 | G38: 0.021988507 | H38: 0.024431382 | I38: 0.0265816 | J38: 0.028480892 | K38: 0.030156955 | L38: 0.031629052 | M38: 0.032911012 | N38: 0.034012965 | O38: 0.034942402 | P38: 0.035704861 | Q38: 0.036304378 | R38: 0.036743797 | S38: 0.037024979 | T38: 0.037148951 | U38: 0.037116001 | V38: 0.036925737 | W38: 0.036577121 | X38: 0.036068468 | Y38: 0.035397427 | Z38: 0.034560923 | AA38: 0.033555078 | AB38: 0.032375077 | AC38: 0.031014978 | AD38: 0.029467444 | AE38: 0.027723333 | AF38: 0.025771091 | AG38: 0.023595787 | AH38: 0.02117752 | AI38: 0.018488558 | AJ38: 0.015487691 | AK38: 0.012107206 | AL38: 0.0082140103 | AM38: 0.0033770701
A39: 38.38 | B39: 38 | C39: 0.0057411782 | D39: 0.011376935 | E39: 0.015251869 | F39: 0.018409149 | G39: 0.021107395 | H39: 0.023463646 | I39: 0.025542733 | J39: 0.027384805 | K39: 0.029016554 | L39: 0.030456586 | M39: 0.031718302 | N39: 0.032811562 | O39: 0.033743705 | P39: 0.034520206 | Q39: 0.035145116 | R39: 0.035621358 | S39: 0.035950934 | T39: 0.036135069 | U39: 0.036174309 | V39: 0.036068587 | W39: 0.035817258 | X39: 0.035419114 | Y39: 0.034872378 | Z39: 0.03417467 | AA39: 0.033322955 | AB39: 0.032313451 | AC39: 0.03114151 | AD39: 0.029801428 | AE39: 0.028286189 | AF39: 0.026587072 | AG39: 0.024693077 | AH39: 0.022590001 | AI39: 0.020258926 | AJ39: 0.017673493 | AK39: 0.014794534 | AL39: 0.011557664 | AM39: 0.0078362767 | AN39: 0.0032200037
A40: 38.39 | B40: 39 | C40: 0.0055106372 | D40: 0.010921776 | E40: 0.01464527 | F40: 0.017682581 | G40: 0.020282099 | H40: 0.022556305 | I40: 0.02456755 | J40: 0.026354494 | K40: 0.027942876 | L40: 0.029350674 | M40: 0.030590876 | N40: 0.031673072 | O40: 0.032604439 | P40: 0.033390379 | Q40: 0.034034933 | R40: 0.034541072 | S40: 0.034910902 | T40: 0.0351458 | U40: 0.035246516 | V40: 0.035213238 | W40: 0.035045635 | X40: 0.03474288 | Y40: 0.034303648 | Z40: 0.033726107 | AA40: 0.033007876 | AB40: 0.032145973 | AC40: 0.031136726 | AD40: 0.02997565 | AE40: 0.028657273 | AF40: 0.027174882 | AG40: 0.025520154 | AH40: 0.023682603 | AI40: 0.021648707 | AJ40: 0.019400455 | AK40: 0.016912766 | AL40: 0.014148355 | AM40: 0.011045927 | AN40: 0.0074848801 | AO40: 0.0030740135
A41: 38.40 | B41: 40 | C41: 0.0052948346 | D41: 0.010495587 | E41: 0.014077006 | F41: 0.017001497 | G41: 0.019507866 | H41: 0.021704309 | I41: 0.023650849 | J41: 0.02538474 | K41: 0.026930817 | L41: 0.028306461 | M41: 0.029524256 | N41: 0.03059353 | O41: 0.031521296 | P41: 0.032312866 | Q41: 0.032972255 | R41: 0.033502462 | S41: 0.033905663 | T41: 0.034183354 | U41: 0.034336443 | V41: 0.034365322 | W41: 0.034269913 | X41: 0.034049689 | Y41: 0.03370369 | Z41: 0.033230516 | AA41: 0.032628306 | AB41: 0.031894699 | AC41: 0.031026777 | AD41: 0.030020981 | AE41: 0.028872991 | AF41: 0.027577553 | AG41: 0.026128243 | AH41: 0.024517112 | AI41: 0.022734156 | AJ41: 0.020766482 | AK41: 0.018596929 | AL41: 0.016201594 | AM41: 0.013544947 | AN41: 0.010568554 | AO41: 0.00715739 | AP41: 0.0029380655
A42: 38.41 | B42: 41 | C42: 0.0050924951 | D42: 0.010095874 | E42: 0.013543802 | F42: 0.016362056 | G42: 0.018780441 | H42: 0.020903129 | I42: 0.022787948 | J42: 0.024470825 | K42: 0.025975737 | L42: 0.027319496 | M42: 0.0285143 | N42: 0.029569214 | O42: 0.030491088 | P42: 0.031285136 | Q42: 0.031955334 | R42: 0.032504689 | S42: 0.032935428 | T42: 0.033249132 | U42: 0.033446835 | V42: 0.033529092 | W42: 0.033496025 | X42: 0.033347353 | Y42: 0.033082407 | Z42: 0.032700133 | AA42: 0.032199084 | AB42: 0.03157739 | AC42: 0.030832725 | AD42: 0.029962243 | AE42: 0.0289625 | AF42: 0.027829333 | AG42: 0.026557702 | AH42: 0.025141456 | AI42: 0.023572995 | AJ42: 0.021842765 | AK42: 0.019938462 | AL42: 0.017843713 | AM42: 0.015535714 | AN42: 0.012980564 | AO42: 0.010122489 | AP42: 0.0068516522 | AQ42: 0.0028112449
A43: 38.42 | B43: 42 | C43: 0.0049024808 | D43: 0.0097204085 | E43: 0.013042733 | F43: 0.01576082 | G43: 0.018096013 | H43: 0.020148695 | I43: 0.021974627 | J43: 0.023608479 | K43: 0.025073417 | L43: 0.026385708 | M43: 0.027557176 | N43: 0.028596636 | O43: 0.029510769 | P43: 0.030304688 | Q43: 0.030982321 | R43: 0.031546667 | S43: 0.031999984 | T43: 0.032343919 | U43: 0.032579602 | V43: 0.032707718 | W43: 0.03272855 | X43: 0.032642014 | Y43: 0.032447679 | Z43: 0.032144771 | AA43: 0.031732173 | AB43: 0.03120841 | AC43: 0.030571623 | AD43: 0.029819526 | AE43: 0.028949352 | AF43: 0.02795777 | AG43: 0.026840773 | AH43: 0.025593522 | AI43: 0.024210123 | AJ43: 0.022683307 | AK43: 0.02100394 | AL43: 0.019160269 | AM43: 0.017136653 | AN43: 0.014911313 | AO43: 0.012451865 | AP43: 0.0097050131 | AQ43: 0.006565752 | AR43: 0.0026927394
A44: 38.43 | B44: 43 | C44: 0.0047237743 | D44: 0.0093671996 | E44: 0.012571179 | F44: 0.015194705 | G44: 0.017451155 | H44: 0.019437341 | I44: 0.021207073 | J44: 0.022793831 | K44: 0.024220011 | L44: 0.02550136 | M44: 0.026649345 | N44: 0.027672535 | O44: 0.028577445 | P44: 0.029369083 | Q44: 0.030051321 | R44: 0.030627138 | S44: 0.031098811 | T44: 0.031468031 | U44: 0.031736005 | V44: 0.03190352 | W44: 0.031970988 | X44: 0.031938488 | Y44: 0.031805778 | Z44: 0.031572314 | AA44: 0.031237247 | AB44: 0.030799419 | AC44: 0.030257345 | AD44: 0.029609185 | AE44: 0.028852702 | AF44: 0.027985211 | AG44: 0.027003491 | AH44: 0.025903686 | AI44: 0.024681148 | AJ44: 0.023330229 | AK44: 0.021843966 | AL44: 0.020213623 | AM44: 0.018427957 | AN44: 0.016472016 | AO44: 0.014324974 | AP44: 0.011955862 | AQ44: 0.0093136966 | AR44: 0.0062979828 | AS44: 0.0025818263
